Workbook

Sheet Cover
A1: شركة فليكسي للتأجير التمويلي
A4: دراسة الجدوى والنموذج المالي المتكامل - Year 1 to Year 5
B8: نطاق النموذج
B9: قوائم مالية سنوية لخمس سنوات
B10: خطة منح شهرية وربع سنوية
B11: تمويل وسيولة وCAR وLCR وNSFR
B12: NPV وIRR وARR والاسترداد وWACC وPI والتعادل
B13: حساسية وسيناريوهات ومؤشرات مالية
B14: هيكل وظيفي ووظائف رقابية
B17: جميع المبالغ بالجنيه المصري. الافتراضات الصفراء قابلة للتعديل، والمعادلات مترابطة بين القوائم والجداول الرقابية. أي مدخل غير مؤكد موصوف صراحة كافتراض.
B22: Version
B23: Final Submission Version
A24: للاطلاع على فهرس تفصيلي بكل ورقة في هذا الملف وما تعرضه ومنهجيتها، مع رابط مباشر لكل ورقة، انظر ورقة "دليل الملف". / For a detailed guide to every sheet in this file, what it shows, and its methodology, with a direct link to each sheet, see the "دليل الملف" (File Guide) sheet.

Sheet دليل الملف
A1: دليل الملف - كل الأوراق ومحتواها
A3: الترتيب | B3: اسم الورقة | C3: ماذا تعرض ومنهجيتها | D3: Navigation
A4: 1 | B4: Cover | C4: صفحة تعريفية بالشركة ونطاق النموذج - لا حسابات، مقدمة فقط. | D4: =IFERROR(HYPERLINK("#'Cover'!A1","Open →"),"Open →") -> Open →
A5: 2 | B5: Assumptions | C5: يجمع الافتراضات الرئيسية: التكاليف، الأسعار، الآجال، رأس المال، والافتراضات الرقابية. معظم محركات النموذج ترتبط بهذه الورقة، مع بقاء بعض بنود Year 1-Year 2 كمدخلات خطة إدارة معتمدة موضحة صراحة في أوراقها. | D5: =IFERROR(HYPERLINK("#'Assumptions'!A1","Open →"),"Open →") -> Open →
A6: 3 | B6: Capital | C6: جدول تحصيل رأس المال من المساهمين الأربعة على دفعات ربع سنوية تبدأ قبل Year 1 وتستكمل خلال Year 2 حتى بلوغ 75 مليون جنيه. | D6: =IFERROR(HYPERLINK("#'Capital'!A1","Open →"),"Open →") -> Open →
A7: 4 | B7: Products | C7: القطاعات والمنتجات التي تستهدفها فليكسي في نشاط التأجير التمويلي. | D7: =IFERROR(HYPERLINK("#'Products'!A1","Open →"),"Open →") -> Open →
A8: 5 | B8: Staff | C8: الهيكل الوظيفي وتكلفة العاملين سنويا حتى نهاية Year 5، شاملا وظيفة مسؤول مكافحة غسل الأموال وتمويل الإرهاب. | D8: =IFERROR(HYPERLINK("#'Staff'!A1","Open →"),"Open →") -> Open →
A9: 6 | B9: Opex | C9: تفصيل المصروفات الإدارية والعمومية بندا ببند (تقنية، تسويق، إيجارات). | D9: =IFERROR(HYPERLINK("#'Opex'!A1","Open →"),"Open →") -> Open →
A10: 7 | B10: Originations | C10: خطة المنح الشهرية والربع سنوية على 60 شهرا، موزعة من الحجم السنوي في Assumptions وفق التوزيع الموسمي المعتمد، مع تجميع سنوي واختبارات ربط. | D10: =IFERROR(HYPERLINK("#'Originations'!A1","Open →"),"Open →") -> Open →
A11: 8 | B11: Cohort Principal | C11: جدول سنوي لتطور أصل المحفظة: رصيد أول السنة + الأصل الممول من المنح - تحصيل/استنفاد الأصل = رصيد آخر السنة، مع اختبار ربط. | D11: =IFERROR(HYPERLINK("#'Cohort Principal'!A1","Open →"),"Open →") -> Open →
A12: 9 | B12: Cohort Interest | C12: جدول سنوي لعوائد التأجير: Year 1-Year 2 مدخلات خطة إدارة معتمدة لعدم توافر جدول EIR/عقود شهري مستقل؛ Year 3-Year 5 تحسب من متوسط المحفظة × العائد السنوي. | D12: =IFERROR(HYPERLINK("#'Cohort Interest'!A1","Open →"),"Open →") -> Open →
A13: 10 | B13: Cohort Fees | C13: جدول سنوي لرسوم الخدمات: المنح × نسبة الرسوم المعتمدة (Year 1=5%، Year 2=7%، ومن Year 3=6%)، مع إظهار دعم/خدمات مساندة منفصلة عند وجودها. | D13: =IFERROR(HYPERLINK("#'Cohort Fees'!A1","Open →"),"Open →") -> Open →
A14: 11 | B14: Monthly Model | C14: تجميع شهري على 60 شهرا للتدفقات والنقدية والدين والرافعة. يستخدم كأساس لاختبارات التمويل والرافعة الشهرية، كما يغذي مؤشرات السيولة التخطيطية التي تستكمل ببيانات الآجال التعاقدية في Funding & Liquidity. | D14: =IFERROR(HYPERLINK("#'Monthly Model'!A1","Open →"),"Open →") -> Open →
A15: 12 | B15: Income Statement | C15: قائمة الدخل التقديرية لخمس سنوات، متضمنة جدول تسوية ضريبية كاملا (ترحيل خسارة Year 1 مقابل ربح Year 2). | D15: =IFERROR(HYPERLINK("#'Income Statement'!A1","Open →"),"Open →") -> Open →
A16: 13 | B16: Balance Sheet | C16: قائمة المركز المالي التقديرية لخمس سنوات، مع فحص توازن آلي يجب أن يساوي صفرا كل سنة. | D16: =IFERROR(HYPERLINK("#'Balance Sheet'!A1","Open →"),"Open →") -> Open →
A17: 14 | B17: Cash Flow | C17: قائمة التدفقات النقدية (تشغيلي/استثماري/تمويلي)، مع ربط آلي للرصيد الختامي بالميزانية. | D17: =IFERROR(HYPERLINK("#'Cash Flow'!A1","Open →"),"Open →") -> Open →
A18: 15 | B18: Investments | C18: الخطة الاستثمارية لخمس سنوات على ست قنوات (منصة التأجير، الأمن السيبراني، معدات، إلخ). | D18: =IFERROR(HYPERLINK("#'Investments'!A1","Open →"),"Open →") -> Open →
A19: 16 | B19: Feasibility | C19: مؤشرات الجدوى: NPV، IRR، فترة الاسترداد، ARR، تكلفة رأس المال WACC، ودليل الربحية PI. | D19: =IFERROR(HYPERLINK("#'Feasibility'!A1","Open →"),"Open →") -> Open →
A20: 17 | B20: Ratios | C20: النسب المالية: العائد على الأصول ROA، العائد على حقوق الملكية ROE، العائد على الاستثمار ROI، ومؤشرات سيولة تكميلية. | D20: =IFERROR(HYPERLINK("#'Ratios'!A1","Open →"),"Open →") -> Open →
A21: 18 | B21: Scenarios | C21: ثلاثة سيناريوهات تجارية عامة (أفضل/أساسي/أسوأ) لأثر التشغيل على الربحية - سيناريوهات نشاط عامة، غير مرتبطة بسقف الرافعة الرقابي (راجع Scenario - Slower Year 2 لهذا الغرض). | D21: =IFERROR(HYPERLINK("#'Scenarios'!A1","Open →"),"Open →") -> Open →
A22: 19 | B22: Sensitivity | C22: حساسية صافي ربح Year 5 لتغير عائد العميل وحجم المنح معا. | D22: =IFERROR(HYPERLINK("#'Sensitivity'!A1","Open →"),"Open →") -> Open →
A23: 20 | B23: Break Even | C23: نقطة تعادل حجم المحفظة والمنح المطلوبين سنويا، وهامش الأمان الفعلي. | D23: =IFERROR(HYPERLINK("#'Break Even'!A1","Open →"),"Open →") -> Open →
A24: 21 | B24: Compliance | C24: مصفوفة تقابل كل بند من الـ14 بندا الأساسية في خطاب الهيئة بمكان استيفائه في الملف - للمراجع السريع قبل التقديم. | D24: =IFERROR(HYPERLINK("#'Compliance'!A1","Open →"),"Open →") -> Open →
A25: 22 | B25: Checks | C25: اختبارات ذاتية للتأكد من سلامة الأرقام حسابيا (توازن الميزانية، تطابق التدفقات، تسوية الدين) - أداة مراجعة داخلية للنموذج، وليست موجهة للهيئة. | D25: =IFERROR(HYPERLINK("#'Checks'!A1","Open →"),"Open →") -> Open →
A26: 23 | B26: Sources | C26: سجل بكل افتراض غير مؤكد بعد ومصدره ومكان استخدامه، بما في ذلك روابط النصوص الرقابية الرسمية (قرار 268/2023 وقرار 137/2025). | D26: =IFERROR(HYPERLINK("#'Sources'!A1","Open →"),"Open →") -> Open →
A27: 24 | B27: Formula Map | C27: دليل مختصر يوضح في أي ورقة وأي صف تحسب كل نسبة أو مؤشر رئيسي. | D27: =IFERROR(HYPERLINK("#'Formula Map'!A1","Open →"),"Open →") -> Open →
A28: 25 | B28: Regulatory Capital Plan | C28: المصدر الأساسي لحساب القاعدة الرأسمالية، الأصول المرجحة بالمخاطر، CAR، وسقف الرافعة (4×/9×) بالتفصيل - كل الأوراق الأخرى التي تعرض هذه الأرقام (Basel III، Compliance، Checks) تسحبها من هنا. | D28: =IFERROR(HYPERLINK("#'Regulatory Capital Plan'!A1","Open →"),"Open →") -> Open →
A29: 26 | B29: Funding & Liquidity | C29: تفصيل مصادر التمويل وتكلفتها، اختبار الرافعة الشهري خلال Year 2، وسلمي LCR (30 يوما) وNSFR (حسب الأجل المتبقي) التفصيليين. | D29: =IFERROR(HYPERLINK("#'Funding & Liquidity'!A1","Open →"),"Open →") -> Open →
A30: 27 | B30: Scenario - Slower Year 2 | C30: أداة إدارة عملية لفجوة سقف الرافعة عبر تباطؤ نمو Year 2 (تخفيض معدل المنح والتمويل معا) - وليس سيناريو تجاري عام. | D30: =IFERROR(HYPERLINK("#'Scenario - Slower 2028'!A1","Open →"),"Open →") -> Open →
A31: 28 | B31: Scenario - Standby Capital | C31: أداة إدارة عملية لفجوة سقف الرافعة عبر ضخ رأس مال احتياطي من المساهمين، بحساب الحد الأدنى الكافي تلقائيا. | D31: =IFERROR(HYPERLINK("#'Scenario - Standby Capital'!A1","Open →"),"Open →") -> Open →
A32: 29 | B32: رد الملاحظات | C32: رد مباشر ومرقم على كل ملاحظة وردت في خطاب الهيئة، مع رابط لكل رد يوصل إلى الورقة التي تثبته فعليا. | D32: =IFERROR(HYPERLINK("#'رد الملاحظات'!A1","Open →"),"Open →") -> Open →
A33: 30 | B33: Basel III | C33: يجمع أرقام كفاية رأس المال (من Regulatory Capital Plan) ونسب السيولة (من Funding & Liquidity) في عرض واحد متكامل لبازل 3، ويضيف تفاصيل غير موجودة في مكان آخر: الانكشافات غير المرجحة، تصنيف مؤشر الأعمال، جدول تركز العملاء، وحساسية CAR لمعامل مخاطر التشغيل. ملاحظة: نحو ثلث صفوف الجزء الأول من هذه الورقة نسخة مباشرة من Regulatory Capital Plan بغرض تجميعها في عرض واحد يخص بازل 3 تحديدا. | D33: =IFERROR(HYPERLINK("#'Basel III'!A1","Open →"),"Open →") -> Open →
A34: 31 | B34: Regulatory Data Requirements | C34: قائمة بكل مستند أو بيان مطلوب من الإدارة ولم يتوفر بعد، مع الجهة المسؤولة والموعد المستهدف وأثر عدم التوفر. | D34: =IFERROR(HYPERLINK("#'Regulatory Data Requirements'!A1","Open →"),"Open →") -> Open →
A35: 32 | B35: جاهزية التقديم | C35: لوحة ملخصة نهائية بكل نتائج الالتزام الرئيسية (الرافعة، CAR، LCR، NSFR)، وقرار صريح بجاهزية الملف للتقديم كدراسة جدوى وليس كإقرار امتثال فعلي. | D35: =IFERROR(HYPERLINK("#'جاهزية التقديم'!A1","Open →"),"Open →") -> Open →

Sheet Assumptions
A1: Flexy - الافتراضات الرئيسية للنموذج المالي
A3: البند | B3: Year 1 | C3: Year 2 | D3: Year 3 | E3: Year 4 | F3: Year 5
A4: حجم المنح السنوي | B4: 27750000 | C4: 527500000 | D4: 700000000 | E4: 1350000000 | F4: 2500000000
A5: خطة التشغيل السنوية | B5: =B4 -> 27750000 | C5: =C4 -> 527500000 | D5: =D4 -> 700000000 | E5: =E4 -> 1350000000 | F5: =F4 -> 2500000000
A6: العائد السنوي الاسمي على رصيد العميل | B6: 0.34 | C6: 0.32 | D6: 0.3 | E6: 0.28 | F6: 0.26
A7: سعر مرجعي تقديري | B7: 0.21 | C7: 0.19 | D7: 0.17 | E7: 0.15 | F7: 0.14
A8: هامش البنك فوق السعر المرجعي | B8: 0.03 | C8: 0.03 | D8: 0.03 | E8: 0.03 | F8: 0.03
A9: تكلفة الاقتراض السنوية | B9: 0.24 | C9: 0.22 | D9: 0.2 | E9: 0.18 | F9: 0.17
A10: متوسط قيمة العقد | B10: 150000 | C10: 315868.26 | D10: 888461.54 | E10: 1100000 | F10: 1350000
A11: الإنفاق الرأسمالي | B11: 4302000 | C11: 500000 | D11: 1000000 | E11: 1500000 | F11: 2000000
A12: عدد مكاتب التوقيع وخدمات الأصول | B12: 8 | C12: 8 | D12: 8 | E12: 15 | F12: 22
A13: الحد الأدنى للسيولة | B13: 2500000 | C13: 25000000 | D13: 25000000 | E13: 50000000 | F13: 100000000
A15: افتراضات ثابتة وقانونية
A16: Establishment Phase | B16: 46296 | C16: مؤكد من الإدارة
A17: Start of Operations Phase | B17: 46388 | C17: ترخيص مبدئي/بدء النشاط
A18: First Contract Phase | B18: 46419 | C18: خلال شهر من ترخيص البدء
A19: Target Final License Phase | B19: 47026 | C19: Management planning assumption: capital completion and target final license during Year 2
A20: رأس المال المرخص | B20: 75000000 | C20: مؤكد من الإدارة
A21: رأس المال المصدر والمدفوع عند البداية | B21: 15000000 | C21: مؤكد من الإدارة
A22: القيمة الاسمية المقترحة للسهم | B22: 1 | C22: افتراض قانوني لحين اعتماد عقد التأسيس
A23: إجمالي الأسهم عند استكمال 75 مليون | B23: =C91/$B$22 -> 75000000 | C23: رأس المال ÷ القيمة الاسمية
A24: صافي فاقد ائتماني على الأقساط المستحقة - افتراض تخطيطي | C24: 4x قبل الترخيص النهائي و9x بعده
A25: نسبة مقدم العميل / الجزء غير الممول من قيمة الأصل | B25: 0.15 | C25: افتراض تشغيلي مستخدم في احتساب صافي أصل محفظة التأجير؛ ليس نسبة مخصص خسائر ائتمانية
A26: نسبة الرسوم الإدارية حسب السنة | B26: 0.05 | C26: 0.07 | D26: 0.06 | E26: 0.06 | F26: 0.06
A27: نسبة الاعتراف بالرسوم عند المنح - سياسة محاسبية مستهدفة (غير مطبقة في القوائم المقفلة حاليا) | B27: 0.7 | C27: مقابل خدمات منفصلة - تخضع لاعتماد المراجع
A28: نسبة الرسوم المؤجلة - سياسة محاسبية مستهدفة (غير مطبقة في القوائم المقفلة حاليا) | B28: =1-B27 -> 0.3 | C28: تستهلك على مدة العقد
A29: متوسط مدة العقد - شهر | B29: 30 | C29: الغالبية 24-36 شهر
A30: صافي فاقد ائتماني على الأقساط المستحقة | B30: 0.02 | C30: افتراض تحفظي قابل للتعديل
A31: نسبة مخصص الخسائر الائتمانية التخطيطي من إجمالي المحفظة الختامية (ليس نموذج EAS 47 كامل) | B31: 0.03 | C31: افتراض دراسة جدوى؛ إلى حين بناء نموذج EAS 47 ببيانات PD/LGD/EAD والمراحل الائتمانية
A32: نسبة سداد أصل تمويل البنك من تحصيلات الأصل | B32: 0.75 | C32: Cash sweep
A33: ضريبة الدخل | B33: 0.225 | C33: ضريبة الشركات
A34: زيادة الرواتب السنوية | B34: 0.2 | C34: طبقا لجدول الهيكل الوظيفي المرجعي
A35: زيادة المصروفات السنوية | B35: 0.1 | C35: تقدير إداري
A36: معدل الحوافز المتغيرة الضمني من موازنة العاملين المعتمدة | B36: =IFERROR(Staff!H10/SUM(Staff!H4:H9,Staff!H11:H20),0) -> 0 | C36: =IFERROR(Staff!I10/SUM(Staff!I4:I9,Staff!I11:I20),0) -> 0.16662508 | D36: =IFERROR(Staff!J10/SUM(Staff!J4:J9,Staff!J11:J20),0) -> 0.36284717 | E36: =IFERROR(Staff!K10/SUM(Staff!K4:K9,Staff!K11:K20),0) -> 0.3 | F36: =IFERROR(Staff!L10/SUM(Staff!L4:L9,Staff!L11:L20),0) -> 0.3
A37: معدل حافز إنتاج مرجعي على منح الشهر السابق (مرجع تشغيلي؛ غير مستخدم كمعامل موازنة سنوي) | B37: 0.005 | C37: مرتبطة بالإنتاج
A38: نسبة الرسوم المتغيرة/بوابات الدفع من التحصيلات | B38: 0.002 | C38: تقدير
A39: تكلفة حقوق الملكية | B39: 0.25 | C39: معدل خصم اسمي بالجنيه - افتراض تقييم
A40: مضاعف الربحية النهائي | B40: 8 | C40: حالة أساسية للتقييم عند نهاية Year 5
A41: نسبة الاحتياطي القانوني من الربح | B41: 0.05 | C41: حتى 50% من رأس المال
A42: أقصى رصيد للاحتياطي القانوني | B42: 0.5 | C42: من رأس المال المصدر
A43: نسبة الاعتراف بعوائد العقود نقديا | B43: 0.98 | C43: تعكس التعثر/عدم الاستحقاق
A44: الوحدات | B44: جنيه مصري | C44: الأرقام بالجنيه ما لم يذكر خلاف ذلك
A45: السقف الداخلي للرافعة المالية | B45: 3 | C45: 3.5 | D45: 7.5 | E45: 7.75 | F45: 8
A46: دليل الألوان | B46: مدخلات قابلة للتعديل | C46: معادلات | D46: روابط داخل النموذج | E46: تنبيه/مطلوب اعتماد
B47: أزرق | C47: أسود | D47: أخضر | E47: خلفية صفراء
A48: قاعدة الاستخدام | B48: تعديل الخلايا الزرقاء فقط | C48: لا تستبدل المعادلات | D48: تتبع إلى جداول أخرى | E48: تحتاج اعتمادا نهائيا
A49: الحالة المختارة | B49: Base
A50: إطار رقابي وتمويلي
A51: السقف التنظيمي الساري وفق قرار 268/2023: 4x من صافي حقوق الملكية طوال Year 1 وYear 2 بالكامل (المرحلة المؤقتة قبل الترخيص النهائي)، و9x من القاعدة الرأسمالية التنظيمية بدءا من Year 3 فقط بافتراض صدور الترخيص النهائي فعليا وفق خطة الادارة | B51: 4 | C51: 4 | D51: 9 | E51: 9 | F51: 9
A52: هامش الأمان عن سقف الرافعة | B52: 0.75 | C52: 0.75 | D52: 0.75 | E52: 0.75 | F52: 0.75
A53: الحد المخطط للتسهيلات البنكية | B53: 0 | C53: 420000000 | D53: 850000000 | E53: 1600000000 | F53: 3000000000
A54: زيادة حقوق ملكية خارج رأس المال المدفوع | B54: 0 | C54: 0 | D54: 0 | E54: 0 | F54: 0
A55: Tier 2 ضمن القاعدة الرأسمالية | B55: 0 | C55: 0 | D55: 0 | E55: 0 | F55: 0
A56: استبعادات رقابية من القاعدة الرأسمالية | B56: 0 | C56: 0 | D56: 0 | E56: 0 | F56: 0
A57: الحد الأدنى لكفاية رأس المال | B57: 0.12 | C57: 0.12 | D57: 0.12 | E57: 0.12 | F57: 0.12
A58: الحد الأدنى لتغطية السيولة | B58: 1 | C58: 1 | D58: 1 | E58: 1 | F58: 1
A59: الحد الأدنى لصافي التمويل المستقر | B59: 1 | C59: 1 | D59: 1 | E59: 1 | F59: 1
A60: حد تركز العميل الواحد | B60: 0.3 | C60: 0.3 | D60: 0.3 | E60: 0.3 | F60: 0.3
A61: معامل مؤشر الأعمال لمخاطر التشغيل | B61: 0.18 | C61: 0.18 | D61: 0.18 | E61: 0.18 | F61: 0.18
A62: نسبة التمويل البنكي المستقر المرجحة | B62: 0.9 | C62: 0.9 | D62: 0.95 | E62: 0.95 | F62: 0.95
A63: عامل التمويل المستقر المطلوب - مؤشر تخطيطي | B63: 0.8 | C63: 0.8 | D63: 0.8 | E63: 0.8 | F63: 0.8
A64: عدد العاملين بنهاية السنة | B64: =Staff!C21 -> 36 | C64: =Staff!D21 -> 36 | D64: =Staff!E21 -> 36 | E64: =Staff!F21 -> 36 | F64: =Staff!G21 -> 36
A65: معامل تواجد القوة العاملة خلال السنة | B65: 1 | C65: 1 | D65: 1 | E65: 1 | F65: 1
A66: معامل مواءمة موازنة G&A المقفلة (Year 1-Year 2 فقط؛ من Year 3 = 1.0) | B66: =IFERROR(Opex!H20/(SUMPRODUCT(Opex!$B$4:$B$18,Opex!$C$4:$C$18)*12),1) -> 0.64615385 | C66: =IFERROR(Opex!I20/(SUMPRODUCT(Opex!$B$4:$B$18,Opex!$D$4:$D$18)*12*(1+$B$35)),1) -> 0.98181818 | D66: 1 | E66: 1 | F66: 1
A67: منهج المخصص التخطيطي | B67: الرصيد الختامي للمخصص = 3% من إجمالي المحفظة الختامية؛ مصروف الخسائر في قائمة الدخل = حركة رصيد المخصص، مع افتراض صفر شطب وصفر استردادات في التوقعات الحالية. هذا ليس نموذج EAS 47 كامل.
A68: ملاحظات الإفصاح
A69: تعريف القاعدة الرأسمالية | B69: المستخدم حاليا تقريب لحقوق الملكية المحاسبية المعدلة، وليس حسابا نهائيا للقاعدة الرأسمالية الرقابية.
A70: مخاطر التشغيل | B70: RWA التشغيلي = مؤشر الأعمال × معامل BI × مضاعف الخسارة الداخلية × 12.5. يستخدم النموذج معامل BI التخطيطي المشتق من شريحة BI في Basel III (حاليا 12%) وILM=1 مؤقتا، مع حساسية 15% و18% إلى أن تحدد الهيئة المعامل وتتوافر بيانات خسائر فعلية.
A71: التمويل البنكي | B71: حدود التسهيلات وآجالها وتكلفتها افتراضات تخطيطية لحين استلام عروض ملزمة من البنوك. السحب الفعلي مرتبط باحتياج السيولة وبحدود الرافعة وكفاية رأس المال.
A72: شرط مصدر التمويل خلال الترخيص المبدئي | B72: لا يتضمن النموذج أي مبالغ استثمار رأسمالي إضافية. وبصورة مستقلة عن الحسابات، يتطلب البند (9) من المادة الثالثة بالقرار 268 لسنة 2023 استيفاء مستندات اعتماد مصدر التمويل المقرر للشركات الناشئة قبل الترخيص؛ ويظل ذلك إجراء قانونيا مطلوب الإقفال مع المستشار والهيئة.
A73: حالة المؤشرات الرقابية | B73: مؤشرات تخطيطية أولية؛ أي نقص في CAR أو LCR أو NSFR يظهر كفجوة يجب إقفالها، وليس كنجاح مشروط.
A74: سداد التمويل البنكي المحسوب | B74: ='Funding & Liquidity'!B12 -> 0 | C74: ='Funding & Liquidity'!C12 -> 71677563 | D74: ='Funding & Liquidity'!D12 -> 292500000 | E74: ='Funding & Liquidity'!E12 -> 615000000 | F74: ='Funding & Liquidity'!F12 -> 1162500000
A75: مدخلات الخطة السنوية والقوائم المالية
A76: المنح السنوي | B76: =B4 -> 27750000 | C76: =C4 -> 527500000 | D76: =D4 -> 700000000 | E76: =E4 -> 1350000000 | F76: =F4 -> 2500000000
A77: عدد العقود | B77: 185 | C77: 1670 | D77: 788 | E77: 1227 | F77: 1852
A78: تحصيلات العملاء | B78: 7077695.9 | C78: 95570084 | D78: 390000000 | E78: 820000000 | F78: 1550000000
A79: رصيد محفظة التأجير الإجمالي الختامي | B79: 20672304 | C79: 4.5260222e+08 | D79: =C79*(1-12/$B$29)+D76*(1-$B$25) -> 8.6656133e+08 | E79: =D79*(1-12/$B$29)+E76*(1-$B$25) -> 1.6674368e+09 | F79: =E79*(1-12/$B$29)+F76*(1-$B$25) -> 3.1254621e+09
A80: عوائد التأجير | B80: ='Cohort Interest'!B8 -> 3538848 | C80: ='Cohort Interest'!C8 -> 45873640 | D80: ='Cohort Interest'!D8 -> 1.9787453e+08 | E80: ='Cohort Interest'!E8 -> 3.5475974e+08 | F80: ='Cohort Interest'!F8 -> 6.2307685e+08
A81: رسوم الخدمات الإدارية | B81: =B76*B26 -> 1387500 | C81: =C76*C26 -> 36925000 | D81: =D76*D26 -> 42000000 | E81: =E76*E26 -> 81000000 | F81: =F76*F26 -> 150000000
A82: دعم تشغيلي / إيرادات خدمات مساندة أخرى | B82: 3118262.4 | C82: 0 | D82: =D76*0.8% -> 5600000 | E82: =E76*0.8% -> 10800000 | F82: =F76*0.8% -> 20000000
A83: تكلفة التمويل البنكي | B83: =SUMIFS('Monthly Model'!$B$41:$BI$41,'Monthly Model'!$B$4:$BI$4,2027) -> 0 | C83: =SUMIFS('Monthly Model'!$B$41:$BI$41,'Monthly Model'!$B$4:$BI$4,2028) -> 37240500 | D83: =SUMIFS('Monthly Model'!$B$41:$BI$41,'Monthly Model'!$B$4:$BI$4,2029) -> 102822500 | E83: =SUMIFS('Monthly Model'!$B$41:$BI$41,'Monthly Model'!$B$4:$BI$4,2030) -> 176827500 | F83: =SUMIFS('Monthly Model'!$B$41:$BI$41,'Monthly Model'!$B$4:$BI$4,2031) -> 325335375
A84: مصروف الخسائر الائتمانية / حركة المخصص التخطيطي | B84: =B79*$B$31 -> 620169.12 | C84: =C79*$B$31-B79*$B$31 -> 12957897 | D84: =D79*$B$31-C79*$B$31 -> 12418773 | E84: =E79*$B$31-D79*$B$31 -> 24026264 | F84: =F79*$B$31-E79*$B$31 -> 43740758
A85: تكلفة العاملين الشاملة | B85: =Staff!H21 -> 11156112 | C85: =Staff!I21 -> 15618000 | D85: =Staff!J21 -> 21893869 | E85: =Staff!K21 -> 25061090 | F85: =Staff!L21 -> 30073308
A86: المصروفات الإدارية والتشغيلية | B86: 4435200 | C86: 7413120 | D86: =Opex!J19 -> 8305440 | E86: =Opex!K19 -> 12769614 | F86: =Opex!L19 -> 18043568
A87: الإهلاك والاستهلاك | B87: 0 | C87: 0 | D87: 1000000 | E87: 1500000 | F87: 2000000
A88: ضريبة الدخل | B88: ='Income Statement'!B46 -> 0 | C88: ='Income Statement'!C46 -> 315506.7 | D88: ='Income Statement'!D46 -> 22282639 | E88: ='Income Statement'!E46 -> 46434436 | F88: ='Income Statement'!F46 -> 84123865
A89: صافي الربح | B89: =B80+B81+B82-B83-B84-B85-B86-B87-B88 -> -8166870.8 | C89: =C80+C81+C82-C83-C84-C85-C86-C87-C88 -> 9253616.1 | D89: =D80+D81+D82-D83-D84-D85-D86-D87-D88 -> 76751312 | E89: =E80+E81+E82-E83-E84-E85-E86-E87-E88 -> 1.5994083e+08 | F89: =F80+F81+F82-F83-F84-F85-F86-F87-F88 -> 2.8975998e+08
A90: رصيد التمويل البنكي الختامي | B90: 0 | C90: 370000000 | D90: 685000000 | E90: 1335000000 | F90: 2600000000
A91: رأس المال المصدر والمدفوع | B91: 30000000 | C91: 75000000 | D91: 75000000 | E91: 75000000 | F91: 75000000
A92: الأرباح/(الخسائر) التراكمية | B92: =B89 -> -8166870.8 | C92: =B92+C89 -> 1086745.3 | D92: =C92+D89 -> 77838057 | E92: =D92+E89 -> 2.3777889e+08 | F92: =E92+F89 -> 5.2753887e+08
A93: الاحتياطي القانوني التراكمي | B93: =0 -> 0 | C93: =MAX(0,C89*$B$41) -> 462680.8 | D93: =C93+MAX(0,D89*$B$41) -> 4300246.4 | E93: =D93+MAX(0,E89*$B$41) -> 12297288 | F93: =E93+MAX(0,F89*$B$41) -> 26785287
A94: القاعدة الرأسمالية قبل الخصومات | B94: =B91+B92 -> 21833129 | C94: =C91+C92 -> 76086745 | D94: =D91+D92 -> 1.5283806e+08 | E94: =E91+E92 -> 3.1277889e+08 | F94: =F91+F92 -> 6.0253887e+08
A95: الحد الأدنى لكفاية رأس المال | B95: 0.12 | C95: 0.12 | D95: 0.12 | E95: 0.12 | F95: 0.12
A96: معامل BI لاختبار التحمل الأعلى / افتراض بديل (18%) | B96: 0.18 | C96: 0.18 | D96: 0.18 | E96: 0.18 | F96: 0.18
A97: مضاعف تحويل مخاطر التشغيل | B97: 12.5 | C97: 12.5 | D97: 12.5 | E97: 12.5 | F97: 12.5
A98: النقدية الختامية | B98: ='Cash Flow'!B25 -> 3220918 | C98: ='Cash Flow'!C25 -> 9502515.4 | D98: ='Cash Flow'!D25 -> 13213489 | E98: ='Cash Flow'!E25 -> 65805120 | F98: ='Cash Flow'!F25 -> 2.4078058e+08
A99: أصول أخرى | B99: 258076.28 | C99: 258076.28 | D99: 258076.28 | E99: 258076.28 | F99: 258076.28
A100: رسوم مؤجلة والتزامات تشغيلية | B100: 6000000 | C100: 7500000 | D100: 21000000 | E100: 40500000 | F100: 75000000
A101: حدود التسهيلات البنكية | B101: 0 | C101: 420000000 | D101: 850000000 | E101: 1600000000 | F101: 3000000000
A102: نسبة الدين بأجل متبق سنة فأكثر | B102: 0.8 | C102: 0.85 | D102: 0.9 | E102: 0.9 | F102: 0.9
...

Sheet Capital
A1: رأس المال والتزامات المساهمين
A3: Plan Stage | B3: البيان | C3: إجمالي الزيادة | D3: Finvera | E3: El-Mobadara | F3: CDS | G3: Egabi
A4: 46296 | B4: رأس المال المصدر والمدفوع عند التأسيس | C4: 15000000 | D4: 3750000 | E4: 3750000 | F4: 3750000 | G4: 3750000
A5: 46478 | B5: دفعة ربع سنوية | C5: 3750000 | D5: 937500 | E5: 937500 | F5: 937500 | G5: 937500
A6: 46569 | B6: دفعة ربع سنوية | C6: 3750000 | D6: 937500 | E6: 937500 | F6: 937500 | G6: 937500
A7: 46661 | B7: دفعة ربع سنوية | C7: 3750000 | D7: 937500 | E7: 937500 | F7: 937500 | G7: 937500
A8: 46752 | B8: استكمال 30 مليون | C8: 3750000 | D8: 937500 | E8: 937500 | F8: 937500 | G8: 937500
A9: 46783 | B9: دفعة لاستكمال رأس المال | C9: 15000000 | D9: 3750000 | E9: 3750000 | F9: 3750000 | G9: 3750000
A10: 46904 | B10: دفعة لاستكمال رأس المال | C10: 15000000 | D10: 3750000 | E10: 3750000 | F10: 3750000 | G10: 3750000
A11: 47026 | B11: استكمال 75 مليون | C11: 15000000 | D11: 3750000 | E11: 3750000 | F11: 3750000 | G11: 3750000
A13: بيانات رأس المال والأسهم
A14: رأس المال المرخص به | B14: 75000000
A15: رأس المال المصدر والمدفوع عند البداية | B15: 15000000
A16: رأس المال المصدر والمدفوع بعد الاستكمال | B16: 75000000
A17: القيمة الاسمية للسهم | B17: 1
A18: إجمالي عدد الأسهم بعد الاستكمال | B18: 75000000
A19: إجمالي عدد الأسهم المصرح بها | B19: =B14/B17 -> 75000000
A20: المساهمون
A21: المساهم | B21: نسبة الملكية | C21: رأس المال النقدي | D21: مصروفات تأسيس مسددة | E21: إجمالي التزام نقدي | F21: حد الإدارة | G21: هامش
A22: Finvera | B22: 0.25 | C22: 18750000 | D22: 64519.07 | E22: 18814519 | F22: 20000000 | G22: 1185480.9
A23: El-Mobadara | B23: 0.25 | C23: 18750000 | D23: 64519.07 | E23: 18814519 | F23: 20000000 | G23: 1185480.9
A24: CDS | B24: 0.25 | C24: 18750000 | D24: 64519.07 | E24: 18814519 | F24: 20000000 | G24: 1185480.9
A25: Egabi | B25: 0.25 | C25: 18750000 | D25: 64519.07 | E25: 18814519 | F25: 20000000 | G25: 1185480.9
A27: مصروفات التأسيس البالغة 258,076.28 جنيه تحملها المساهمون بالتساوي وفق نسب الملكية، ولا تدخل في القاعدة الرأسمالية التنظيمية ما لم يعتمد المستشار القانوني ومراقب الحسابات معالجتها كحقوق ملكية مؤهلة.

Sheet Products
A1: المنتجات والقطاعات المستهدفة
A3: القطاع | B3: المزيج | C3: متوسط العقد | D3: الحد الأدنى | E3: الحد الأقصى الإرشادي | F3: المقدم الأدنى | G3: المقدم الأقصى | H3: المدة الدنيا - شهر | I3: المدة القصوى - شهر | J3: ملاحظات
A4: معدات صناعية | B4: 0.25 | C4: 250000 | D4: 50000 | E4: 500000 | F4: 0.1 | G4: 0.2 | H4: 12 | I4: 60 | J4: طبقا للعمر الإنتاجي للأصل
A5: معدات زراعية | B5: 0.2 | C5: 300000 | D5: 50000 | E5: 500000 | F5: 0.1 | G5: 0.2 | H5: 6 | I5: 48 | J5: يجوز تحصيل ربع/نصف سنوي للأنشطة الموسمية
A6: معدات طبية | B6: 0.2 | C6: 150000 | D6: 50000 | E6: 500000 | F6: 0.1 | G6: 0.2 | H6: 12 | I6: 60 | J6: موردون معتمدون وتأمين على الأصل
A7: نقل تجاري خفيف | B7: 0.25 | C7: 500000 | D7: 100000 | E7: 1000000 | F7: 0.1 | G7: 0.2 | H7: 12 | I7: 60 | J7: التأمين والترخيص شرط صرف
A8: قطاعات أخرى | B8: 0.1 | C8: 275000 | D8: 50000 | E8: 500000 | F8: 0.1 | G8: 0.2 | H8: 6 | I8: 48 | J8: تخضع لحدود التركز والسياسة الائتمانية
A10: مؤشر | B10: القيمة | C10: الفحص
A11: إجمالي المزيج | B11: =SUM(B4:B8) -> 1 | C11: =IF(ABS(B11-100%)<0.0001,"OK","راجع المزيج") -> OK
A12: متوسط العقد المرجح | B12: =SUMPRODUCT(B4:B8,C4:C8) -> 305000 | C12: استرشادي؛ يختلف سنويا حسب خطة المنح
A14: قواعد التسعير | B14: سعر العميل ثابت لكل عقد موقع، ويحدد عند المنح وفق تكلفة تمويل البنك + هامش مخاطر وتشغيل.
A15: السداد المعجل | B15: خصم العوائد غير المستحقة مع عمولة سداد معجل 5%-10% وفق العقد والقواعد المعتمدة.
A16: التأخير | B16: غرامة شهرية على الأجرة المتأخرة وفق العقد وبما لا يخالف الضوابط؛ لم يفترض دخل منها في الحالة الأساسية.
A17: التملك | B17: سعر رمزي جنيه واحد بعد سداد جميع الالتزامات والمصروفات والأقساط.

Sheet Staff
A1: الهيكل الوظيفي وتكلفة العمالة
A3: الوظيفة | B3: الراتب الشهري الأساسي Year 1 | C3: Year 1 FTE | D3: Year 2 FTE | E3: Year 3 FTE | F3: Year 4 FTE | G3: Year 5 FTE | H3: Year 1 Cost | I3: Year 2 Cost | J3: Year 3 Cost | K3: Year 4 Cost | L3: Year 5 Cost | M3: ملاحظة رقابية
A4: الرئيس التنفيذي والعضو المنتدب | B4: 150000 | C4: 1 | D4: 1 | E4: 1 | F4: 1 | G4: 1 | H4: =ROUND($B4*C4*12*(1+Assumptions!$B$34)^0,2) -> 1800000 | I4: =ROUND($B4*D4*12*(1+Assumptions!$B$34)^1,2) -> 2160000 | J4: =ROUND($B4*E4*12*(1+Assumptions!$B$34)^2,2) -> 2592000 | K4: =ROUND($B4*F4*12*(1+Assumptions!$B$34)^3,2) -> 3110400 | L4: =ROUND($B4*G4*12*(1+Assumptions!$B$34)^4,2) -> 3732480 | M4: إدارة تنفيذية
A5: نائب الرئيس التنفيذي/عضو مجلس الإدارة | B5: 120000 | C5: 1 | D5: 1 | E5: 1 | F5: 1 | G5: 1 | H5: =ROUND($B5*C5*12*(1+Assumptions!$B$34)^0,2) -> 1440000 | I5: =ROUND($B5*D5*12*(1+Assumptions!$B$34)^1,2) -> 1728000 | J5: =ROUND($B5*E5*12*(1+Assumptions!$B$34)^2,2) -> 2073600 | K5: =ROUND($B5*F5*12*(1+Assumptions!$B$34)^3,2) -> 2488320 | L5: =ROUND($B5*G5*12*(1+Assumptions!$B$34)^4,2) -> 2985984 | M5: حوكمة
A6: المدير المالي والإداري | B6: 65000 | C6: 1 | D6: 1 | E6: 1 | F6: 1 | G6: 1 | H6: =ROUND($B6*C6*12*(1+Assumptions!$B$34)^0,2) -> 780000 | I6: =ROUND($B6*D6*12*(1+Assumptions!$B$34)^1,2) -> 936000 | J6: =ROUND($B6*E6*12*(1+Assumptions!$B$34)^2,2) -> 1123200 | K6: =ROUND($B6*F6*12*(1+Assumptions!$B$34)^3,2) -> 1347840 | L6: =ROUND($B6*G6*12*(1+Assumptions!$B$34)^4,2) -> 1617408 | M6: قوائم وسيولة
A7: مدير المخاطر | B7: 35000 | C7: 1 | D7: 1 | E7: 1 | F7: 1 | G7: 1 | H7: =ROUND($B7*C7*12*(1+Assumptions!$B$34)^0,2) -> 420000 | I7: =ROUND($B7*D7*12*(1+Assumptions!$B$34)^1,2) -> 504000 | J7: =ROUND($B7*E7*12*(1+Assumptions!$B$34)^2,2) -> 604800 | K7: =ROUND($B7*F7*12*(1+Assumptions!$B$34)^3,2) -> 725760 | L7: =ROUND($B7*G7*12*(1+Assumptions!$B$34)^4,2) -> 870912 | M7: مستقل رقابيا
A8: مدير التقنية | B8: 60000 | C8: 1 | D8: 1 | E8: 1 | F8: 1 | G8: 1 | H8: =ROUND($B8*C8*12*(1+Assumptions!$B$34)^0,2) -> 720000 | I8: =ROUND($B8*D8*12*(1+Assumptions!$B$34)^1,2) -> 864000 | J8: =ROUND($B8*E8*12*(1+Assumptions!$B$34)^2,2) -> 1036800 | K8: =ROUND($B8*F8*12*(1+Assumptions!$B$34)^3,2) -> 1244160 | L8: =ROUND($B8*G8*12*(1+Assumptions!$B$34)^4,2) -> 1492992 | M8: حماية واستمرارية الأعمال
A9: مسؤولو التقنية | B9: 36000 | C9: 3 | D9: 3 | E9: 3 | F9: 3 | G9: 3 | H9: =ROUND($B9*C9*12*(1+Assumptions!$B$34)^0,2) -> 1296000 | I9: =ROUND($B9*D9*12*(1+Assumptions!$B$34)^1,2) -> 1555200 | J9: =ROUND($B9*E9*12*(1+Assumptions!$B$34)^2,2) -> 1866240 | K9: =ROUND($B9*F9*12*(1+Assumptions!$B$34)^3,2) -> 2239488 | L9: =ROUND($B9*G9*12*(1+Assumptions!$B$34)^4,2) -> 2687385.6 | M9: توسع تقني متدرج
A10: حوافز ومكافآت أداء متغيرة ضمن موازنة العاملين المعتمدة | C10: 0 | D10: 0 | E10: 0 | F10: 0 | G10: 0 | H10: =MAX(0,H$22-SUM(H$4:H$9,H$11:H$20)) -> 0 | I10: =MAX(0,I$22-SUM(I$4:I$9,I$11:I$20)) -> 2230665.6 | J10: =MAX(0,J$22-SUM(J$4:J$9,J$11:J$20)) -> 5829067.7 | K10: =MAX(0,K$22-SUM(K$4:K$9,K$11:K$20)) -> 5783328.5 | L10: =MAX(0,L$22-SUM(L$4:L$9,L$11:L$20)) -> 6939994.2 | M10: رصيد موازنة متغير: إجمالي موازنة العاملين المعتمدة ناقص الرواتب الثابتة؛ الصرف الفعلي يخضع لمؤشرات الإنتاج والأداء.
A11: مسؤول الالتزام | B11: 15000 | C11: 1 | D11: 1 | E11: 1 | F11: 1 | G11: 1 | H11: =ROUND($B11*C11*12*(1+Assumptions!$B$34)^0,2) -> 180000 | I11: =ROUND($B11*D11*12*(1+Assumptions!$B$34)^1,2) -> 216000 | J11: =ROUND($B11*E11*12*(1+Assumptions!$B$34)^2,2) -> 259200 | K11: =ROUND($B11*F11*12*(1+Assumptions!$B$34)^3,2) -> 311040 | L11: =ROUND($B11*G11*12*(1+Assumptions!$B$34)^4,2) -> 373248 | M11: تقارير مباشرة للمجلس/لجنة المراجعة
A12: مسؤول مكافحة غسل الأموال وتمويل الإرهاب | B12: 15000 | C12: 1 | D12: 1 | E12: 1 | F12: 1 | G12: 1 | H12: =ROUND($B12*C12*12*(1+Assumptions!$B$34)^0,2) -> 180000 | I12: =ROUND($B12*D12*12*(1+Assumptions!$B$34)^1,2) -> 216000 | J12: =ROUND($B12*E12*12*(1+Assumptions!$B$34)^2,2) -> 259200 | K12: =ROUND($B12*F12*12*(1+Assumptions!$B$34)^3,2) -> 311040 | L12: =ROUND($B12*G12*12*(1+Assumptions!$B$34)^4,2) -> 373248 | M12: وظيفة مستقلة واتصال مباشر بالمجلس والجهات المختصة
A13: مسؤول المراجعة الداخلية | B13: 25000 | C13: 1 | D13: 1 | E13: 1 | F13: 1 | G13: 1 | H13: =ROUND($B13*C13*12*(1+Assumptions!$B$34)^0,2) -> 300000 | I13: =ROUND($B13*D13*12*(1+Assumptions!$B$34)^1,2) -> 360000 | J13: =ROUND($B13*E13*12*(1+Assumptions!$B$34)^2,2) -> 432000 | K13: =ROUND($B13*F13*12*(1+Assumptions!$B$34)^3,2) -> 518400 | L13: =ROUND($B13*G13*12*(1+Assumptions!$B$34)^4,2) -> 622080 | M13: استقلال وظيفي
A14: مسؤول الموارد البشرية | B14: 15000 | C14: 1 | D14: 1 | E14: 1 | F14: 1 | G14: 1 | H14: =ROUND($B14*C14*12*(1+Assumptions!$B$34)^0,2) -> 180000 | I14: =ROUND($B14*D14*12*(1+Assumptions!$B$34)^1,2) -> 216000 | J14: =ROUND($B14*E14*12*(1+Assumptions!$B$34)^2,2) -> 259200 | K14: =ROUND($B14*F14*12*(1+Assumptions!$B$34)^3,2) -> 311040 | L14: =ROUND($B14*G14*12*(1+Assumptions!$B$34)^4,2) -> 373248 | M14: دعم إداري
A15: فريق مخاطر الائتمان | B15: 15000 | C15: 2 | D15: 2 | E15: 2 | F15: 2 | G15: 2 | H15: =ROUND($B15*C15*12*(1+Assumptions!$B$34)^0,2) -> 360000 | I15: =ROUND($B15*D15*12*(1+Assumptions!$B$34)^1,2) -> 432000 | J15: =ROUND($B15*E15*12*(1+Assumptions!$B$34)^2,2) -> 518400 | K15: =ROUND($B15*F15*12*(1+Assumptions!$B$34)^3,2) -> 622080 | L15: =ROUND($B15*G15*12*(1+Assumptions!$B$34)^4,2) -> 746496 | M15: يتدرج مع المحفظة
A16: المشتريات وإدارة الموردين | B16: 15000 | C16: 3 | D16: 3 | E16: 3 | F16: 3 | G16: 3 | H16: =ROUND($B16*C16*12*(1+Assumptions!$B$34)^0,2) -> 540000 | I16: =ROUND($B16*D16*12*(1+Assumptions!$B$34)^1,2) -> 648000 | J16: =ROUND($B16*E16*12*(1+Assumptions!$B$34)^2,2) -> 777600 | K16: =ROUND($B16*F16*12*(1+Assumptions!$B$34)^3,2) -> 933120 | L16: =ROUND($B16*G16*12*(1+Assumptions!$B$34)^4,2) -> 1119744 | M16: تحقق من الأصل والمورد
A17: مسؤولو التوقيعات والمعاينات الميدانية | B17: 14000 | C17: 8 | D17: 8 | E17: 8 | F17: 8 | G17: 8 | H17: =ROUND($B17*C17*12*(1+Assumptions!$B$34)^0,2) -> 1344000 | I17: =ROUND($B17*D17*12*(1+Assumptions!$B$34)^1,2) -> 1612800 | J17: =ROUND($B17*E17*12*(1+Assumptions!$B$34)^2,2) -> 1935360 | K17: =ROUND($B17*F17*12*(1+Assumptions!$B$34)^3,2) -> 2322432 | L17: =ROUND($B17*G17*12*(1+Assumptions!$B$34)^4,2) -> 2786918.4 | M17: توقيع، استلام/تسليم، معاينة، متابعة واسترداد
A18: التسويق والتواصل الرقمي | B18: 14676 | C18: 1 | D18: 1 | E18: 1 | F18: 1 | G18: 1 | H18: =ROUND($B18*C18*12*(1+Assumptions!$B$34)^0,2) -> 176112 | I18: =ROUND($B18*D18*12*(1+Assumptions!$B$34)^1,2) -> 211334.4 | J18: =ROUND($B18*E18*12*(1+Assumptions!$B$34)^2,2) -> 253601.28 | K18: =ROUND($B18*F18*12*(1+Assumptions!$B$34)^3,2) -> 304321.54 | L18: =ROUND($B18*G18*12*(1+Assumptions!$B$34)^4,2) -> 365185.84 | M18: توسع مرحلي
A19: مسؤولو التأجير التمويلي داخل الفروع | B19: 12000 | C19: 8 | D19: 8 | E19: 8 | F19: 8 | G19: 8 | H19: =ROUND($B19*C19*12*(1+Assumptions!$B$34)^0,2) -> 1152000 | I19: =ROUND($B19*D19*12*(1+Assumptions!$B$34)^1,2) -> 1382400 | J19: =ROUND($B19*E19*12*(1+Assumptions!$B$34)^2,2) -> 1658880 | K19: =ROUND($B19*F19*12*(1+Assumptions!$B$34)^3,2) -> 1990656 | L19: =ROUND($B19*G19*12*(1+Assumptions!$B$34)^4,2) -> 2388787.2 | M19: مرتبط بحجم المنح
A20: مساعدون إداريون | B20: 12000 | C20: 2 | D20: 2 | E20: 2 | F20: 2 | G20: 2 | H20: =ROUND($B20*C20*12*(1+Assumptions!$B$34)^0,2) -> 288000 | I20: =ROUND($B20*D20*12*(1+Assumptions!$B$34)^1,2) -> 345600 | J20: =ROUND($B20*E20*12*(1+Assumptions!$B$34)^2,2) -> 414720 | K20: =ROUND($B20*F20*12*(1+Assumptions!$B$34)^3,2) -> 497664 | L20: =ROUND($B20*G20*12*(1+Assumptions!$B$34)^4,2) -> 597196.8 | M20: دعم
A21: الإجمالي | C21: =SUM(C4:C20) -> 36 | D21: =SUM(D4:D20) -> 36 | E21: =SUM(E4:E20) -> 36 | F21: =SUM(F4:F20) -> 36 | G21: =SUM(G4:G20) -> 36 | H21: =SUM(H4:H20) -> 11156112 | I21: =SUM(I4:I20) -> 15618000 | J21: =SUM(J4:J20) -> 21893869 | ... L21: =SUM(L4:L20) -> 30073308
A22: إجمالي موازنة العاملين المعتمدة | B22: إجمالي سنوي معتمد من الإدارة | H22: 11156112 | I22: 15618000 | J22: 21893869 | K22: 25061090 | L22: 30073308
A23: موقع مسؤول مكافحة غسل الأموال | B23: وظيفة رقابية مستقلة عن المبيعات والائتمان؛ ترتبط وظيفيا بلجنة المراجعة/مجلس الإدارة وإداريا بالرئيس التنفيذي
A24: اختصاصات أساسية | B24: تقييم المخاطر، KYC/UBO، مراقبة العمليات، فحص الجزاءات، البلاغات، السجلات والتدريب
A25: أساس العدد والتكلفة | B25: إجمالي القوى العاملة 36 موظفا في كل سنة، مع زيادة سنوية 20% وحوافز إنتاج وفق جدول الافتراضات. لا توجد وظيفة مدير تشغيل مخصصة في الموازنة (العدد صفر في المصدر)، وتتولى الإدارة التنفيذية مهام الإشراف التشغيلي في مرحلة الإطلاق. تم تخصيص وظيفة مستقلة لمسؤول مكافحة غسل الأموال داخل نفس إجمالي العدد والتكلفة.

Sheet Opex
A1: المصروفات الإدارية والعمومية السنوية
A3: البند | B3: تكلفة الوحدة شهريا | C3: Year 1 Units | D3: Year 2 Units | E3: Year 3 Units | F3: Year 4 Units | G3: Year 5 Units | H3: Year 1 | I3: Year 2 | J3: Year 3 | K3: Year 4 | L3: Year 5
A4: إيجار المركز الرئيسي | B4: 80000 | C4: 1 | D4: 1 | E4: 1 | F4: 1 | G4: 1 | H4: =$B4*C4*12*(1+Assumptions!$B$35)^0*Assumptions!$B$66 -> 620307.69 | I4: =$B4*D4*12*(1+Assumptions!$B$35)^1*Assumptions!$C$66 -> 1036800 | J4: =ROUND($B4*E4*12*(1+Assumptions!$B$35)^2*Assumptions!$D$66,2) -> 1161600 | K4: =ROUND($B4*F4*12*(1+Assumptions!$B$35)^3*Assumptions!$E$66,2) -> 1277760 | L4: =ROUND($B4*G4*12*(1+Assumptions!$B$35)^4*Assumptions!$F$66,2) -> 1405536
A5: إيجار مكاتب التوقيع وخدمات الأصول | B5: 30000 | C5: 8 | D5: 8 | E5: 8 | F5: 15 | G5: 22 | H5: =$B5*C5*12*(1+Assumptions!$B$35)^0*Assumptions!$B$66 -> 1860923.1 | I5: =$B5*D5*12*(1+Assumptions!$B$35)^1*Assumptions!$C$66 -> 3110400 | J5: =ROUND($B5*E5*12*(1+Assumptions!$B$35)^2*Assumptions!$D$66,2) -> 3484800 | K5: =ROUND($B5*F5*12*(1+Assumptions!$B$35)^3*Assumptions!$E$66,2) -> 7187400 | L5: =ROUND($B5*G5*12*(1+Assumptions!$B$35)^4*Assumptions!$F$66,2) -> 11595672
A6: بدلات مجلس الإدارة والحوكمة | B6: 25000 | C6: 1 | D6: 1 | E6: 1 | F6: 1 | G6: 1 | H6: =$B6*C6*12*(1+Assumptions!$B$35)^0*Assumptions!$B$66 -> 193846.15 | I6: =$B6*D6*12*(1+Assumptions!$B$35)^1*Assumptions!$C$66 -> 324000 | J6: =ROUND($B6*E6*12*(1+Assumptions!$B$35)^2*Assumptions!$D$66,2) -> 363000 | K6: =ROUND($B6*F6*12*(1+Assumptions!$B$35)^3*Assumptions!$E$66,2) -> 399300 | L6: =ROUND($B6*G6*12*(1+Assumptions!$B$35)^4*Assumptions!$F$66,2) -> 439230
A7: كهرباء وإنترنت المركز الرئيسي | B7: 20000 | C7: 1 | D7: 1 | E7: 1 | F7: 1 | G7: 1 | H7: =$B7*C7*12*(1+Assumptions!$B$35)^0*Assumptions!$B$66 -> 155076.92 | I7: =$B7*D7*12*(1+Assumptions!$B$35)^1*Assumptions!$C$66 -> 259200 | J7: =ROUND($B7*E7*12*(1+Assumptions!$B$35)^2*Assumptions!$D$66,2) -> 290400 | K7: =ROUND($B7*F7*12*(1+Assumptions!$B$35)^3*Assumptions!$E$66,2) -> 319440 | L7: =ROUND($B7*G7*12*(1+Assumptions!$B$35)^4*Assumptions!$F$66,2) -> 351384
A8: مرافق مكاتب التوقيع وخدمات الأصول | B8: 2500 | C8: 8 | D8: 8 | E8: 8 | F8: 15 | G8: 22 | H8: =$B8*C8*12*(1+Assumptions!$B$35)^0*Assumptions!$B$66 -> 155076.92 | I8: =$B8*D8*12*(1+Assumptions!$B$35)^1*Assumptions!$C$66 -> 259200 | J8: =ROUND($B8*E8*12*(1+Assumptions!$B$35)^2*Assumptions!$D$66,2) -> 290400 | K8: =ROUND($B8*F8*12*(1+Assumptions!$B$35)^3*Assumptions!$E$66,2) -> 598950 | L8: =ROUND($B8*G8*12*(1+Assumptions!$B$35)^4*Assumptions!$F$66,2) -> 966306
A9: مياه ونظافة | B9: 5000 | C9: 1 | D9: 1 | E9: 1 | F9: 1 | G9: 1 | H9: =$B9*C9*12*(1+Assumptions!$B$35)^0*Assumptions!$B$66 -> 38769.231 | I9: =$B9*D9*12*(1+Assumptions!$B$35)^1*Assumptions!$C$66 -> 64800 | J9: =ROUND($B9*E9*12*(1+Assumptions!$B$35)^2*Assumptions!$D$66,2) -> 72600 | K9: =ROUND($B9*F9*12*(1+Assumptions!$B$35)^3*Assumptions!$E$66,2) -> 79860 | L9: =ROUND($B9*G9*12*(1+Assumptions!$B$35)^4*Assumptions!$F$66,2) -> 87846
A10: مواصلات وانتقالات | B10: 10000 | C10: 1 | D10: 1 | E10: 1 | F10: 1 | G10: 1 | H10: =$B10*C10*12*(1+Assumptions!$B$35)^0*Assumptions!$B$66 -> 77538.462 | I10: =$B10*D10*12*(1+Assumptions!$B$35)^1*Assumptions!$C$66 -> 129600 | J10: =ROUND($B10*E10*12*(1+Assumptions!$B$35)^2*Assumptions!$D$66,2) -> 145200 | K10: =ROUND($B10*F10*12*(1+Assumptions!$B$35)^3*Assumptions!$E$66,2) -> 159720 | L10: =ROUND($B10*G10*12*(1+Assumptions!$B$35)^4*Assumptions!$F$66,2) -> 175692
A11: صيانة أجهزة وأنظمة | B11: 15000 | C11: 1 | D11: 1 | E11: 1 | F11: 1 | G11: 1 | H11: =$B11*C11*12*(1+Assumptions!$B$35)^0*Assumptions!$B$66 -> 116307.69 | I11: =$B11*D11*12*(1+Assumptions!$B$35)^1*Assumptions!$C$66 -> 194400 | J11: =ROUND($B11*E11*12*(1+Assumptions!$B$35)^2*Assumptions!$D$66,2) -> 217800 | K11: =ROUND($B11*F11*12*(1+Assumptions!$B$35)^3*Assumptions!$E$66,2) -> 239580 | L11: =ROUND($B11*G11*12*(1+Assumptions!$B$35)^4*Assumptions!$F$66,2) -> 263538
A12: تسويق وتشغيل رقمي | B12: 35000 | C12: 1 | D12: 1 | E12: 1 | F12: 1 | G12: 1 | H12: =$B12*C12*12*(1+Assumptions!$B$35)^0*Assumptions!$B$66 -> 271384.62 | I12: =$B12*D12*12*(1+Assumptions!$B$35)^1*Assumptions!$C$66 -> 453600 | J12: =ROUND($B12*E12*12*(1+Assumptions!$B$35)^2*Assumptions!$D$66,2) -> 508200 | K12: =ROUND($B12*F12*12*(1+Assumptions!$B$35)^3*Assumptions!$E$66,2) -> 559020 | L12: =ROUND($B12*G12*12*(1+Assumptions!$B$35)^4*Assumptions!$F$66,2) -> 614922
A13: رسوم الهيئة وتجديدات رقابية | B13: 50000 | C13: 1 | D13: 1 | E13: 1 | F13: 1 | G13: 1 | H13: =$B13*C13*12*(1+Assumptions!$B$35)^0*Assumptions!$B$66 -> 387692.31 | I13: =$B13*D13*12*(1+Assumptions!$B$35)^1*Assumptions!$C$66 -> 648000 | J13: =ROUND($B13*E13*12*(1+Assumptions!$B$35)^2*Assumptions!$D$66,2) -> 726000 | K13: =ROUND($B13*F13*12*(1+Assumptions!$B$35)^3*Assumptions!$E$66,2) -> 798600 | L13: =ROUND($B13*G13*12*(1+Assumptions!$B$35)^4*Assumptions!$F$66,2) -> 878460
A14: أدوات كتابية ومطبوعات | B14: 20000 | C14: 1 | D14: 1 | E14: 1 | F14: 1 | G14: 1 | H14: =$B14*C14*12*(1+Assumptions!$B$35)^0*Assumptions!$B$66 -> 155076.92 | I14: =$B14*D14*12*(1+Assumptions!$B$35)^1*Assumptions!$C$66 -> 259200 | J14: =ROUND($B14*E14*12*(1+Assumptions!$B$35)^2*Assumptions!$D$66,2) -> 290400 | K14: =ROUND($B14*F14*12*(1+Assumptions!$B$35)^3*Assumptions!$E$66,2) -> 319440 | L14: =ROUND($B14*G14*12*(1+Assumptions!$B$35)^4*Assumptions!$F$66,2) -> 351384
A15: مصروفات قانونية واستشارات | B15: 12000 | C15: 1 | D15: 1 | E15: 1 | F15: 1 | G15: 1 | H15: =$B15*C15*12*(1+Assumptions!$B$35)^0*Assumptions!$B$66 -> 93046.154 | I15: =$B15*D15*12*(1+Assumptions!$B$35)^1*Assumptions!$C$66 -> 155520 | J15: =ROUND($B15*E15*12*(1+Assumptions!$B$35)^2*Assumptions!$D$66,2) -> 174240 | K15: =ROUND($B15*F15*12*(1+Assumptions!$B$35)^3*Assumptions!$E$66,2) -> 191664 | L15: =ROUND($B15*G15*12*(1+Assumptions!$B$35)^4*Assumptions!$F$66,2) -> 210830.4
... A18: خدمة عملاء واتصالات | B18: 10000 | C18: 1 | D18: 1 | E18: 1 | F18: 1 | G18: 1 | H18: =$B18*C18*12*(1+Assumptions!$B$35)^0*Assumptions!$B$66 -> 77538.462 | I18: =$B18*D18*12*(1+Assumptions!$B$35)^1*Assumptions!$C$66 -> 129600 | J18: =ROUND($B18*E18*12*(1+Assumptions!$B$35)^2*Assumptions!$D$66,2) -> 145200 | K18: =ROUND($B18*F18*12*(1+Assumptions!$B$35)^3*Assumptions!$E$66,2) -> 159720 | L18: =ROUND($B18*G18*12*(1+Assumptions!$B$35)^4*Assumptions!$F$66,2) -> 175692
A19: إجمالي المصروفات الإدارية والعمومية | H19: =SUM(H4:H18) -> 4435200 | I19: =SUM(I4:I18) -> 7413120 | J19: =SUM(J4:J18) -> 8305440 | K19: =SUM(K4:K18) -> 12769614 | L19: =SUM(L4:L18) -> 18043568
A20: موازنة G&A المعتمدة للسنتين المقفلتين | H20: 4435200 | I20: 7413120
A21: منهجية المصروفات | B21: Year 1-Year 2: تفاصيل البنود توائم إلى الموازنة السنوية المعتمدة باستخدام معامل مشتق آليا من إجمالي الموازنة. من Year 3: تكلفة الوحدة الشهرية × عدد الوحدات × 12 × الزيادة السنوية، بدون معامل موازنة إضافي.
A22: وظائف المكاتب | B22: التوقيعات، استلام وتسليم الأصل، المعاينات والاستعلامات الميدانية، المتابعة الدورية والاسترداد
A23: مخزن الأصول المستردة | B23: افتراض: مخزن بالقاهرة في أول 3 سنوات بإيجار تقديري 20,000 جنيه شهريا؛ إفصاح فقط وغير مدرج بالمصروفات لحين التعاقد
A24: مصروفات غير مدرجة | B24: غرامات التأخير ليست إيرادا أساسيا، وتأمين الأصل يحمل على العميل/العقد عند السماح والتوثيق

Sheet Originations
A1: Origination Plan by Period and Quarter - 60 Periods
A3: Period | B3: 46388 | C3: 46419 | D3: 46447 | E3: 46478 | F3: 46508 | G3: 46539 | H3: 46569 | I3: 46600 | J3: 46631 | K3: 46661 | L3: 46692 | M3: 46722 | N3: 46753 | O3: 46784 | P3: 46813 | Q3: 46844 | R3: 46874 | S3: 46905 | T3: 46935 | U3: 46966 | V3: 46997 | W3: 47027 | X3: 47058 | Y3: 47088 | Z3: 47119 | AA3: 47150 | AB3: 47178 | AC3: 47209 | AD3: 47239 | AE3: 47270 | AF3: 47300 | AG3: 47331 | AH3: 47362 | AI3: 47392 | AJ3: 47423 | AK3: 47453 | AL3: 47484 | AM3: 47515 | AN3: 47543 | AO3: 47574 | AP3: 47604 | AQ3: 47635 | AR3: 47665 | AS3: 47696 | AT3: 47727 | AU3: 47757 | AV3: 47788 | AW3: 47818 | AX3: 47849 | AY3: 47880 | AZ3: 47908 | BA3: 47939 | BB3: 47969 | BC3: 48000 | BD3: 48030 | BE3: 48061 | BF3: 48092 | BG3: 48122 | BH3: 48153 | BI3: 48183
A4: Plan Year | B4: 2027 | C4: 2027 | D4: 2027 | E4: 2027 | F4: 2027 | G4: 2027 | H4: 2027 | I4: 2027 | J4: 2027 | K4: 2027 | L4: 2027 | M4: 2027 | N4: 2028 | O4: 2028 | P4: 2028 | Q4: 2028 | R4: 2028 | S4: 2028 | T4: 2028 | U4: 2028 | V4: 2028 | W4: 2028 | X4: 2028 | Y4: 2028 | Z4: 2029 | AA4: 2029 | AB4: 2029 | AC4: 2029 | AD4: 2029 | AE4: 2029 | AF4: 2029 | AG4: 2029 | AH4: 2029 | AI4: 2029 | AJ4: 2029 | AK4: 2029 | AL4: 2030 | AM4: 2030 | AN4: 2030 | AO4: 2030 | AP4: 2030 | AQ4: 2030 | AR4: 2030 | AS4: 2030 | AT4: 2030 | AU4: 2030 | AV4: 2030 | AW4: 2030 | AX4: 2031 | AY4: 2031 | AZ4: 2031 | BA4: 2031 | BB4: 2031 | BC4: 2031 | BD4: 2031 | BE4: 2031 | BF4: 2031 | BG4: 2031 | BH4: 2031 | BI4: 2031
A5: Period Sequence | B5: 1 | C5: 2 | D5: 3 | E5: 4 | F5: 5 | G5: 6 | H5: 7 | I5: 8 | J5: 9 | K5: 10 | L5: 11 | M5: 12 | N5: 13 | O5: 14 | P5: 15 | Q5: 16 | R5: 17 | S5: 18 | T5: 19 | U5: 20 | V5: 21 | W5: 22 | X5: 23 | Y5: 24 | Z5: 25 | AA5: 26 | AB5: 27 | AC5: 28 | AD5: 29 | AE5: 30 | AF5: 31 | AG5: 32 | AH5: 33 | AI5: 34 | AJ5: 35 | AK5: 36 | AL5: 37 | AM5: 38 | AN5: 39 | AO5: 40 | AP5: 41 | AQ5: 42 | AR5: 43 | AS5: 44 | AT5: 45 | AU5: 46 | AV5: 47 | AW5: 48 | AX5: 49 | AY5: 50 | AZ5: 51 | BA5: 52 | BB5: 53 | BC5: 54 | BD5: 55 | BE5: 56 | BF5: 57 | BG5: 58 | BH5: 59 | BI5: 60
A6: وزن الشهر داخل السنة | B6: 0 | C6: 0.071428571 | D6: 0.071428571 | E6: 0.082142857 | F6: 0.082142857 | G6: 0.082142857 | H6: 0.096428571 | I6: 0.096428571 | J6: 0.096428571 | K6: 0.10714286 | L6: 0.10714286 | M6: 0.10714286 | N6: 0.066666667 | O6: 0.066666667 | P6: 0.066666667 | Q6: 0.076666667 | R6: 0.076666667 | S6: 0.076666667 | T6: 0.09 | U6: 0.09 | V6: 0.09 | W6: 0.1 | X6: 0.1 | Y6: 0.1 | Z6: 0.066666667 | AA6: 0.066666667 | AB6: 0.066666667 | AC6: 0.076666667 | AD6: 0.076666667 | AE6: 0.076666667 | AF6: 0.09 | AG6: 0.09 | AH6: 0.09 | AI6: 0.1 | AJ6: 0.1 | AK6: 0.1 | AL6: 0.066666667 | AM6: 0.066666667 | AN6: 0.066666667 | AO6: 0.076666667 | AP6: 0.076666667 | AQ6: 0.076666667 | AR6: 0.09 | AS6: 0.09 | AT6: 0.09 | AU6: 0.1 | AV6: 0.1 | AW6: 0.1 | AX6: 0.066666667 | AY6: 0.066666667 | AZ6: 0.066666667 | BA6: 0.076666667 | BB6: 0.076666667 | BC6: 0.076666667 | BD6: 0.09 | BE6: 0.09 | BF6: 0.09 | BG6: 0.1 | BH6: 0.1 | BI6: 0.1
A7: المنح الشهري المخطط | B7: =Assumptions!B$4*B$6 -> 0 | C7: =Assumptions!B$4*C$6 -> 1982142.9 | D7: =Assumptions!B$4*D$6 -> 1982142.9 | E7: =Assumptions!B$4*E$6 -> 2279464.3 | F7: =Assumptions!B$4*F$6 -> 2279464.3 | G7: =Assumptions!B$4*G$6 -> 2279464.3 | H7: =Assumptions!B$4*H$6 -> 2675892.9 | I7: =Assumptions!B$4*I$6 -> 2675892.9 | J7: =Assumptions!B$4*J$6 -> 2675892.9 | K7: =Assumptions!B$4*K$6 -> 2973214.3 | L7: =Assumptions!B$4*L$6 -> 2973214.3 | M7: =Assumptions!B$4*M$6 -> 2973214.3 | N7: =Assumptions!C$4*N$6 -> 35166667 | O7: =Assumptions!C$4*O$6 -> 35166667 | P7: =Assumptions!C$4*P$6 -> 35166667 | Q7: =Assumptions!C$4*Q$6 -> 40441667 | R7: =Assumptions!C$4*R$6 -> 40441667 | S7: =Assumptions!C$4*S$6 -> 40441667 | T7: =Assumptions!C$4*T$6 -> 47475000 | U7: =Assumptions!C$4*U$6 -> 47475000 | V7: =Assumptions!C$4*V$6 -> 47475000 | W7: =Assumptions!C$4*W$6 -> 52750000 | X7: =Assumptions!C$4*X$6 -> 52750000 | Y7: =Assumptions!C$4*Y$6 -> 52750000 | Z7: =Assumptions!D$4*Z$6 -> 46666667 | AA7: =Assumptions!D$4*AA$6 -> 46666667 | AB7: =Assumptions!D$4*AB$6 -> 46666667 | AC7: =Assumptions!D$4*AC$6 -> 53666667 | AD7: =Assumptions!D$4*AD$6 -> 53666667 | AE7: =Assumptions!D$4*AE$6 -> 53666667 | AF7: =Assumptions!D$4*AF$6 -> 63000000 | AG7: =Assumptions!D$4*AG$6 -> 63000000 | AH7: =Assumptions!D$4*AH$6 -> 63000000 | AI7: =Assumptions!D$4*AI$6 -> 70000000 | AJ7: =Assumptions!D$4*AJ$6 -> 70000000 | AK7: =Assumptions!D$4*AK$6 -> 70000000 | AL7: =Assumptions!E$4*AL$6 -> 90000000 | AM7: =Assumptions!E$4*AM$6 -> 90000000 | AN7: =Assumptions!E$4*AN$6 -> 90000000 | AO7: =Assumptions!E$4*AO$6 -> 103500000 | AP7: =Assumptions!E$4*AP$6 -> 103500000 | AQ7: =Assumptions!E$4*AQ$6 -> 103500000 | AR7: =Assumptions!E$4*AR$6 -> 121500000 | AS7: =Assumptions!E$4*AS$6 -> 121500000 | AT7: =Assumptions!E$4*AT$6 -> 121500000 | AU7: =Assumptions!E$4*AU$6 -> 135000000 | AV7: =Assumptions!E$4*AV$6 -> 135000000 | AW7: =Assumptions!E$4*AW$6 -> 135000000 | AX7: =Assumptions!F$4*AX$6 -> 1.6666667e+08 | AY7: =Assumptions!F$4*AY$6 -> 1.6666667e+08 | AZ7: =Assumptions!F$4*AZ$6 -> 1.6666667e+08 | BA7: =Assumptions!F$4*BA$6 -> 1.9166667e+08 | BB7: =Assumptions!F$4*BB$6 -> 1.9166667e+08 | BC7: =Assumptions!F$4*BC$6 -> 1.9166667e+08 | BD7: =Assumptions!F$4*BD$6 -> 225000000 | BE7: =Assumptions!F$4*BE$6 -> 225000000 | BF7: =Assumptions!F$4*BF$6 -> 225000000 | BG7: =Assumptions!F$4*BG$6 -> 250000000 | BH7: =Assumptions!F$4*BH$6 -> 250000000 | BI7: =Assumptions!F$4*BI$6 -> 250000000
A8: المنح المتاح ضمن الخطة التمويلية | B8: =Assumptions!B$5*B$6 -> 0 | C8: =Assumptions!B$5*C$6 -> 1982142.9 | D8: =Assumptions!B$5*D$6 -> 1982142.9 | E8: =Assumptions!B$5*E$6 -> 2279464.3 | F8: =Assumptions!B$5*F$6 -> 2279464.3 | G8: =Assumptions!B$5*G$6 -> 2279464.3 | H8: =Assumptions!B$5*H$6 -> 2675892.9 | I8: =Assumptions!B$5*I$6 -> 2675892.9 | J8: =Assumptions!B$5*J$6 -> 2675892.9 | K8: =Assumptions!B$5*K$6 -> 2973214.3 | L8: =Assumptions!B$5*L$6 -> 2973214.3 | M8: =Assumptions!B$5*M$6 -> 2973214.3 | N8: =Assumptions!C$5*N$6 -> 35166667 | O8: =Assumptions!C$5*O$6 -> 35166667 | P8: =Assumptions!C$5*P$6 -> 35166667 | Q8: =Assumptions!C$5*Q$6 -> 40441667 | R8: =Assumptions!C$5*R$6 -> 40441667 | S8: =Assumptions!C$5*S$6 -> 40441667 | T8: =Assumptions!C$5*T$6 -> 47475000 | U8: =Assumptions!C$5*U$6 -> 47475000 | V8: =Assumptions!C$5*V$6 -> 47475000 | W8: =Assumptions!C$5*W$6 -> 52750000 | X8: =Assumptions!C$5*X$6 -> 52750000 | Y8: =Assumptions!C$5*Y$6 -> 52750000 | Z8: =Assumptions!D$5*Z$6 -> 46666667 | AA8: =Assumptions!D$5*AA$6 -> 46666667 | AB8: =Assumptions!D$5*AB$6 -> 46666667 | AC8: =Assumptions!D$5*AC$6 -> 53666667 | AD8: =Assumptions!D$5*AD$6 -> 53666667 | AE8: =Assumptions!D$5*AE$6 -> 53666667 | AF8: =Assumptions!D$5*AF$6 -> 63000000 | AG8: =Assumptions!D$5*AG$6 -> 63000000 | AH8: =Assumptions!D$5*AH$6 -> 63000000 | AI8: =Assumptions!D$5*AI$6 -> 70000000 | AJ8: =Assumptions!D$5*AJ$6 -> 70000000 | AK8: =Assumptions!D$5*AK$6 -> 70000000 | AL8: =Assumptions!E$5*AL$6 -> 90000000 | AM8: =Assumptions!E$5*AM$6 -> 90000000 | AN8: =Assumptions!E$5*AN$6 -> 90000000 | AO8: =Assumptions!E$5*AO$6 -> 103500000 | AP8: =Assumptions!E$5*AP$6 -> 103500000 | AQ8: =Assumptions!E$5*AQ$6 -> 103500000 | AR8: =Assumptions!E$5*AR$6 -> 121500000 | AS8: =Assumptions!E$5*AS$6 -> 121500000 | AT8: =Assumptions!E$5*AT$6 -> 121500000 | AU8: =Assumptions!E$5*AU$6 -> 135000000 | AV8: =Assumptions!E$5*AV$6 -> 135000000 | AW8: =Assumptions!E$5*AW$6 -> 135000000 | AX8: =Assumptions!F$5*AX$6 -> 1.6666667e+08 | AY8: =Assumptions!F$5*AY$6 -> 1.6666667e+08 | AZ8: =Assumptions!F$5*AZ$6 -> 1.6666667e+08 | BA8: =Assumptions!F$5*BA$6 -> 1.9166667e+08 | BB8: =Assumptions!F$5*BB$6 -> 1.9166667e+08 | BC8: =Assumptions!F$5*BC$6 -> 1.9166667e+08 | BD8: =Assumptions!F$5*BD$6 -> 225000000 | BE8: =Assumptions!F$5*BE$6 -> 225000000 | BF8: =Assumptions!F$5*BF$6 -> 225000000 | BG8: =Assumptions!F$5*BG$6 -> 250000000 | BH8: =Assumptions!F$5*BH$6 -> 250000000 | BI8: =Assumptions!F$5*BI$6 -> 250000000
A9: المنح المستخدم في جداول المحفظة | B9: =Assumptions!B$4*B$6 -> 0 | C9: =Assumptions!B$4*C$6 -> 1982142.9 | D9: =Assumptions!B$4*D$6 -> 1982142.9 | E9: =Assumptions!B$4*E$6 -> 2279464.3 | F9: =Assumptions!B$4*F$6 -> 2279464.3 | G9: =Assumptions!B$4*G$6 -> 2279464.3 | H9: =Assumptions!B$4*H$6 -> 2675892.9 | I9: =Assumptions!B$4*I$6 -> 2675892.9 | J9: =Assumptions!B$4*J$6 -> 2675892.9 | K9: =Assumptions!B$4*K$6 -> 2973214.3 | L9: =Assumptions!B$4*L$6 -> 2973214.3 | M9: =Assumptions!B$4*M$6 -> 2973214.3 | N9: =Assumptions!C$4*N$6 -> 35166667 | O9: =Assumptions!C$4*O$6 -> 35166667 | P9: =Assumptions!C$4*P$6 -> 35166667 | Q9: =Assumptions!C$4*Q$6 -> 40441667 | R9: =Assumptions!C$4*R$6 -> 40441667 | S9: =Assumptions!C$4*S$6 -> 40441667 | T9: =Assumptions!C$4*T$6 -> 47475000 | U9: =Assumptions!C$4*U$6 -> 47475000 | V9: =Assumptions!C$4*V$6 -> 47475000 | W9: =Assumptions!C$4*W$6 -> 52750000 | X9: =Assumptions!C$4*X$6 -> 52750000 | Y9: =Assumptions!C$4*Y$6 -> 52750000 | Z9: =Assumptions!D$4*Z$6 -> 46666667 | AA9: =Assumptions!D$4*AA$6 -> 46666667 | AB9: =Assumptions!D$4*AB$6 -> 46666667 | AC9: =Assumptions!D$4*AC$6 -> 53666667 | AD9: =Assumptions!D$4*AD$6 -> 53666667 | AE9: =Assumptions!D$4*AE$6 -> 53666667 | AF9: =Assumptions!D$4*AF$6 -> 63000000 | AG9: =Assumptions!D$4*AG$6 -> 63000000 | AH9: =Assumptions!D$4*AH$6 -> 63000000 | AI9: =Assumptions!D$4*AI$6 -> 70000000 | AJ9: =Assumptions!D$4*AJ$6 -> 70000000 | AK9: =Assumptions!D$4*AK$6 -> 70000000 | AL9: =Assumptions!E$4*AL$6 -> 90000000 | AM9: =Assumptions!E$4*AM$6 -> 90000000 | AN9: =Assumptions!E$4*AN$6 -> 90000000 | AO9: =Assumptions!E$4*AO$6 -> 103500000 | AP9: =Assumptions!E$4*AP$6 -> 103500000 | AQ9: =Assumptions!E$4*AQ$6 -> 103500000 | AR9: =Assumptions!E$4*AR$6 -> 121500000 | AS9: =Assumptions!E$4*AS$6 -> 121500000 | AT9: =Assumptions!E$4*AT$6 -> 121500000 | AU9: =Assumptions!E$4*AU$6 -> 135000000 | AV9: =Assumptions!E$4*AV$6 -> 135000000 | AW9: =Assumptions!E$4*AW$6 -> 135000000 | AX9: =Assumptions!F$4*AX$6 -> 1.6666667e+08 | AY9: =Assumptions!F$4*AY$6 -> 1.6666667e+08 | AZ9: =Assumptions!F$4*AZ$6 -> 1.6666667e+08 | BA9: =Assumptions!F$4*BA$6 -> 1.9166667e+08 | BB9: =Assumptions!F$4*BB$6 -> 1.9166667e+08 | BC9: =Assumptions!F$4*BC$6 -> 1.9166667e+08 | BD9: =Assumptions!F$4*BD$6 -> 225000000 | BE9: =Assumptions!F$4*BE$6 -> 225000000 | BF9: =Assumptions!F$4*BF$6 -> 225000000 | BG9: =Assumptions!F$4*BG$6 -> 250000000 | BH9: =Assumptions!F$4*BH$6 -> 250000000 | BI9: =Assumptions!F$4*BI$6 -> 250000000
A10: هامش تمويلي غير مستخدم | B10: =0 -> 0 | C10: =0 -> 0 | D10: =0 -> 0 | E10: =0 -> 0 | F10: =0 -> 0 | G10: =0 -> 0 | H10: =0 -> 0 | I10: =0 -> 0 | ... BI10: =0 -> 0
A11: عدد العقود | B11: =ROUND(Assumptions!B77*B$6,0) -> 0 | C11: =ROUND(Assumptions!B77*C$6,0) -> 13 | D11: =ROUND(Assumptions!B77*D$6,0) -> 13 | E11: =ROUND(Assumptions!B77*E$6,0) -> 15 | F11: =ROUND(Assumptions!B77*F$6,0) -> 15 | G11: =ROUND(Assumptions!B77*G$6,0) -> 15 | H11: =ROUND(Assumptions!B77*H$6,0) -> 18 | I11: =ROUND(Assumptions!B77*I$6,0) -> 18 | J11: =ROUND(Assumptions!B77*J$6,0) -> 18 | K11: =ROUND(Assumptions!B77*K$6,0) -> 20 | L11: =ROUND(Assumptions!B77*L$6,0) -> 20 | M11: =Assumptions!B77-SUM(B11:L11) -> 20 | N11: =ROUND(Assumptions!C77*N$6,0) -> 111 | O11: =ROUND(Assumptions!C77*O$6,0) -> 111 | P11: =ROUND(Assumptions!C77*P$6,0) -> 111 | Q11: =ROUND(Assumptions!C77*Q$6,0) -> 128 | R11: =ROUND(Assumptions!C77*R$6,0) -> 128 | S11: =ROUND(Assumptions!C77*S$6,0) -> 128 | T11: =ROUND(Assumptions!C77*T$6,0) -> 150 | U11: =ROUND(Assumptions!C77*U$6,0) -> 150 | V11: =ROUND(Assumptions!C77*V$6,0) -> 150 | W11: =ROUND(Assumptions!C77*W$6,0) -> 167 | X11: =ROUND(Assumptions!C77*X$6,0) -> 167 | Y11: =Assumptions!C77-SUM(N11:X11) -> 169 | Z11: =ROUND(Assumptions!D77*Z$6,0) -> 53 | AA11: =ROUND(Assumptions!D77*AA$6,0) -> 53 | AB11: =ROUND(Assumptions!D77*AB$6,0) -> 53 | AC11: =ROUND(Assumptions!D77*AC$6,0) -> 60 | AD11: =ROUND(Assumptions!D77*AD$6,0) -> 60 | AE11: =ROUND(Assumptions!D77*AE$6,0) -> 60 | AF11: =ROUND(Assumptions!D77*AF$6,0) -> 71 | AG11: =ROUND(Assumptions!D77*AG$6,0) -> 71 | AH11: =ROUND(Assumptions!D77*AH$6,0) -> 71 | AI11: =ROUND(Assumptions!D77*AI$6,0) -> 79 | AJ11: =ROUND(Assumptions!D77*AJ$6,0) -> 79 | AK11: =Assumptions!D77-SUM(Z11:AJ11) -> 78 | AL11: =ROUND(Assumptions!E77*AL$6,0) -> 82 | AM11: =ROUND(Assumptions!E77*AM$6,0) -> 82 | AN11: =ROUND(Assumptions!E77*AN$6,0) -> 82 | AO11: =ROUND(Assumptions!E77*AO$6,0) -> 94 | AP11: =ROUND(Assumptions!E77*AP$6,0) -> 94 | AQ11: =ROUND(Assumptions!E77*AQ$6,0) -> 94 | AR11: =ROUND(Assumptions!E77*AR$6,0) -> 110 | AS11: =ROUND(Assumptions!E77*AS$6,0) -> 110 | AT11: =ROUND(Assumptions!E77*AT$6,0) -> 110 | AU11: =ROUND(Assumptions!E77*AU$6,0) -> 123 | AV11: =ROUND(Assumptions!E77*AV$6,0) -> 123 | AW11: =Assumptions!E77-SUM(AL11:AV11) -> 123 | AX11: =ROUND(Assumptions!F77*AX$6,0) -> 123 | AY11: =ROUND(Assumptions!F77*AY$6,0) -> 123 | AZ11: =ROUND(Assumptions!F77*AZ$6,0) -> 123 | BA11: =ROUND(Assumptions!F77*BA$6,0) -> 142 | BB11: =ROUND(Assumptions!F77*BB$6,0) -> 142 | BC11: =ROUND(Assumptions!F77*BC$6,0) -> 142 | BD11: =ROUND(Assumptions!F77*BD$6,0) -> 167 | BE11: =ROUND(Assumptions!F77*BE$6,0) -> 167 | BF11: =ROUND(Assumptions!F77*BF$6,0) -> 167 | BG11: =ROUND(Assumptions!F77*BG$6,0) -> 185 | BH11: =ROUND(Assumptions!F77*BH$6,0) -> 185 | BI11: =Assumptions!F77-SUM(AX11:BH11) -> 186
A12: Quarterly Origination Summary
A13: Quarter | B13: Year 1 | C13: Year 2 | D13: Year 3 | E13: Year 4 | F13: Year 5
A14: الربع الأول (Q1) | B14: =SUM(B7:D7) -> 3964285.7 | C14: =SUM(N7:P7) -> 105500000 | D14: =SUM(Z7:AB7) -> 140000000 | E14: =SUM(AL7:AN7) -> 270000000 | F14: =SUM(AX7:AZ7) -> 500000000
A15: الربع الثاني (Q2) | B15: =SUM(E7:G7) -> 6838392.9 | C15: =SUM(Q7:S7) -> 121325000 | D15: =SUM(AC7:AE7) -> 161000000 | E15: =SUM(AO7:AQ7) -> 310500000 | F15: =SUM(BA7:BC7) -> 575000000
A16: الربع الثالث (Q3) | B16: =SUM(H7:J7) -> 8027678.6 | C16: =SUM(T7:V7) -> 142425000 | D16: =SUM(AF7:AH7) -> 189000000 | E16: =SUM(AR7:AT7) -> 364500000 | F16: =SUM(BD7:BF7) -> 675000000
A17: الربع الرابع (Q4) | B17: =SUM(K7:M7) -> 8919642.9 | C17: =SUM(W7:Y7) -> 158250000 | D17: =SUM(AI7:AK7) -> 210000000 | E17: =SUM(AU7:AW7) -> 405000000 | F17: =SUM(BG7:BI7) -> 750000000
A18: الإجمالي | B18: =SUM(B14:B17) -> 27750000 | C18: =SUM(C14:C17) -> 527500000 | D18: =SUM(D14:D17) -> 700000000 | E18: =SUM(E14:E17) -> 1350000000 | F18: =SUM(F14:F17) -> 2500000000
A19: Year 4 | B19: =SUM(AL9:AN9)/1000000 -> 270 | C19: =SUM(AO9:AQ9)/1000000 -> 310.5 | D19: =SUM(AR9:AT9)/1000000 -> 364.5 | E19: =SUM(AU9:AW9)/1000000 -> 405 | F19: =SUM(B19:E19) -> 1350
A20: Year 5 | B20: =SUM(AX9:AZ9)/1000000 -> 500 | C20: =SUM(BA9:BC9)/1000000 -> 575 | D20: =SUM(BD9:BF9)/1000000 -> 675 | E20: =SUM(BG9:BI9)/1000000 -> 750 | F20: =SUM(B20:E20) -> 2500

Sheet Cohort Principal
A1: جدول تطور أصل المحفظة
A3: البند | B3: Year 1 | C3: Year 2 | D3: Year 3 | E3: Year 4 | F3: Year 5
A4: رصيد أول السنة | B4: =0 -> 0 | C4: =B7 -> 20672304 | D4: =C7 -> 4.5260222e+08 | E4: =D7 -> 8.6656133e+08 | F4: =E7 -> 1.6674368e+09
A5: الأصل الممول من المنح | B5: =Assumptions!B76*(1-Assumptions!$B$25) -> 23587500 | C5: =Assumptions!C76*(1-Assumptions!$B$25) -> 448375000 | D5: =Assumptions!D76*(1-Assumptions!$B$25) -> 595000000 | E5: =Assumptions!E76*(1-Assumptions!$B$25) -> 1147500000 | F5: =Assumptions!F76*(1-Assumptions!$B$25) -> 2125000000
A6: تحصيل/استنفاد أصل المحفظة | B6: =B4+B5-Assumptions!B79 -> 2915195.9 | C6: =C4+C5-Assumptions!C79 -> 16445084 | D6: =D4+D5-Assumptions!D79 -> 1.8104089e+08 | E6: =E4+E5-Assumptions!E79 -> 3.4662453e+08 | F6: =F4+F5-Assumptions!F79 -> 6.6697472e+08
A7: رصيد آخر السنة | B7: =B4+B5-B6 -> 20672304 | C7: =C4+C5-C6 -> 4.5260222e+08 | D7: =D4+D5-D6 -> 8.6656133e+08 | E7: =E4+E5-E6 -> 1.6674368e+09 | F7: =F4+F5-F6 -> 3.1254621e+09
A8: اختبار الربط | B8: =B7-'Balance Sheet'!B6 -> 0 | C8: =C7-'Balance Sheet'!C6 -> 0 | D8: =D7-'Balance Sheet'!D6 -> 0 | E8: =E7-'Balance Sheet'!E6 -> 0 | F8: =F7-'Balance Sheet'!F6 -> 0

Sheet Cohort Interest
A1: جدول احتساب عوائد التأجير
A3: البند | B3: Year 1 | C3: Year 2 | D3: Year 3 | E3: Year 4 | F3: Year 5
A4: رصيد أول السنة | B4: =0 -> 0 | C4: ='Balance Sheet'!B6 -> 20672304 | D4: ='Balance Sheet'!C6 -> 4.5260222e+08 | E4: ='Balance Sheet'!D6 -> 8.6656133e+08 | F4: ='Balance Sheet'!E6 -> 1.6674368e+09
A5: رصيد آخر السنة | B5: ='Balance Sheet'!B6 -> 20672304 | C5: ='Balance Sheet'!C6 -> 4.5260222e+08 | D5: ='Balance Sheet'!D6 -> 8.6656133e+08 | E5: ='Balance Sheet'!E6 -> 1.6674368e+09 | F5: ='Balance Sheet'!F6 -> 3.1254621e+09
A6: متوسط المحفظة | B6: =AVERAGE(B4,B5) -> 10336152 | C6: =AVERAGE(C4,C5) -> 2.3663726e+08 | D6: =AVERAGE(D4,D5) -> 6.5958178e+08 | E6: =AVERAGE(E4,E5) -> 1.2669991e+09 | F6: =AVERAGE(F4,F5) -> 2.3964494e+09
A7: العائد السنوي | B7: =Assumptions!B6 -> 0.34 | C7: =Assumptions!C6 -> 0.32 | D7: =Assumptions!D6 -> 0.3 | E7: =Assumptions!E6 -> 0.28 | F7: =Assumptions!F6 -> 0.26
A8: عوائد التأجير | B8: 3538848 | C8: 45873640 | D8: =D6*D7 -> 1.9787453e+08 | E8: =E6*E7 -> 3.5475974e+08 | F8: =F6*F7 -> 6.2307685e+08
A9: منهجية الاحتساب | B9: مدخل خطة Year 1 المعتمدة - لا يوجد جدول EIR/عقود شهري مستقل | C9: مدخل خطة Year 2 المعتمدة - لا يوجد جدول EIR/عقود شهري مستقل | D9: متوسط المحفظة × العائد | E9: متوسط المحفظة × العائد | F9: متوسط المحفظة × العائد
A10: العائد الضمني على متوسط المحفظة | B10: =IFERROR(B8/B6,0) -> 0.34237576 | C10: =IFERROR(C8/C6,0) -> 0.19385637 | D10: =IFERROR(D8/D6,0) -> 0.3 | E10: =IFERROR(E8/E6,0) -> 0.28 | F10: =IFERROR(F8/F6,0) -> 0.26

Sheet Cohort Fees
A1: جدول رسوم الخدمات
A3: البند | B3: Year 1 | C3: Year 2 | D3: Year 3 | E3: Year 4 | F3: Year 5
A4: المنح السنوي | B4: =Assumptions!B76 -> 27750000 | C4: =Assumptions!C76 -> 527500000 | D4: =Assumptions!D76 -> 700000000 | E4: =Assumptions!E76 -> 1350000000 | F4: =Assumptions!F76 -> 2500000000
A5: نسبة الرسوم | B5: =Assumptions!B26 -> 0.05 | C5: =Assumptions!C26 -> 0.07 | D5: =Assumptions!D26 -> 0.06 | E5: =Assumptions!E26 -> 0.06 | F5: =Assumptions!F26 -> 0.06
A6: إجمالي الرسوم المحصلة | B6: =B4*B5 -> 1387500 | C6: =C4*C5 -> 36925000 | D6: =D4*D5 -> 42000000 | E6: =E4*E5 -> 81000000 | F6: =F4*F5 -> 150000000
A7: إيرادات الرسوم الإدارية المعتمدة - خطة الإدارة | B7: =Assumptions!B81 -> 1387500 | C7: =Assumptions!C81 -> 36925000 | D7: =Assumptions!D81 -> 42000000 | E7: =Assumptions!E81 -> 81000000 | F7: =Assumptions!F81 -> 150000000
A8: دعم تشغيلي / إيرادات خدمات مساندة أخرى | B8: ='Income Statement'!B13 -> 3118262.4 | C8: ='Income Statement'!C13 -> 0 | D8: ='Income Statement'!D13 -> 5600000 | E8: ='Income Statement'!E13 -> 10800000 | F8: ='Income Statement'!F13 -> 20000000

Sheet Monthly Model
A1: Liquidity and Funding Model - 60 Planning Periods
A3: Period | B3: 46388 | C3: 46419 | D3: 46447 | E3: 46478 | F3: 46508 | G3: 46539 | H3: 46569 | I3: 46600 | J3: 46631 | K3: 46661 | L3: 46692 | M3: 46722 | N3: 46753 | O3: 46784 | P3: 46813 | Q3: 46844 | R3: 46874 | S3: 46905 | T3: 46935 | U3: 46966 | V3: 46997 | W3: 47027 | X3: 47058 | Y3: 47088 | Z3: 47119 | AA3: 47150 | AB3: 47178 | AC3: 47209 | AD3: 47239 | AE3: 47270 | AF3: 47300 | AG3: 47331 | AH3: 47362 | AI3: 47392 | AJ3: 47423 | AK3: 47453 | AL3: 47484 | AM3: 47515 | AN3: 47543 | AO3: 47574 | AP3: 47604 | AQ3: 47635 | AR3: 47665 | AS3: 47696 | AT3: 47727 | AU3: 47757 | AV3: 47788 | AW3: 47818 | AX3: 47849 | AY3: 47880 | AZ3: 47908 | BA3: 47939 | BB3: 47969 | BC3: 48000 | BD3: 48030 | BE3: 48061 | BF3: 48092 | BG3: 48122 | BH3: 48153 | BI3: 48183
A4: Plan Year | B4: 2027 | C4: 2027 | D4: 2027 | E4: 2027 | F4: 2027 | G4: 2027 | H4: 2027 | I4: 2027 | J4: 2027 | K4: 2027 | L4: 2027 | M4: 2027 | N4: 2028 | O4: 2028 | P4: 2028 | Q4: 2028 | R4: 2028 | S4: 2028 | T4: 2028 | U4: 2028 | V4: 2028 | W4: 2028 | X4: 2028 | Y4: 2028 | Z4: 2029 | AA4: 2029 | AB4: 2029 | AC4: 2029 | AD4: 2029 | AE4: 2029 | AF4: 2029 | AG4: 2029 | AH4: 2029 | AI4: 2029 | AJ4: 2029 | AK4: 2029 | AL4: 2030 | AM4: 2030 | AN4: 2030 | AO4: 2030 | AP4: 2030 | AQ4: 2030 | AR4: 2030 | AS4: 2030 | AT4: 2030 | AU4: 2030 | AV4: 2030 | AW4: 2030 | AX4: 2031 | AY4: 2031 | AZ4: 2031 | BA4: 2031 | BB4: 2031 | BC4: 2031 | BD4: 2031 | BE4: 2031 | BF4: 2031 | BG4: 2031 | BH4: 2031 | BI4: 2031
A5: Period Sequence | B5: 1 | C5: 2 | D5: 3 | E5: 4 | F5: 5 | G5: 6 | H5: 7 | I5: 8 | J5: 9 | K5: 10 | L5: 11 | M5: 12 | N5: 13 | O5: 14 | P5: 15 | Q5: 16 | R5: 17 | S5: 18 | T5: 19 | U5: 20 | V5: 21 | W5: 22 | X5: 23 | Y5: 24 | Z5: 25 | AA5: 26 | AB5: 27 | AC5: 28 | AD5: 29 | AE5: 30 | AF5: 31 | AG5: 32 | AH5: 33 | AI5: 34 | AJ5: 35 | AK5: 36 | AL5: 37 | AM5: 38 | AN5: 39 | AO5: 40 | AP5: 41 | AQ5: 42 | AR5: 43 | AS5: 44 | AT5: 45 | AU5: 46 | AV5: 47 | AW5: 48 | AX5: 49 | AY5: 50 | AZ5: 51 | BA5: 52 | BB5: 53 | BC5: 54 | BD5: 55 | BE5: 56 | BF5: 57 | BG5: 58 | BH5: 59 | BI5: 60
A6: وزن الشهر | B6: =Originations!B6 -> 0 | C6: =Originations!C6 -> 0.071428571 | D6: =Originations!D6 -> 0.071428571 | E6: =Originations!E6 -> 0.082142857 | F6: =Originations!F6 -> 0.082142857 | G6: =Originations!G6 -> 0.082142857 | H6: =Originations!H6 -> 0.096428571 | I6: =Originations!I6 -> 0.096428571 | ... BI6: =Originations!BI6 -> 0.1
A8: المنح المخطط | B8: =Originations!B7 -> 0 | C8: =Originations!C7 -> 1982142.9 | D8: =Originations!D7 -> 1982142.9 | E8: =Originations!E7 -> 2279464.3 | F8: =Originations!F7 -> 2279464.3 | G8: =Originations!G7 -> 2279464.3 | H8: =Originations!H7 -> 2675892.9 | I8: =Originations!I7 -> 2675892.9 | ... BI8: =Originations!BI7 -> 250000000
A10: صافي الربح | B10: ='Cash Flow'!B5*B6 -> 0 | C10: ='Cash Flow'!B5*C6 -> -583347.91 | D10: ='Cash Flow'!B5*D6 -> -583347.91 | E10: ='Cash Flow'!B5*E6 -> -670850.1 | F10: ='Cash Flow'!B5*F6 -> -670850.1 | G10: ='Cash Flow'!B5*G6 -> -670850.1 | H10: ='Cash Flow'!B5*H6 -> -787519.68 | I10: ='Cash Flow'!B5*I6 -> -787519.68 | J10: ='Cash Flow'!B5*J6 -> -787519.68 | K10: ='Cash Flow'!B5*K6 -> -875021.87 | L10: ='Cash Flow'!B5*L6 -> -875021.87 | M10: ='Cash Flow'!B5*M6 -> -875021.87 | N10: ='Cash Flow'!C5*N6 -> 616907.74 | O10: ='Cash Flow'!C5*O6 -> 616907.74 | P10: ='Cash Flow'!C5*P6 -> 616907.74 | Q10: ='Cash Flow'!C5*Q6 -> 709443.9 | R10: ='Cash Flow'!C5*R6 -> 709443.9 | S10: ='Cash Flow'!C5*S6 -> 709443.9 | T10: ='Cash Flow'!C5*T6 -> 832825.45 | U10: ='Cash Flow'!C5*U6 -> 832825.45 | V10: ='Cash Flow'!C5*V6 -> 832825.45 | W10: ='Cash Flow'!C5*W6 -> 925361.61 | X10: ='Cash Flow'!C5*X6 -> 925361.61 | Y10: ='Cash Flow'!C5*Y6 -> 925361.61 | Z10: ='Cash Flow'!D5*Z6 -> 5116754.1 | AA10: ='Cash Flow'!D5*AA6 -> 5116754.1 | AB10: ='Cash Flow'!D5*AB6 -> 5116754.1 | AC10: ='Cash Flow'!D5*AC6 -> 5884267.2 | AD10: ='Cash Flow'!D5*AD6 -> 5884267.2 | AE10: ='Cash Flow'!D5*AE6 -> 5884267.2 | AF10: ='Cash Flow'!D5*AF6 -> 6907618 | AG10: ='Cash Flow'!D5*AG6 -> 6907618 | AH10: ='Cash Flow'!D5*AH6 -> 6907618 | AI10: ='Cash Flow'!D5*AI6 -> 7675131.2 | AJ10: ='Cash Flow'!D5*AJ6 -> 7675131.2 | AK10: ='Cash Flow'!D5*AK6 -> 7675131.2 | AL10: ='Cash Flow'!E5*AL6 -> 10662722 | AM10: ='Cash Flow'!E5*AM6 -> 10662722 | AN10: ='Cash Flow'!E5*AN6 -> 10662722 | AO10: ='Cash Flow'!E5*AO6 -> 12262131 | AP10: ='Cash Flow'!E5*AP6 -> 12262131 | AQ10: ='Cash Flow'!E5*AQ6 -> 12262131 | AR10: ='Cash Flow'!E5*AR6 -> 14394675 | AS10: ='Cash Flow'!E5*AS6 -> 14394675 | AT10: ='Cash Flow'!E5*AT6 -> 14394675 | AU10: ='Cash Flow'!E5*AU6 -> 15994083 | AV10: ='Cash Flow'!E5*AV6 -> 15994083 | AW10: ='Cash Flow'!E5*AW6 -> 15994083 | AX10: ='Cash Flow'!F5*AX6 -> 19317332 | AY10: ='Cash Flow'!F5*AY6 -> 19317332 | AZ10: ='Cash Flow'!F5*AZ6 -> 19317332 | BA10: ='Cash Flow'!F5*BA6 -> 22214932 | BB10: ='Cash Flow'!F5*BB6 -> 22214932 | BC10: ='Cash Flow'!F5*BC6 -> 22214932 | BD10: ='Cash Flow'!F5*BD6 -> 26078398 | BE10: ='Cash Flow'!F5*BE6 -> 26078398 | BF10: ='Cash Flow'!F5*BF6 -> 26078398 | BG10: ='Cash Flow'!F5*BG6 -> 28975998 | BH10: ='Cash Flow'!F5*BH6 -> 28975998 | BI10: ='Cash Flow'!F5*BI6 -> 28975998
A11: الإهلاك والاستهلاك (D&A) | B11: ='Cash Flow'!B6*B6 -> 0 | C11: ='Cash Flow'!B6*C6 -> 0 | D11: ='Cash Flow'!B6*D6 -> 0 | E11: ='Cash Flow'!B6*E6 -> 0 | F11: ='Cash Flow'!B6*F6 -> 0 | G11: ='Cash Flow'!B6*G6 -> 0 | H11: ='Cash Flow'!B6*H6 -> 0 | I11: ='Cash Flow'!B6*I6 -> 0 | J11: ='Cash Flow'!B6*J6 -> 0 | K11: ='Cash Flow'!B6*K6 -> 0 | L11: ='Cash Flow'!B6*L6 -> 0 | M11: ='Cash Flow'!B6*M6 -> 0 | N11: ='Cash Flow'!C6*N6 -> 0 | O11: ='Cash Flow'!C6*O6 -> 0 | P11: ='Cash Flow'!C6*P6 -> 0 | Q11: ='Cash Flow'!C6*Q6 -> 0 | R11: ='Cash Flow'!C6*R6 -> 0 | S11: ='Cash Flow'!C6*S6 -> 0 | T11: ='Cash Flow'!C6*T6 -> 0 | U11: ='Cash Flow'!C6*U6 -> 0 | V11: ='Cash Flow'!C6*V6 -> 0 | W11: ='Cash Flow'!C6*W6 -> 0 | X11: ='Cash Flow'!C6*X6 -> 0 | Y11: ='Cash Flow'!C6*Y6 -> 0 | Z11: ='Cash Flow'!D6*Z6 -> 66666.667 | AA11: ='Cash Flow'!D6*AA6 -> 66666.667 | AB11: ='Cash Flow'!D6*AB6 -> 66666.667 | AC11: ='Cash Flow'!D6*AC6 -> 76666.667 | AD11: ='Cash Flow'!D6*AD6 -> 76666.667 | AE11: ='Cash Flow'!D6*AE6 -> 76666.667 | AF11: ='Cash Flow'!D6*AF6 -> 90000 | AG11: ='Cash Flow'!D6*AG6 -> 90000 | AH11: ='Cash Flow'!D6*AH6 -> 90000 | AI11: ='Cash Flow'!D6*AI6 -> 100000 | AJ11: ='Cash Flow'!D6*AJ6 -> 100000 | AK11: ='Cash Flow'!D6*AK6 -> 100000 | AL11: ='Cash Flow'!E6*AL6 -> 100000 | AM11: ='Cash Flow'!E6*AM6 -> 100000 | AN11: ='Cash Flow'!E6*AN6 -> 100000 | AO11: ='Cash Flow'!E6*AO6 -> 115000 | AP11: ='Cash Flow'!E6*AP6 -> 115000 | AQ11: ='Cash Flow'!E6*AQ6 -> 115000 | AR11: ='Cash Flow'!E6*AR6 -> 135000 | AS11: ='Cash Flow'!E6*AS6 -> 135000 | AT11: ='Cash Flow'!E6*AT6 -> 135000 | AU11: ='Cash Flow'!E6*AU6 -> 150000 | AV11: ='Cash Flow'!E6*AV6 -> 150000 | AW11: ='Cash Flow'!E6*AW6 -> 150000 | AX11: ='Cash Flow'!F6*AX6 -> 133333.33 | AY11: ='Cash Flow'!F6*AY6 -> 133333.33 | AZ11: ='Cash Flow'!F6*AZ6 -> 133333.33 | BA11: ='Cash Flow'!F6*BA6 -> 153333.33 | BB11: ='Cash Flow'!F6*BB6 -> 153333.33 | BC11: ='Cash Flow'!F6*BC6 -> 153333.33 | BD11: ='Cash Flow'!F6*BD6 -> 180000 | BE11: ='Cash Flow'!F6*BE6 -> 180000 | BF11: ='Cash Flow'!F6*BF6 -> 180000 | BG11: ='Cash Flow'!F6*BG6 -> 200000 | BH11: ='Cash Flow'!F6*BH6 -> 200000 | BI11: ='Cash Flow'!F6*BI6 -> 200000
A12: الزيادة في المخصص | B12: ='Cash Flow'!B7*B6 -> 0 | C12: ='Cash Flow'!B7*C6 -> 44297.794 | D12: ='Cash Flow'!B7*D6 -> 44297.794 | E12: ='Cash Flow'!B7*E6 -> 50942.464 | F12: ='Cash Flow'!B7*F6 -> 50942.464 | G12: ='Cash Flow'!B7*G6 -> 50942.464 | H12: ='Cash Flow'!B7*H6 -> 59802.023 | I12: ='Cash Flow'!B7*I6 -> 59802.023 | J12: ='Cash Flow'!B7*J6 -> 59802.023 | K12: ='Cash Flow'!B7*K6 -> 66446.692 | L12: ='Cash Flow'!B7*L6 -> 66446.692 | M12: ='Cash Flow'!B7*M6 -> 66446.692 | N12: ='Cash Flow'!C7*N6 -> 863859.83 | O12: ='Cash Flow'!C7*O6 -> 863859.83 | P12: ='Cash Flow'!C7*P6 -> 863859.83 | Q12: ='Cash Flow'!C7*Q6 -> 993438.81 | R12: ='Cash Flow'!C7*R6 -> 993438.81 | S12: ='Cash Flow'!C7*S6 -> 993438.81 | T12: ='Cash Flow'!C7*T6 -> 1166210.8 | U12: ='Cash Flow'!C7*U6 -> 1166210.8 | V12: ='Cash Flow'!C7*V6 -> 1166210.8 | W12: ='Cash Flow'!C7*W6 -> 1295789.7 | X12: ='Cash Flow'!C7*X6 -> 1295789.7 | Y12: ='Cash Flow'!C7*Y6 -> 1295789.7 | Z12: ='Cash Flow'!D7*Z6 -> 827918.22 | AA12: ='Cash Flow'!D7*AA6 -> 827918.22 | AB12: ='Cash Flow'!D7*AB6 -> 827918.22 | AC12: ='Cash Flow'!D7*AC6 -> 952105.96 | AD12: ='Cash Flow'!D7*AD6 -> 952105.96 | AE12: ='Cash Flow'!D7*AE6 -> 952105.96 | AF12: ='Cash Flow'!D7*AF6 -> 1117689.6 | AG12: ='Cash Flow'!D7*AG6 -> 1117689.6 | AH12: ='Cash Flow'!D7*AH6 -> 1117689.6 | AI12: ='Cash Flow'!D7*AI6 -> 1241877.3 | AJ12: ='Cash Flow'!D7*AJ6 -> 1241877.3 | AK12: ='Cash Flow'!D7*AK6 -> 1241877.3 | AL12: ='Cash Flow'!E7*AL6 -> 1601750.9 | AM12: ='Cash Flow'!E7*AM6 -> 1601750.9 | AN12: ='Cash Flow'!E7*AN6 -> 1601750.9 | AO12: ='Cash Flow'!E7*AO6 -> 1842013.6 | AP12: ='Cash Flow'!E7*AP6 -> 1842013.6 | AQ12: ='Cash Flow'!E7*AQ6 -> 1842013.6 | AR12: ='Cash Flow'!E7*AR6 -> 2162363.8 | AS12: ='Cash Flow'!E7*AS6 -> 2162363.8 | AT12: ='Cash Flow'!E7*AT6 -> 2162363.8 | AU12: ='Cash Flow'!E7*AU6 -> 2402626.4 | AV12: ='Cash Flow'!E7*AV6 -> 2402626.4 | AW12: ='Cash Flow'!E7*AW6 -> 2402626.4 | AX12: ='Cash Flow'!F7*AX6 -> 2916050.6 | AY12: ='Cash Flow'!F7*AY6 -> 2916050.6 | AZ12: ='Cash Flow'!F7*AZ6 -> 2916050.6 | BA12: ='Cash Flow'!F7*BA6 -> 3353458.1 | BB12: ='Cash Flow'!F7*BB6 -> 3353458.1 | BC12: ='Cash Flow'!F7*BC6 -> 3353458.1 | BD12: ='Cash Flow'!F7*BD6 -> 3936668.3 | BE12: ='Cash Flow'!F7*BE6 -> 3936668.3 | BF12: ='Cash Flow'!F7*BF6 -> 3936668.3 | BG12: ='Cash Flow'!F7*BG6 -> 4374075.8 | BH12: ='Cash Flow'!F7*BH6 -> 4374075.8 | BI12: ='Cash Flow'!F7*BI6 -> 4374075.8
A13: الزيادة في المحفظة | B13: ='Cash Flow'!B8*B6 -> 0 | C13: ='Cash Flow'!B8*C6 -> -1476593.1 | D13: ='Cash Flow'!B8*D6 -> -1476593.1 | E13: ='Cash Flow'!B8*E6 -> -1698082.1 | F13: ='Cash Flow'!B8*F6 -> -1698082.1 | G13: ='Cash Flow'!B8*G6 -> -1698082.1 | H13: ='Cash Flow'!B8*H6 -> -1993400.8 | I13: ='Cash Flow'!B8*I6 -> -1993400.8 | J13: ='Cash Flow'!B8*J6 -> -1993400.8 | K13: ='Cash Flow'!B8*K6 -> -2214889.7 | L13: ='Cash Flow'!B8*L6 -> -2214889.7 | M13: ='Cash Flow'!B8*M6 -> -2214889.7 | N13: ='Cash Flow'!C8*N6 -> -28795328 | O13: ='Cash Flow'!C8*O6 -> -28795328 | P13: ='Cash Flow'!C8*P6 -> -28795328 | Q13: ='Cash Flow'!C8*Q6 -> -33114627 | R13: ='Cash Flow'!C8*R6 -> -33114627 | S13: ='Cash Flow'!C8*S6 -> -33114627 | T13: ='Cash Flow'!C8*T6 -> -38873692 | U13: ='Cash Flow'!C8*U6 -> -38873692 | V13: ='Cash Flow'!C8*V6 -> -38873692 | W13: ='Cash Flow'!C8*W6 -> -43192992 | X13: ='Cash Flow'!C8*X6 -> -43192992 | Y13: ='Cash Flow'!C8*Y6 -> -43192992 | Z13: ='Cash Flow'!D8*Z6 -> -27597274 | AA13: ='Cash Flow'!D8*AA6 -> -27597274 | AB13: ='Cash Flow'!D8*AB6 -> -27597274 | AC13: ='Cash Flow'!D8*AC6 -> -31736865 | AD13: ='Cash Flow'!D8*AD6 -> -31736865 | AE13: ='Cash Flow'!D8*AE6 -> -31736865 | AF13: ='Cash Flow'!D8*AF6 -> -37256320 | AG13: ='Cash Flow'!D8*AG6 -> -37256320 | AH13: ='Cash Flow'!D8*AH6 -> -37256320 | AI13: ='Cash Flow'!D8*AI6 -> -41395911 | AJ13: ='Cash Flow'!D8*AJ6 -> -41395911 | AK13: ='Cash Flow'!D8*AK6 -> -41395911 | AL13: ='Cash Flow'!E8*AL6 -> -53391698 | AM13: ='Cash Flow'!E8*AM6 -> -53391698 | AN13: ='Cash Flow'!E8*AN6 -> -53391698 | AO13: ='Cash Flow'!E8*AO6 -> -61400452 | AP13: ='Cash Flow'!E8*AP6 -> -61400452 | AQ13: ='Cash Flow'!E8*AQ6 -> -61400452 | AR13: ='Cash Flow'!E8*AR6 -> -72078792 | AS13: ='Cash Flow'!E8*AS6 -> -72078792 | AT13: ='Cash Flow'!E8*AT6 -> -72078792 | AU13: ='Cash Flow'!E8*AU6 -> -80087547 | AV13: ='Cash Flow'!E8*AV6 -> -80087547 | AW13: ='Cash Flow'!E8*AW6 -> -80087547 | AX13: ='Cash Flow'!F8*AX6 -> -97201685 | AY13: ='Cash Flow'!F8*AY6 -> -97201685 | AZ13: ='Cash Flow'!F8*AZ6 -> -97201685 | BA13: ='Cash Flow'!F8*BA6 -> -1.1178194e+08 | BB13: ='Cash Flow'!F8*BB6 -> -1.1178194e+08 | BC13: ='Cash Flow'!F8*BC6 -> -1.1178194e+08 | BD13: ='Cash Flow'!F8*BD6 -> -1.3122228e+08 | BE13: ='Cash Flow'!F8*BE6 -> -1.3122228e+08 | BF13: ='Cash Flow'!F8*BF6 -> -1.3122228e+08 | BG13: ='Cash Flow'!F8*BG6 -> -1.4580253e+08 | BH13: ='Cash Flow'!F8*BH6 -> -1.4580253e+08 | BI13: ='Cash Flow'!F8*BI6 -> -1.4580253e+08
A14: التغير في مقدمات العملاء والالتزامات | B14: ='Cash Flow'!B9*B6 -> 0 | C14: ='Cash Flow'!B9*C6 -> 428571.43 | D14: ='Cash Flow'!B9*D6 -> 428571.43 | E14: ='Cash Flow'!B9*E6 -> 492857.14 | F14: ='Cash Flow'!B9*F6 -> 492857.14 | G14: ='Cash Flow'!B9*G6 -> 492857.14 | H14: ='Cash Flow'!B9*H6 -> 578571.43 | I14: ='Cash Flow'!B9*I6 -> 578571.43 | J14: ='Cash Flow'!B9*J6 -> 578571.43 | K14: ='Cash Flow'!B9*K6 -> 642857.14 | L14: ='Cash Flow'!B9*L6 -> 642857.14 | M14: ='Cash Flow'!B9*M6 -> 642857.14 | N14: ='Cash Flow'!C9*N6 -> 100000 | O14: ='Cash Flow'!C9*O6 -> 100000 | P14: ='Cash Flow'!C9*P6 -> 100000 | Q14: ='Cash Flow'!C9*Q6 -> 115000 | R14: ='Cash Flow'!C9*R6 -> 115000 | S14: ='Cash Flow'!C9*S6 -> 115000 | T14: ='Cash Flow'!C9*T6 -> 135000 | U14: ='Cash Flow'!C9*U6 -> 135000 | V14: ='Cash Flow'!C9*V6 -> 135000 | W14: ='Cash Flow'!C9*W6 -> 150000 | X14: ='Cash Flow'!C9*X6 -> 150000 | Y14: ='Cash Flow'!C9*Y6 -> 150000 | Z14: ='Cash Flow'!D9*Z6 -> 900000 | AA14: ='Cash Flow'!D9*AA6 -> 900000 | AB14: ='Cash Flow'!D9*AB6 -> 900000 | AC14: ='Cash Flow'!D9*AC6 -> 1035000 | AD14: ='Cash Flow'!D9*AD6 -> 1035000 | AE14: ='Cash Flow'!D9*AE6 -> 1035000 | AF14: ='Cash Flow'!D9*AF6 -> 1215000 | AG14: ='Cash Flow'!D9*AG6 -> 1215000 | AH14: ='Cash Flow'!D9*AH6 -> 1215000 | AI14: ='Cash Flow'!D9*AI6 -> 1350000 | AJ14: ='Cash Flow'!D9*AJ6 -> 1350000 | AK14: ='Cash Flow'!D9*AK6 -> 1350000 | AL14: ='Cash Flow'!E9*AL6 -> 1300000 | AM14: ='Cash Flow'!E9*AM6 -> 1300000 | AN14: ='Cash Flow'!E9*AN6 -> 1300000 | AO14: ='Cash Flow'!E9*AO6 -> 1495000 | AP14: ='Cash Flow'!E9*AP6 -> 1495000 | AQ14: ='Cash Flow'!E9*AQ6 -> 1495000 | AR14: ='Cash Flow'!E9*AR6 -> 1755000 | AS14: ='Cash Flow'!E9*AS6 -> 1755000 | AT14: ='Cash Flow'!E9*AT6 -> 1755000 | AU14: ='Cash Flow'!E9*AU6 -> 1950000 | AV14: ='Cash Flow'!E9*AV6 -> 1950000 | AW14: ='Cash Flow'!E9*AW6 -> 1950000 | AX14: ='Cash Flow'!F9*AX6 -> 2300000 | AY14: ='Cash Flow'!F9*AY6 -> 2300000 | AZ14: ='Cash Flow'!F9*AZ6 -> 2300000 | BA14: ='Cash Flow'!F9*BA6 -> 2645000 | BB14: ='Cash Flow'!F9*BB6 -> 2645000 | BC14: ='Cash Flow'!F9*BC6 -> 2645000 | BD14: ='Cash Flow'!F9*BD6 -> 3105000 | BE14: ='Cash Flow'!F9*BE6 -> 3105000 | BF14: ='Cash Flow'!F9*BF6 -> 3105000 | BG14: ='Cash Flow'!F9*BG6 -> 3450000 | BH14: ='Cash Flow'!F9*BH6 -> 3450000 | BI14: ='Cash Flow'!F9*BI6 -> 3450000
A15: التغير في الأصول الأخرى | B15: ='Cash Flow'!B10*B6 -> 0 | C15: ='Cash Flow'!B10*C6 -> 0 | D15: ='Cash Flow'!B10*D6 -> 0 | E15: ='Cash Flow'!B10*E6 -> 0 | F15: ='Cash Flow'!B10*F6 -> 0 | G15: ='Cash Flow'!B10*G6 -> 0 | H15: ='Cash Flow'!B10*H6 -> 0 | I15: ='Cash Flow'!B10*I6 -> 0 | J15: ='Cash Flow'!B10*J6 -> 0 | K15: ='Cash Flow'!B10*K6 -> 0 | L15: ='Cash Flow'!B10*L6 -> 0 | M15: ='Cash Flow'!B10*M6 -> 0 | N15: ='Cash Flow'!C10*N6 -> 0 | O15: ='Cash Flow'!C10*O6 -> 0 | P15: ='Cash Flow'!C10*P6 -> 0 | Q15: ='Cash Flow'!C10*Q6 -> 0 | R15: ='Cash Flow'!C10*R6 -> 0 | S15: ='Cash Flow'!C10*S6 -> 0 | T15: ='Cash Flow'!C10*T6 -> 0 | U15: ='Cash Flow'!C10*U6 -> 0 | V15: ='Cash Flow'!C10*V6 -> 0 | W15: ='Cash Flow'!C10*W6 -> 0 | X15: ='Cash Flow'!C10*X6 -> 0 | Y15: ='Cash Flow'!C10*Y6 -> 0 | Z15: ='Cash Flow'!D10*Z6 -> 0 | AA15: ='Cash Flow'!D10*AA6 -> 0 | AB15: ='Cash Flow'!D10*AB6 -> 0 | AC15: ='Cash Flow'!D10*AC6 -> 0 | AD15: ='Cash Flow'!D10*AD6 -> 0 | AE15: ='Cash Flow'!D10*AE6 -> 0 | AF15: ='Cash Flow'!D10*AF6 -> 0 | AG15: ='Cash Flow'!D10*AG6 -> 0 | AH15: ='Cash Flow'!D10*AH6 -> 0 | AI15: ='Cash Flow'!D10*AI6 -> 0 | AJ15: ='Cash Flow'!D10*AJ6 -> 0 | AK15: ='Cash Flow'!D10*AK6 -> 0 | AL15: ='Cash Flow'!E10*AL6 -> 0 | AM15: ='Cash Flow'!E10*AM6 -> 0 | AN15: ='Cash Flow'!E10*AN6 -> 0 | AO15: ='Cash Flow'!E10*AO6 -> 0 | AP15: ='Cash Flow'!E10*AP6 -> 0 | AQ15: ='Cash Flow'!E10*AQ6 -> 0 | AR15: ='Cash Flow'!E10*AR6 -> 0 | AS15: ='Cash Flow'!E10*AS6 -> 0 | AT15: ='Cash Flow'!E10*AT6 -> 0 | AU15: ='Cash Flow'!E10*AU6 -> 0 | AV15: ='Cash Flow'!E10*AV6 -> 0 | AW15: ='Cash Flow'!E10*AW6 -> 0 | AX15: ='Cash Flow'!F10*AX6 -> 0 | AY15: ='Cash Flow'!F10*AY6 -> 0 | AZ15: ='Cash Flow'!F10*AZ6 -> 0 | BA15: ='Cash Flow'!F10*BA6 -> 0 | BB15: ='Cash Flow'!F10*BB6 -> 0 | BC15: ='Cash Flow'!F10*BC6 -> 0 | BD15: ='Cash Flow'!F10*BD6 -> 0 | BE15: ='Cash Flow'!F10*BE6 -> 0 | BF15: ='Cash Flow'!F10*BF6 -> 0 | BG15: ='Cash Flow'!F10*BG6 -> 0 | BH15: ='Cash Flow'!F10*BH6 -> 0 | BI15: ='Cash Flow'!F10*BI6 -> 0
A16: صافي التدفق التشغيلي | B16: =SUM(B10:B15) -> 0 | C16: =SUM(C10:C15) -> -1587071.8 | D16: =SUM(D10:D15) -> -1587071.8 | E16: =SUM(E10:E15) -> -1825132.6 | F16: =SUM(F10:F15) -> -1825132.6 | G16: =SUM(G10:G15) -> -1825132.6 | H16: =SUM(H10:H15) -> -2142547 | I16: =SUM(I10:I15) -> -2142547 | ... BI16: =SUM(BI10:BI15) -> -1.0880245e+08
A18: الإنفاق الرأسمالي | B18: ='Cash Flow'!B14*B6 -> 0 | C18: ='Cash Flow'!B14*C6 -> -307285.71 | D18: ='Cash Flow'!B14*D6 -> -307285.71 | E18: ='Cash Flow'!B14*E6 -> -353378.57 | F18: ='Cash Flow'!B14*F6 -> -353378.57 | G18: ='Cash Flow'!B14*G6 -> -353378.57 | H18: ='Cash Flow'!B14*H6 -> -414835.71 | I18: ='Cash Flow'!B14*I6 -> -414835.71 | J18: ='Cash Flow'!B14*J6 -> -414835.71 | K18: ='Cash Flow'!B14*K6 -> -460928.57 | L18: ='Cash Flow'!B14*L6 -> -460928.57 | M18: ='Cash Flow'!B14*M6 -> -460928.57 | N18: ='Cash Flow'!C14*N6 -> -33333.333 | O18: ='Cash Flow'!C14*O6 -> -33333.333 | P18: ='Cash Flow'!C14*P6 -> -33333.333 | Q18: ='Cash Flow'!C14*Q6 -> -38333.333 | R18: ='Cash Flow'!C14*R6 -> -38333.333 | S18: ='Cash Flow'!C14*S6 -> -38333.333 | T18: ='Cash Flow'!C14*T6 -> -45000 | U18: ='Cash Flow'!C14*U6 -> -45000 | V18: ='Cash Flow'!C14*V6 -> -45000 | W18: ='Cash Flow'!C14*W6 -> -50000 | X18: ='Cash Flow'!C14*X6 -> -50000 | Y18: ='Cash Flow'!C14*Y6 -> -50000 | Z18: ='Cash Flow'!D14*Z6 -> -66666.667 | AA18: ='Cash Flow'!D14*AA6 -> -66666.667 | AB18: ='Cash Flow'!D14*AB6 -> -66666.667 | AC18: ='Cash Flow'!D14*AC6 -> -76666.667 | AD18: ='Cash Flow'!D14*AD6 -> -76666.667 | AE18: ='Cash Flow'!D14*AE6 -> -76666.667 | AF18: ='Cash Flow'!D14*AF6 -> -90000 | AG18: ='Cash Flow'!D14*AG6 -> -90000 | AH18: ='Cash Flow'!D14*AH6 -> -90000 | AI18: ='Cash Flow'!D14*AI6 -> -100000 | AJ18: ='Cash Flow'!D14*AJ6 -> -100000 | AK18: ='Cash Flow'!D14*AK6 -> -100000 | AL18: ='Cash Flow'!E14*AL6 -> -100000 | AM18: ='Cash Flow'!E14*AM6 -> -100000 | AN18: ='Cash Flow'!E14*AN6 -> -100000 | AO18: ='Cash Flow'!E14*AO6 -> -115000 | AP18: ='Cash Flow'!E14*AP6 -> -115000 | AQ18: ='Cash Flow'!E14*AQ6 -> -115000 | AR18: ='Cash Flow'!E14*AR6 -> -135000 | AS18: ='Cash Flow'!E14*AS6 -> -135000 | AT18: ='Cash Flow'!E14*AT6 -> -135000 | AU18: ='Cash Flow'!E14*AU6 -> -150000 | AV18: ='Cash Flow'!E14*AV6 -> -150000 | AW18: ='Cash Flow'!E14*AW6 -> -150000 | AX18: ='Cash Flow'!F14*AX6 -> -133333.33 | AY18: ='Cash Flow'!F14*AY6 -> -133333.33 | AZ18: ='Cash Flow'!F14*AZ6 -> -133333.33 | BA18: ='Cash Flow'!F14*BA6 -> -153333.33 | BB18: ='Cash Flow'!F14*BB6 -> -153333.33 | BC18: ='Cash Flow'!F14*BC6 -> -153333.33 | BD18: ='Cash Flow'!F14*BD6 -> -180000 | BE18: ='Cash Flow'!F14*BE6 -> -180000 | BF18: ='Cash Flow'!F14*BF6 -> -180000 | BG18: ='Cash Flow'!F14*BG6 -> -200000 | BH18: ='Cash Flow'!F14*BH6 -> -200000 | BI18: ='Cash Flow'!F14*BI6 -> -200000
A19: صافي التدفق الاستثماري | B19: =B18 -> 0 | C19: =C18 -> -307285.71 | D19: =D18 -> -307285.71 | E19: =E18 -> -353378.57 | F19: =F18 -> -353378.57 | G19: =G18 -> -353378.57 | H19: =H18 -> -414835.71 | I19: =I18 -> -414835.71 | ... BI19: =BI18 -> -200000
A20: حد التسهيلات البنكية المخطط | B20: =Assumptions!B101 -> 0 | C20: =Assumptions!B101 -> 0 | D20: =Assumptions!B101 -> 0 | E20: =Assumptions!B101 -> 0 | F20: =Assumptions!B101 -> 0 | G20: =Assumptions!B101 -> 0 | H20: =Assumptions!B101 -> 0 | I20: =Assumptions!B101 -> 0 | J20: =Assumptions!B101 -> 0 | K20: =Assumptions!B101 -> 0 | L20: =Assumptions!B101 -> 0 | M20: =Assumptions!B101 -> 0 | N20: =Assumptions!C101 -> 420000000 | O20: =Assumptions!C101 -> 420000000 | P20: =Assumptions!C101 -> 420000000 | Q20: =Assumptions!C101 -> 420000000 | R20: =Assumptions!C101 -> 420000000 | S20: =Assumptions!C101 -> 420000000 | T20: =Assumptions!C101 -> 420000000 | U20: =Assumptions!C101 -> 420000000 | V20: =Assumptions!C101 -> 420000000 | W20: =Assumptions!C101 -> 420000000 | X20: =Assumptions!C101 -> 420000000 | Y20: =Assumptions!C101 -> 420000000 | Z20: =Assumptions!D101 -> 850000000 | AA20: =Assumptions!D101 -> 850000000 | AB20: =Assumptions!D101 -> 850000000 | AC20: =Assumptions!D101 -> 850000000 | AD20: =Assumptions!D101 -> 850000000 | AE20: =Assumptions!D101 -> 850000000 | AF20: =Assumptions!D101 -> 850000000 | AG20: =Assumptions!D101 -> 850000000 | AH20: =Assumptions!D101 -> 850000000 | AI20: =Assumptions!D101 -> 850000000 | AJ20: =Assumptions!D101 -> 850000000 | AK20: =Assumptions!D101 -> 850000000 | AL20: =Assumptions!E101 -> 1600000000 | AM20: =Assumptions!E101 -> 1600000000 | AN20: =Assumptions!E101 -> 1600000000 | AO20: =Assumptions!E101 -> 1600000000 | AP20: =Assumptions!E101 -> 1600000000 | AQ20: =Assumptions!E101 -> 1600000000 | AR20: =Assumptions!E101 -> 1600000000 | AS20: =Assumptions!E101 -> 1600000000 | AT20: =Assumptions!E101 -> 1600000000 | AU20: =Assumptions!E101 -> 1600000000 | AV20: =Assumptions!E101 -> 1600000000 | AW20: =Assumptions!E101 -> 1600000000 | AX20: =Assumptions!F101 -> 3000000000 | AY20: =Assumptions!F101 -> 3000000000 | AZ20: =Assumptions!F101 -> 3000000000 | BA20: =Assumptions!F101 -> 3000000000 | BB20: =Assumptions!F101 -> 3000000000 | BC20: =Assumptions!F101 -> 3000000000 | BD20: =Assumptions!F101 -> 3000000000 | BE20: =Assumptions!F101 -> 3000000000 | BF20: =Assumptions!F101 -> 3000000000 | BG20: =Assumptions!F101 -> 3000000000 | BH20: =Assumptions!F101 -> 3000000000 | BI20: =Assumptions!F101 -> 3000000000
A21: صافي حركة الدين البنكي المخطط - توزيع الخطة السنوية حسب وزن النشاط (حتى ورود عقود بنكية) | B21: ='Cash Flow'!B18*B6 -> 0 | C21: ='Cash Flow'!B18*C6 -> 0 | D21: ='Cash Flow'!B18*D6 -> 0 | E21: ='Cash Flow'!B18*E6 -> 0 | F21: ='Cash Flow'!B18*F6 -> 0 | G21: ='Cash Flow'!B18*G6 -> 0 | H21: ='Cash Flow'!B18*H6 -> 0 | I21: ='Cash Flow'!B18*I6 -> 0 | J21: ='Cash Flow'!B18*J6 -> 0 | K21: ='Cash Flow'!B18*K6 -> 0 | L21: ='Cash Flow'!B18*L6 -> 0 | M21: ='Cash Flow'!B18*M6 -> 0 | N21: ='Cash Flow'!C18*N6 -> 24666667 | O21: ='Cash Flow'!C18*O6 -> 24666667 | P21: ='Cash Flow'!C18*P6 -> 24666667 | Q21: ='Cash Flow'!C18*Q6 -> 28366667 | R21: ='Cash Flow'!C18*R6 -> 28366667 | S21: ='Cash Flow'!C18*S6 -> 28366667 | T21: ='Cash Flow'!C18*T6 -> 33300000 | U21: ='Cash Flow'!C18*U6 -> 33300000 | V21: ='Cash Flow'!C18*V6 -> 33300000 | W21: ='Cash Flow'!C18*W6 -> 37000000 | X21: ='Cash Flow'!C18*X6 -> 37000000 | Y21: ='Cash Flow'!C18*Y6 -> 37000000 | Z21: ='Cash Flow'!D18*Z6 -> 21000000 | AA21: ='Cash Flow'!D18*AA6 -> 21000000 | AB21: ='Cash Flow'!D18*AB6 -> 21000000 | AC21: ='Cash Flow'!D18*AC6 -> 24150000 | AD21: ='Cash Flow'!D18*AD6 -> 24150000 | AE21: ='Cash Flow'!D18*AE6 -> 24150000 | AF21: ='Cash Flow'!D18*AF6 -> 28350000 | AG21: ='Cash Flow'!D18*AG6 -> 28350000 | AH21: ='Cash Flow'!D18*AH6 -> 28350000 | AI21: ='Cash Flow'!D18*AI6 -> 31500000 | AJ21: ='Cash Flow'!D18*AJ6 -> 31500000 | AK21: ='Cash Flow'!D18*AK6 -> 31500000 | AL21: ='Cash Flow'!E18*AL6 -> 43333333 | AM21: ='Cash Flow'!E18*AM6 -> 43333333 | AN21: ='Cash Flow'!E18*AN6 -> 43333333 | AO21: ='Cash Flow'!E18*AO6 -> 49833333 | AP21: ='Cash Flow'!E18*AP6 -> 49833333 | AQ21: ='Cash Flow'!E18*AQ6 -> 49833333 | AR21: ='Cash Flow'!E18*AR6 -> 58500000 | AS21: ='Cash Flow'!E18*AS6 -> 58500000 | AT21: ='Cash Flow'!E18*AT6 -> 58500000 | AU21: ='Cash Flow'!E18*AU6 -> 65000000 | AV21: ='Cash Flow'!E18*AV6 -> 65000000 | AW21: ='Cash Flow'!E18*AW6 -> 65000000 | AX21: ='Cash Flow'!F18*AX6 -> 84333333 | AY21: ='Cash Flow'!F18*AY6 -> 84333333 | AZ21: ='Cash Flow'!F18*AZ6 -> 84333333 | BA21: ='Cash Flow'!F18*BA6 -> 96983333 | BB21: ='Cash Flow'!F18*BB6 -> 96983333 | BC21: ='Cash Flow'!F18*BC6 -> 96983333 | BD21: ='Cash Flow'!F18*BD6 -> 113850000 | BE21: ='Cash Flow'!F18*BE6 -> 113850000 | BF21: ='Cash Flow'!F18*BF6 -> 113850000 | BG21: ='Cash Flow'!F18*BG6 -> 126500000 | BH21: ='Cash Flow'!F18*BH6 -> 126500000 | BI21: ='Cash Flow'!F18*BI6 -> 126500000
A22: زيادة رأس المال المدفوع | B22: 0 | C22: 0 | D22: 3750000 | E22: 0 | F22: 0 | G22: 3750000 | H22: 0 | I22: 0 | J22: 3750000 | K22: 0 | L22: 0 | M22: 3750000 | N22: 15000000 | O22: 0 | P22: 0 | Q22: 0 | R22: 15000000 | S22: 0 | T22: 0 | U22: 0 | V22: 15000000 | W22: 0 | X22: 0 | Y22: 0 | Z22: 0 | AA22: 0 | AB22: 0 | AC22: 0 | AD22: 0 | AE22: 0 | AF22: 0 | AG22: 0 | AH22: 0 | AI22: 0 | AJ22: 0 | AK22: 0 | AL22: 0 | AM22: 0 | AN22: 0 | AO22: 0 | AP22: 0 | AQ22: 0 | AR22: 0 | AS22: 0 | AT22: 0 | AU22: 0 | AV22: 0 | AW22: 0 | AX22: 0 | AY22: 0 | AZ22: 0 | BA22: 0 | BB22: 0 | BC22: 0 | BD22: 0 | BE22: 0 | BF22: 0 | BG22: 0 | BH22: 0 | BI22: 0
A23: صافي التدفق التمويلي | B23: =SUM(B21:B22) -> 0 | C23: =SUM(C21:C22) -> 0 | D23: =SUM(D21:D22) -> 3750000 | E23: =SUM(E21:E22) -> 0 | F23: =SUM(F21:F22) -> 0 | G23: =SUM(G21:G22) -> 3750000 | H23: =SUM(H21:H22) -> 0 | I23: =SUM(I21:I22) -> 0 | ... BI23: =SUM(BI21:BI22) -> 126500000
A24: سداد التمويل البنكي - توزيع تخطيطي لسداد الخطة السنوية حسب وزن النشاط | B24: =IF(B$4=2027,'Funding & Liquidity'!$B$12*B$6,IF(B$4=2028,'Funding & Liquidity'!$C$12*B$6,IF(B$4=2029,'Funding & Liquidity'!$D$12*B$6,IF(B$4=2030,'Funding & Liquidity'!$E$12*B$6,'Funding & Liquidity'!$F$12*B$6)))) -> 0 | C24: =IF(C$4=2027,'Funding & Liquidity'!$B$12*C$6,IF(C$4=2028,'Funding & Liquidity'!$C$12*C$6,IF(C$4=2029,'Funding & Liquidity'!$D$12*C$6,IF(C$4=2030,'Funding & Liquidity'!$E$12*C$6,'Funding & Liquidity'!$F$12*C$6)))) -> 0 | D24: =IF(D$4=2027,'Funding & Liquidity'!$B$12*D$6,IF(D$4=2028,'Funding & Liquidity'!$C$12*D$6,IF(D$4=2029,'Funding & Liquidity'!$D$12*D$6,IF(D$4=2030,'Funding & Liquidity'!$E$12*D$6,'Funding & Liquidity'!$F$12*D$6)))) -> 0 | E24: =IF(E$4=2027,'Funding & Liquidity'!$B$12*E$6,IF(E$4=2028,'Funding & Liquidity'!$C$12*E$6,IF(E$4=2029,'Funding & Liquidity'!$D$12*E$6,IF(E$4=2030,'Funding & Liquidity'!$E$12*E$6,'Funding & Liquidity'!$F$12*E$6)))) -> 0 | F24: =IF(F$4=2027,'Funding & Liquidity'!$B$12*F$6,IF(F$4=2028,'Funding & Liquidity'!$C$12*F$6,IF(F$4=2029,'Funding & Liquidity'!$D$12*F$6,IF(F$4=2030,'Funding & Liquidity'!$E$12*F$6,'Funding & Liquidity'!$F$12*F$6)))) -> 0 | G24: =IF(G$4=2027,'Funding & Liquidity'!$B$12*G$6,IF(G$4=2028,'Funding & Liquidity'!$C$12*G$6,IF(G$4=2029,'Funding & Liquidity'!$D$12*G$6,IF(G$4=2030,'Funding & Liquidity'!$E$12*G$6,'Funding & Liquidity'!$F$12*G$6)))) -> 0 | H24: =IF(H$4=2027,'Funding & Liquidity'!$B$12*H$6,IF(H$4=2028,'Funding & Liquidity'!$C$12*H$6,IF(H$4=2029,'Funding & Liquidity'!$D$12*H$6,IF(H$4=2030,'Funding & Liquidity'!$E$12*H$6,'Funding & Liquidity'!$F$12*H$6)))) -> 0 | I24: =IF(I$4=2027,'Funding & Liquidity'!$B$12*I$6,IF(I$4=2028,'Funding & Liquidity'!$C$12*I$6,IF(I$4=2029,'Funding & Liquidity'!$D$12*I$6,IF(I$4=2030,'Funding & Liquidity'!$E$12*I$6,'Funding & Liquidity'!$F$12*I$6)))) -> 0 | ... BI24: =IF(BI$4=2027,'Funding & Liquidity'!$B$12*BI$6,IF(BI$4=2028,'Funding & Liquidity'!$C$12*BI$6,IF(BI$4=2029,'Funding & Liquidity'!$D$12*BI$6,IF(BI$4=2030,'Funding & Liquidity'!$E$12*BI$6,'Funding & Liquidity'!$F$12*BI$6)))) -> 116250000
A25: صافي التغير في النقدية | B25: =B16+B19+B23 -> 0 | C25: =C16+C19+C23 -> -1894357.6 | D25: =D16+D19+D23 -> 1855642.4 | E25: =E16+E19+E23 -> -2178511.2 | F25: =F16+F19+F23 -> -2178511.2 | G25: =G16+G19+G23 -> 1571488.8 | H25: =H16+H19+H23 -> -2557382.7 | I25: =I16+I19+I23 -> -2557382.7 | ... BI25: =BI16+BI19+BI23 -> 17497546
A26: النقدية أول الشهر | B26: =14741923.72 -> 14741924 | C26: =B27 -> 14741924 | D26: =C27 -> 12847566 | E26: =D27 -> 14703209 | F26: =E27 -> 12524697 | G26: =F27 -> 10346186 | H26: =G27 -> 11917675 | I26: =H27 -> 9360292.4 | J26: =I27 -> 6802909.7 | ... BI26: =BH27 -> 2.2328303e+08
A27: النقدية آخر الشهر | B27: =B26+B25 -> 14741924 | C27: =C26+C25 -> 12847566 | D27: =D26+D25 -> 14703209 | E27: =E26+E25 -> 12524697 | F27: =F26+F25 -> 10346186 | G27: =G26+G25 -> 11917675 | H27: =H26+H25 -> 9360292.4 | I27: =I26+I25 -> 6802909.7 | ... BI27: =BI26+BI25 -> 2.4078058e+08
A28: السحوبات البنكية الإجمالية = صافي حركة الدين + سداد الأصل | B28: =B21+B24 -> 0 | C28: =C21+C24 -> 0 | D28: =D21+D24 -> 0 | E28: =E21+E24 -> 0 | F28: =F21+F24 -> 0 | G28: =G21+G24 -> 0 | H28: =H21+H24 -> 0 | I28: =I21+I24 -> 0 | ... BI28: =BI21+BI24 -> 242750000
A29: القاعدة الرأسمالية أول الشهر | B29: =15000000 -> 15000000 | C29: =B32 -> 15000000 | D29: =C32 -> 14416652 | E29: =D32 -> 17583304 | F29: =E32 -> 16912454 | G29: =F32 -> 16241604 | H29: =G32 -> 19320754 | I29: =H32 -> 18533234 | J29: =I32 -> 17745715 | ... BI29: =BH32 -> 5.7356287e+08
A30: نتيجة الشهر | B30: =B10 -> 0 | C30: =C10 -> -583347.91 | D30: =D10 -> -583347.91 | E30: =E10 -> -670850.1 | F30: =F10 -> -670850.1 | G30: =G10 -> -670850.1 | H30: =H10 -> -787519.68 | I30: =I10 -> -787519.68 | ... BI30: =BI10 -> 28975998
A31: زيادة رأس المال | B31: =B22 -> 0 | C31: =C22 -> 0 | D31: =D22 -> 3750000 | E31: =E22 -> 0 | F31: =F22 -> 0 | G31: =G22 -> 3750000 | H31: =H22 -> 0 | I31: =I22 -> 0 | ... BI31: =BI22 -> 0
A32: القاعدة الرأسمالية آخر الشهر | B32: =B29+B30+B31 -> 15000000 | C32: =C29+C30+C31 -> 14416652 | D32: =D29+D30+D31 -> 17583304 | E32: =E29+E30+E31 -> 16912454 | F32: =F29+F30+F31 -> 16241604 | G32: =G29+G30+G31 -> 19320754 | H32: =H29+H30+H31 -> 18533234 | I32: =I29+I30+I31 -> 17745715 | ... BI32: =BI29+BI30+BI31 -> 6.0253887e+08
A33: الدين البنكي آخر الشهر | B33: =B21 -> 0 | C33: =B33+C21 -> 0 | D33: =C33+D21 -> 0 | E33: =D33+E21 -> 0 | F33: =E33+F21 -> 0 | G33: =F33+G21 -> 0 | H33: =G33+H21 -> 0 | I33: =H33+I21 -> 0 | J33: =I33+J21 -> 0 | ... BI33: =BH33+BI21 -> 2600000000
A34: سقف الرافعة الساري (4x طوال Year 1-Year 2، ثم 9x من Year 3 بافتراض صدور الترخيص النهائي فعليا) | B34: =IF(B$4<=2028,4,9) -> 4 | C34: =IF(C$4<=2028,4,9) -> 4 | D34: =IF(D$4<=2028,4,9) -> 4 | E34: =IF(E$4<=2028,4,9) -> 4 | F34: =IF(F$4<=2028,4,9) -> 4 | G34: =IF(G$4<=2028,4,9) -> 4 | H34: =IF(H$4<=2028,4,9) -> 4 | I34: =IF(I$4<=2028,4,9) -> 4 | ... BI34: =IF(BI$4<=2028,4,9) -> 9
A35: الرافعة المالية (4× على صافي حقوق الملكية قبل النهائي؛ 9× على القاعدة الرأسمالية التخطيطية بعد الخصومات بعد النهائي) | B35: =IFERROR(B33/MAX(1,B32-IF(B34=9,INDEX('Regulatory Capital Plan'!$B$9:$F$9,1,B$4-2026),0)),0) -> 0 | C35: =IFERROR(C33/MAX(1,C32-IF(C34=9,INDEX('Regulatory Capital Plan'!$B$9:$F$9,1,C$4-2026),0)),0) -> 0 | D35: =IFERROR(D33/MAX(1,D32-IF(D34=9,INDEX('Regulatory Capital Plan'!$B$9:$F$9,1,D$4-2026),0)),0) -> 0 | E35: =IFERROR(E33/MAX(1,E32-IF(E34=9,INDEX('Regulatory Capital Plan'!$B$9:$F$9,1,E$4-2026),0)),0) -> 0 | F35: =IFERROR(F33/MAX(1,F32-IF(F34=9,INDEX('Regulatory Capital Plan'!$B$9:$F$9,1,F$4-2026),0)),0) -> 0 | G35: =IFERROR(G33/MAX(1,G32-IF(G34=9,INDEX('Regulatory Capital Plan'!$B$9:$F$9,1,G$4-2026),0)),0) -> 0 | H35: =IFERROR(H33/MAX(1,H32-IF(H34=9,INDEX('Regulatory Capital Plan'!$B$9:$F$9,1,H$4-2026),0)),0) -> 0 | I35: =IFERROR(I33/MAX(1,I32-IF(I34=9,INDEX('Regulatory Capital Plan'!$B$9:$F$9,1,I$4-2026),0)),0) -> 0 | ... BI35: =IFERROR(BI33/MAX(1,BI32-IF(BI34=9,INDEX('Regulatory Capital Plan'!$B$9:$F$9,1,BI$4-2026),0)),0) -> 4.3358071
A36: حالة الرافعة | B36: =IF(B35<=B34,"متوافق","فجوة") -> متوافق | C36: =IF(C35<=C34,"متوافق","فجوة") -> متوافق | D36: =IF(D35<=D34,"متوافق","فجوة") -> متوافق | E36: =IF(E35<=E34,"متوافق","فجوة") -> متوافق | F36: =IF(F35<=F34,"متوافق","فجوة") -> متوافق | G36: =IF(G35<=G34,"متوافق","فجوة") -> متوافق | H36: =IF(H35<=H34,"متوافق","فجوة") -> متوافق | I36: =IF(I35<=I34,"متوافق","فجوة") -> متوافق | ... BI36: =IF(BI35<=BI34,"متوافق","فجوة") -> متوافق
A37: LCR شهري - تقدير تخطيطي 30 يوما | B37: =IFERROR(B27/MAX(1,('Income Statement'!B17+'Income Statement'!B18+'Income Statement'!B15)/12-MIN(Assumptions!B78/12,(('Income Statement'!B17+'Income Statement'!B18+'Income Statement'!B15)/12)*90%)),0) -> 20.778842 | C37: =IFERROR(C27/MAX(1,('Income Statement'!B17+'Income Statement'!B18+'Income Statement'!B15)/12-MIN(Assumptions!B78/12,(('Income Statement'!B17+'Income Statement'!B18+'Income Statement'!B15)/12)*90%)),0) -> 18.108732 | D37: =IFERROR(D27/MAX(1,('Income Statement'!B17+'Income Statement'!B18+'Income Statement'!B15)/12-MIN(Assumptions!B78/12,(('Income Statement'!B17+'Income Statement'!B18+'Income Statement'!B15)/12)*90%)),0) -> 20.724273 | E37: =IFERROR(E27/MAX(1,('Income Statement'!B17+'Income Statement'!B18+'Income Statement'!B15)/12-MIN(Assumptions!B78/12,(('Income Statement'!B17+'Income Statement'!B18+'Income Statement'!B15)/12)*90%)),0) -> 17.653647 | F37: =IFERROR(F27/MAX(1,('Income Statement'!B17+'Income Statement'!B18+'Income Statement'!B15)/12-MIN(Assumptions!B78/12,(('Income Statement'!B17+'Income Statement'!B18+'Income Statement'!B15)/12)*90%)),0) -> 14.58302 | G37: =IFERROR(G27/MAX(1,('Income Statement'!B17+'Income Statement'!B18+'Income Statement'!B15)/12-MIN(Assumptions!B78/12,(('Income Statement'!B17+'Income Statement'!B18+'Income Statement'!B15)/12)*90%)),0) -> 16.798044 | H37: =IFERROR(H27/MAX(1,('Income Statement'!B17+'Income Statement'!B18+'Income Statement'!B15)/12-MIN(Assumptions!B78/12,(('Income Statement'!B17+'Income Statement'!B18+'Income Statement'!B15)/12)*90%)),0) -> 13.193396 | I37: =IFERROR(I27/MAX(1,('Income Statement'!B17+'Income Statement'!B18+'Income Statement'!B15)/12-MIN(Assumptions!B78/12,(('Income Statement'!B17+'Income Statement'!B18+'Income Statement'!B15)/12)*90%)),0) -> 9.5887476 | J37: =IFERROR(J27/MAX(1,('Income Statement'!B17+'Income Statement'!B18+'Income Statement'!B15)/12-MIN(Assumptions!B78/12,(('Income Statement'!B17+'Income Statement'!B18+'Income Statement'!B15)/12)*90%)),0) -> 11.26975 | K37: =IFERROR(K27/MAX(1,('Income Statement'!B17+'Income Statement'!B18+'Income Statement'!B15)/12-MIN(Assumptions!B78/12,(('Income Statement'!B17+'Income Statement'!B18+'Income Statement'!B15)/12)*90%)),0) -> 7.264585 | L37: =IFERROR(L27/MAX(1,('Income Statement'!B17+'Income Statement'!B18+'Income Statement'!B15)/12-MIN(Assumptions!B78/12,(('Income Statement'!B17+'Income Statement'!B18+'Income Statement'!B15)/12)*90%)),0) -> 3.2594201 | M37: =IFERROR(M27/MAX(1,('Income Statement'!B17+'Income Statement'!B18+'Income Statement'!B15)/12-MIN(Assumptions!B78/12,(('Income Statement'!B17+'Income Statement'!B18+'Income Statement'!B15)/12)*90%)),0) -> 4.5399059 | N37: =IFERROR(N27/MAX(1,('Income Statement'!C17+'Income Statement'!C18+'Income Statement'!C15)/12-MIN(Assumptions!C78/12,(('Income Statement'!C17+'Income Statement'!C18+'Income Statement'!C15)/12)*90%)),0) -> 31.138419 | O37: =IFERROR(O27/MAX(1,('Income Statement'!C17+'Income Statement'!C18+'Income Statement'!C15)/12-MIN(Assumptions!C78/12,(('Income Statement'!C17+'Income Statement'!C18+'Income Statement'!C15)/12)*90%)),0) -> 25.99923 | P37: =IFERROR(P27/MAX(1,('Income Statement'!C17+'Income Statement'!C18+'Income Statement'!C15)/12-MIN(Assumptions!C78/12,(('Income Statement'!C17+'Income Statement'!C18+'Income Statement'!C15)/12)*90%)),0) -> 20.860042 | Q37: =IFERROR(Q27/MAX(1,('Income Statement'!C17+'Income Statement'!C18+'Income Statement'!C15)/12-MIN(Assumptions!C78/12,(('Income Statement'!C17+'Income Statement'!C18+'Income Statement'!C15)/12)*90%)),0) -> 14.949975 | R37: =IFERROR(R27/MAX(1,('Income Statement'!C17+'Income Statement'!C18+'Income Statement'!C15)/12-MIN(Assumptions!C78/12,(('Income Statement'!C17+'Income Statement'!C18+'Income Statement'!C15)/12)*90%)),0) -> 38.90471 | S37: =IFERROR(S27/MAX(1,('Income Statement'!C17+'Income Statement'!C18+'Income Statement'!C15)/12-MIN(Assumptions!C78/12,(('Income Statement'!C17+'Income Statement'!C18+'Income Statement'!C15)/12)*90%)),0) -> 32.994643 | T37: =IFERROR(T27/MAX(1,('Income Statement'!C17+'Income Statement'!C18+'Income Statement'!C15)/12-MIN(Assumptions!C78/12,(('Income Statement'!C17+'Income Statement'!C18+'Income Statement'!C15)/12)*90%)),0) -> 26.056738 | U37: =IFERROR(U27/MAX(1,('Income Statement'!C17+'Income Statement'!C18+'Income Statement'!C15)/12-MIN(Assumptions!C78/12,(('Income Statement'!C17+'Income Statement'!C18+'Income Statement'!C15)/12)*90%)),0) -> 19.118834 | V37: =IFERROR(V27/MAX(1,('Income Statement'!C17+'Income Statement'!C18+'Income Statement'!C15)/12-MIN(Assumptions!C78/12,(('Income Statement'!C17+'Income Statement'!C18+'Income Statement'!C15)/12)*90%)),0) -> 42.045731 | W37: =IFERROR(W27/MAX(1,('Income Statement'!C17+'Income Statement'!C18+'Income Statement'!C15)/12-MIN(Assumptions!C78/12,(('Income Statement'!C17+'Income Statement'!C18+'Income Statement'!C15)/12)*90%)),0) -> 34.336949 | X37: =IFERROR(X27/MAX(1,('Income Statement'!C17+'Income Statement'!C18+'Income Statement'!C15)/12-MIN(Assumptions!C78/12,(('Income Statement'!C17+'Income Statement'!C18+'Income Statement'!C15)/12)*90%)),0) -> 26.628166 | Y37: =IFERROR(Y27/MAX(1,('Income Statement'!C17+'Income Statement'!C18+'Income Statement'!C15)/12-MIN(Assumptions!C78/12,(('Income Statement'!C17+'Income Statement'!C18+'Income Statement'!C15)/12)*90%)),0) -> 18.919383 | Z37: =IFERROR(Z27/MAX(1,('Income Statement'!D17+'Income Statement'!D18+'Income Statement'!D15)/12-MIN(Assumptions!D78/12,(('Income Statement'!D17+'Income Statement'!D18+'Income Statement'!D15)/12)*90%)),0) -> 8.7954723 | AA37: =IFERROR(AA27/MAX(1,('Income Statement'!D17+'Income Statement'!D18+'Income Statement'!D15)/12-MIN(Assumptions!D78/12,(('Income Statement'!D17+'Income Statement'!D18+'Income Statement'!D15)/12)*90%)),0) -> 9.0186521 | AB37: =IFERROR(AB27/MAX(1,('Income Statement'!D17+'Income Statement'!D18+'Income Statement'!D15)/12-MIN(Assumptions!D78/12,(('Income Statement'!D17+'Income Statement'!D18+'Income Statement'!D15)/12)*90%)),0) -> 9.241832 | AC37: =IFERROR(AC27/MAX(1,('Income Statement'!D17+'Income Statement'!D18+'Income Statement'!D15)/12-MIN(Assumptions!D78/12,(('Income Statement'!D17+'Income Statement'!D18+'Income Statement'!D15)/12)*90%)),0) -> 9.4984888 | AD37: =IFERROR(AD27/MAX(1,('Income Statement'!D17+'Income Statement'!D18+'Income Statement'!D15)/12-MIN(Assumptions!D78/12,(('Income Statement'!D17+'Income Statement'!D18+'Income Statement'!D15)/12)*90%)),0) -> 9.7551456 | AE37: =IFERROR(AE27/MAX(1,('Income Statement'!D17+'Income Statement'!D18+'Income Statement'!D15)/12-MIN(Assumptions!D78/12,(('Income Statement'!D17+'Income Statement'!D18+'Income Statement'!D15)/12)*90%)),0) -> 10.011802 | AF37: =IFERROR(AF27/MAX(1,('Income Statement'!D17+'Income Statement'!D18+'Income Statement'!D15)/12-MIN(Assumptions!D78/12,(('Income Statement'!D17+'Income Statement'!D18+'Income Statement'!D15)/12)*90%)),0) -> 10.313095 | AG37: =IFERROR(AG27/MAX(1,('Income Statement'!D17+'Income Statement'!D18+'Income Statement'!D15)/12-MIN(Assumptions!D78/12,(('Income Statement'!D17+'Income Statement'!D18+'Income Statement'!D15)/12)*90%)),0) -> 10.614388 | AH37: =IFERROR(AH27/MAX(1,('Income Statement'!D17+'Income Statement'!D18+'Income Statement'!D15)/12-MIN(Assumptions!D78/12,(('Income Statement'!D17+'Income Statement'!D18+'Income Statement'!D15)/12)*90%)),0) -> 10.915681 | AI37: =IFERROR(AI27/MAX(1,('Income Statement'!D17+'Income Statement'!D18+'Income Statement'!D15)/12-MIN(Assumptions!D78/12,(('Income Statement'!D17+'Income Statement'!D18+'Income Statement'!D15)/12)*90%)),0) -> 11.25045 | AJ37: =IFERROR(AJ27/MAX(1,('Income Statement'!D17+'Income Statement'!D18+'Income Statement'!D15)/12-MIN(Assumptions!D78/12,(('Income Statement'!D17+'Income Statement'!D18+'Income Statement'!D15)/12)*90%)),0) -> 11.58522 | AK37: =IFERROR(AK27/MAX(1,('Income Statement'!D17+'Income Statement'!D18+'Income Statement'!D15)/12-MIN(Assumptions!D78/12,(('Income Statement'!D17+'Income Statement'!D18+'Income Statement'!D15)/12)*90%)),0) -> 11.91999 | AL37: =IFERROR(AL27/MAX(1,('Income Statement'!E17+'Income Statement'!E18+'Income Statement'!E15)/12-MIN(Assumptions!E78/12,(('Income Statement'!E17+'Income Statement'!E18+'Income Statement'!E15)/12)*90%)),0) -> 9.3467272 | AM37: =IFERROR(AM27/MAX(1,('Income Statement'!E17+'Income Statement'!E18+'Income Statement'!E15)/12-MIN(Assumptions!E78/12,(('Income Statement'!E17+'Income Statement'!E18+'Income Statement'!E15)/12)*90%)),0) -> 11.306741 | AN37: =IFERROR(AN27/MAX(1,('Income Statement'!E17+'Income Statement'!E18+'Income Statement'!E15)/12-MIN(Assumptions!E78/12,(('Income Statement'!E17+'Income Statement'!E18+'Income Statement'!E15)/12)*90%)),0) -> 13.266755 | AO37: =IFERROR(AO27/MAX(1,('Income Statement'!E17+'Income Statement'!E18+'Income Statement'!E15)/12-MIN(Assumptions!E78/12,(('Income Statement'!E17+'Income Statement'!E18+'Income Statement'!E15)/12)*90%)),0) -> 15.520771 | AP37: =IFERROR(AP27/MAX(1,('Income Statement'!E17+'Income Statement'!E18+'Income Statement'!E15)/12-MIN(Assumptions!E78/12,(('Income Statement'!E17+'Income Statement'!E18+'Income Statement'!E15)/12)*90%)),0) -> 17.774787 | AQ37: =IFERROR(AQ27/MAX(1,('Income Statement'!E17+'Income Statement'!E18+'Income Statement'!E15)/12-MIN(Assumptions!E78/12,(('Income Statement'!E17+'Income Statement'!E18+'Income Statement'!E15)/12)*90%)),0) -> 20.028803 | AR37: =IFERROR(AR27/MAX(1,('Income Statement'!E17+'Income Statement'!E18+'Income Statement'!E15)/12-MIN(Assumptions!E78/12,(('Income Statement'!E17+'Income Statement'!E18+'Income Statement'!E15)/12)*90%)),0) -> 22.674821 | AS37: =IFERROR(AS27/MAX(1,('Income Statement'!E17+'Income Statement'!E18+'Income Statement'!E15)/12-MIN(Assumptions!E78/12,(('Income Statement'!E17+'Income Statement'!E18+'Income Statement'!E15)/12)*90%)),0) -> 25.32084 | AT37: =IFERROR(AT27/MAX(1,('Income Statement'!E17+'Income Statement'!E18+'Income Statement'!E15)/12-MIN(Assumptions!E78/12,(('Income Statement'!E17+'Income Statement'!E18+'Income Statement'!E15)/12)*90%)),0) -> 27.966859 | AU37: =IFERROR(AU27/MAX(1,('Income Statement'!E17+'Income Statement'!E18+'Income Statement'!E15)/12-MIN(Assumptions!E78/12,(('Income Statement'!E17+'Income Statement'!E18+'Income Statement'!E15)/12)*90%)),0) -> 30.906879 | AV37: =IFERROR(AV27/MAX(1,('Income Statement'!E17+'Income Statement'!E18+'Income Statement'!E15)/12-MIN(Assumptions!E78/12,(('Income Statement'!E17+'Income Statement'!E18+'Income Statement'!E15)/12)*90%)),0) -> 33.8469 | AW37: =IFERROR(AW27/MAX(1,('Income Statement'!E17+'Income Statement'!E18+'Income Statement'!E15)/12-MIN(Assumptions!E78/12,(('Income Statement'!E17+'Income Statement'!E18+'Income Statement'!E15)/12)*90%)),0) -> 36.786921 | AX37: =IFERROR(AX27/MAX(1,('Income Statement'!F17+'Income Statement'!F18+'Income Statement'!F15)/12-MIN(Assumptions!F78/12,(('Income Statement'!F17+'Income Statement'!F18+'Income Statement'!F15)/12)*90%)),0) -> 24.893191 | AY37: =IFERROR(AY27/MAX(1,('Income Statement'!F17+'Income Statement'!F18+'Income Statement'!F15)/12-MIN(Assumptions!F78/12,(('Income Statement'!F17+'Income Statement'!F18+'Income Statement'!F15)/12)*90%)),0) -> 28.641471 | AZ37: =IFERROR(AZ27/MAX(1,('Income Statement'!F17+'Income Statement'!F18+'Income Statement'!F15)/12-MIN(Assumptions!F78/12,(('Income Statement'!F17+'Income Statement'!F18+'Income Statement'!F15)/12)*90%)),0) -> 32.389751 | BA37: =IFERROR(BA27/MAX(1,('Income Statement'!F17+'Income Statement'!F18+'Income Statement'!F15)/12-MIN(Assumptions!F78/12,(('Income Statement'!F17+'Income Statement'!F18+'Income Statement'!F15)/12)*90%)),0) -> 36.700273 | BB37: =IFERROR(BB27/MAX(1,('Income Statement'!F17+'Income Statement'!F18+'Income Statement'!F15)/12-MIN(Assumptions!F78/12,(('Income Statement'!F17+'Income Statement'!F18+'Income Statement'!F15)/12)*90%)),0) -> 41.010795 | BC37: =IFERROR(BC27/MAX(1,('Income Statement'!F17+'Income Statement'!F18+'Income Statement'!F15)/12-MIN(Assumptions!F78/12,(('Income Statement'!F17+'Income Statement'!F18+'Income Statement'!F15)/12)*90%)),0) -> 45.321317 | BD37: =IFERROR(BD27/MAX(1,('Income Statement'!F17+'Income Statement'!F18+'Income Statement'!F15)/12-MIN(Assumptions!F78/12,(('Income Statement'!F17+'Income Statement'!F18+'Income Statement'!F15)/12)*90%)),0) -> 50.381496 | BE37: =IFERROR(BE27/MAX(1,('Income Statement'!F17+'Income Statement'!F18+'Income Statement'!F15)/12-MIN(Assumptions!F78/12,(('Income Statement'!F17+'Income Statement'!F18+'Income Statement'!F15)/12)*90%)),0) -> 55.441674 | BF37: =IFERROR(BF27/MAX(1,('Income Statement'!F17+'Income Statement'!F18+'Income Statement'!F15)/12-MIN(Assumptions!F78/12,(('Income Statement'!F17+'Income Statement'!F18+'Income Statement'!F15)/12)*90%)),0) -> 60.501852 | BG37: =IFERROR(BG27/MAX(1,('Income Statement'!F17+'Income Statement'!F18+'Income Statement'!F15)/12-MIN(Assumptions!F78/12,(('Income Statement'!F17+'Income Statement'!F18+'Income Statement'!F15)/12)*90%)),0) -> 66.124272 | BH37: =IFERROR(BH27/MAX(1,('Income Statement'!F17+'Income Statement'!F18+'Income Statement'!F15)/12-MIN(Assumptions!F78/12,(('Income Statement'!F17+'Income Statement'!F18+'Income Statement'!F15)/12)*90%)),0) -> 71.746692 | BI37: =IFERROR(BI27/MAX(1,('Income Statement'!F17+'Income Statement'!F18+'Income Statement'!F15)/12-MIN(Assumptions!F78/12,(('Income Statement'!F17+'Income Statement'!F18+'Income Statement'!F15)/12)*90%)),0) -> 77.369113
A38: حالة السيولة | B38: =IF(B37>=100%,"متوافق استرشاديا - يحتاج آجال/عقود فعلية","فجوة") -> متوافق استرشاديا - يحتاج آجال/عقود فعلية | C38: =IF(C37>=100%,"متوافق استرشاديا - يحتاج آجال/عقود فعلية","فجوة") -> متوافق استرشاديا - يحتاج آجال/عقود فعلية | D38: =IF(D37>=100%,"متوافق استرشاديا - يحتاج آجال/عقود فعلية","فجوة") -> متوافق استرشاديا - يحتاج آجال/عقود فعلية | E38: =IF(E37>=100%,"متوافق استرشاديا - يحتاج آجال/عقود فعلية","فجوة") -> متوافق استرشاديا - يحتاج آجال/عقود فعلية | F38: =IF(F37>=100%,"متوافق استرشاديا - يحتاج آجال/عقود فعلية","فجوة") -> متوافق استرشاديا - يحتاج آجال/عقود فعلية | G38: =IF(G37>=100%,"متوافق استرشاديا - يحتاج آجال/عقود فعلية","فجوة") -> متوافق استرشاديا - يحتاج آجال/عقود فعلية | H38: =IF(H37>=100%,"متوافق استرشاديا - يحتاج آجال/عقود فعلية","فجوة") -> متوافق استرشاديا - يحتاج آجال/عقود فعلية | I38: =IF(I37>=100%,"متوافق استرشاديا - يحتاج آجال/عقود فعلية","فجوة") -> متوافق استرشاديا - يحتاج آجال/عقود فعلية | ... BI38: =IF(BI37>=100%,"متوافق استرشاديا - يحتاج آجال/عقود فعلية","فجوة") -> متوافق استرشاديا - يحتاج آجال/عقود فعلية
A39: الدين البنكي أول الشهر | B39: =0 -> 0 | C39: =B33 -> 0 | D39: =C33 -> 0 | E39: =D33 -> 0 | F39: =E33 -> 0 | G39: =F33 -> 0 | H39: =G33 -> 0 | I39: =H33 -> 0 | J39: =I33 -> 0 | ... BI39: =BH33 -> 2473500000
A40: متوسط رصيد الدين البنكي الشهري | B40: =AVERAGE(B39,B33) -> 0 | C40: =AVERAGE(C39,C33) -> 0 | D40: =AVERAGE(D39,D33) -> 0 | E40: =AVERAGE(E39,E33) -> 0 | F40: =AVERAGE(F39,F33) -> 0 | G40: =AVERAGE(G39,G33) -> 0 | H40: =AVERAGE(H39,H33) -> 0 | I40: =AVERAGE(I39,I33) -> 0 | ... BI40: =AVERAGE(BI39,BI33) -> 2536750000
A41: تكلفة التمويل الشهرية على متوسط الدين | B41: =B40*(IF(B$4=2027,Assumptions!$B$9,IF(B$4=2028,Assumptions!$C$9,IF(B$4=2029,Assumptions!$D$9,IF(B$4=2030,Assumptions!$E$9,Assumptions!$F$9)))))/12 -> 0 | C41: =C40*(IF(C$4=2027,Assumptions!$B$9,IF(C$4=2028,Assumptions!$C$9,IF(C$4=2029,Assumptions!$D$9,IF(C$4=2030,Assumptions!$E$9,Assumptions!$F$9)))))/12 -> 0 | D41: =D40*(IF(D$4=2027,Assumptions!$B$9,IF(D$4=2028,Assumptions!$C$9,IF(D$4=2029,Assumptions!$D$9,IF(D$4=2030,Assumptions!$E$9,Assumptions!$F$9)))))/12 -> 0 | E41: =E40*(IF(E$4=2027,Assumptions!$B$9,IF(E$4=2028,Assumptions!$C$9,IF(E$4=2029,Assumptions!$D$9,IF(E$4=2030,Assumptions!$E$9,Assumptions!$F$9)))))/12 -> 0 | F41: =F40*(IF(F$4=2027,Assumptions!$B$9,IF(F$4=2028,Assumptions!$C$9,IF(F$4=2029,Assumptions!$D$9,IF(F$4=2030,Assumptions!$E$9,Assumptions!$F$9)))))/12 -> 0 | G41: =G40*(IF(G$4=2027,Assumptions!$B$9,IF(G$4=2028,Assumptions!$C$9,IF(G$4=2029,Assumptions!$D$9,IF(G$4=2030,Assumptions!$E$9,Assumptions!$F$9)))))/12 -> 0 | H41: =H40*(IF(H$4=2027,Assumptions!$B$9,IF(H$4=2028,Assumptions!$C$9,IF(H$4=2029,Assumptions!$D$9,IF(H$4=2030,Assumptions!$E$9,Assumptions!$F$9)))))/12 -> 0 | I41: =I40*(IF(I$4=2027,Assumptions!$B$9,IF(I$4=2028,Assumptions!$C$9,IF(I$4=2029,Assumptions!$D$9,IF(I$4=2030,Assumptions!$E$9,Assumptions!$F$9)))))/12 -> 0 | ... BI41: =BI40*(IF(BI$4=2027,Assumptions!$B$9,IF(BI$4=2028,Assumptions!$C$9,IF(BI$4=2029,Assumptions!$D$9,IF(BI$4=2030,Assumptions!$E$9,Assumptions!$F$9)))))/12 -> 35937292
A42: النقدية قبل السحب البنكي الإجمالي | B42: =B26+B16+B19+B22-B24 -> 14741924 | C42: =C26+C16+C19+C22-C24 -> 12847566 | D42: =D26+D16+D19+D22-D24 -> 14703209 | E42: =E26+E16+E19+E22-E24 -> 12524697 | F42: =F26+F16+F19+F22-F24 -> 10346186 | G42: =G26+G16+G19+G22-G24 -> 11917675 | H42: =H26+H16+H19+H22-H24 -> 9360292.4 | I42: =I26+I16+I19+I22-I24 -> 6802909.7 | ... BI42: =BI26+BI16+BI19+BI22-BI24 -> -1969422.5
A43: الحد الأدنى للسحب البنكي اللازم لمنع نقدية سالبة | B43: =MAX(0,-B42) -> 0 | C43: =MAX(0,-C42) -> 0 | D43: =MAX(0,-D42) -> 0 | E43: =MAX(0,-E42) -> 0 | F43: =MAX(0,-F42) -> 0 | G43: =MAX(0,-G42) -> 0 | H43: =MAX(0,-H42) -> 0 | I43: =MAX(0,-I42) -> 0 | ... BI43: =MAX(0,-BI42) -> 1969422.5
A44: فائض/(عجز) السحب المخطط مقابل الحد الأدنى المطلوب | B44: =B28-B43 -> 0 | C44: =C28-C43 -> 0 | D44: =D28-D43 -> 0 | E44: =E28-E43 -> 0 | F44: =F28-F43 -> 0 | G44: =G28-G43 -> 0 | H44: =H28-H43 -> 0 | I44: =I28-I43 -> 0 | ... BI44: =BI28-BI43 -> 2.4078058e+08
A45: اختبار كفاية خطة السحب شهريا | B45: =IF(AND(B44>=-1,B33<=B20+1,B27>=-1),"OK","GAP") -> OK | C45: =IF(AND(C44>=-1,C33<=C20+1,C27>=-1),"OK","GAP") -> OK | D45: =IF(AND(D44>=-1,D33<=D20+1,D27>=-1),"OK","GAP") -> OK | E45: =IF(AND(E44>=-1,E33<=E20+1,E27>=-1),"OK","GAP") -> OK | F45: =IF(AND(F44>=-1,F33<=F20+1,F27>=-1),"OK","GAP") -> OK | G45: =IF(AND(G44>=-1,G33<=G20+1,G27>=-1),"OK","GAP") -> OK | H45: =IF(AND(H44>=-1,H33<=H20+1,H27>=-1),"OK","GAP") -> OK | I45: =IF(AND(I44>=-1,I33<=I20+1,I27>=-1),"OK","GAP") -> OK | ... BI45: =IF(AND(BI44>=-1,BI33<=BI20+1,BI27>=-1),"OK","GAP") -> OK

Sheet Income Statement
A1: قائمة الدخل التقديرية - خمس سنوات
A3: البند | B3: Year 1 | C3: Year 2 | D3: Year 3 | E3: Year 4 | F3: Year 5
A4: مؤشرات النشاط
A5: المنح السنوي | B5: =Assumptions!B76 -> 27750000 | C5: =Assumptions!C76 -> 527500000 | D5: =Assumptions!D76 -> 700000000 | E5: =Assumptions!E76 -> 1350000000 | F5: =Assumptions!F76 -> 2500000000
A6: عدد العقود | B6: =Assumptions!B77 -> 185 | C6: =Assumptions!C77 -> 1670 | D6: =Assumptions!D77 -> 788 | E6: =Assumptions!E77 -> 1227 | F6: =Assumptions!F77 -> 1852
A8: الإيرادات
A9: عوائد التأجير | B9: =Assumptions!B80 -> 3538848 | C9: =Assumptions!C80 -> 45873640 | D9: =Assumptions!D80 -> 1.9787453e+08 | E9: =Assumptions!E80 -> 3.5475974e+08 | F9: =Assumptions!F80 -> 6.2307685e+08
A10: رسوم الخدمات الإدارية | B10: ='Cohort Fees'!B7 -> 1387500 | C10: ='Cohort Fees'!C7 -> 36925000 | D10: ='Cohort Fees'!D7 -> 42000000 | E10: ='Cohort Fees'!E7 -> 81000000 | F10: ='Cohort Fees'!F7 -> 150000000
A11: إيرادات الرسوم المؤجلة | B11: =0 -> 0 | C11: =0 -> 0 | D11: =0 -> 0 | E11: =0 -> 0 | F11: =0 -> 0
A12: إجمالي الإيرادات | B12: =SUM(B9:B11) -> 4926348 | C12: =SUM(C9:C11) -> 82798640 | D12: =SUM(D9:D11) -> 2.3987453e+08 | E12: =SUM(E9:E11) -> 4.3575974e+08 | F12: =SUM(F9:F11) -> 7.7307685e+08
A13: دعم تشغيلي / إيرادات خدمات مساندة أخرى | B13: =Assumptions!B82 -> 3118262.4 | C13: =Assumptions!C82 -> 0 | D13: =Assumptions!D82 -> 5600000 | E13: =Assumptions!E82 -> 10800000 | F13: =Assumptions!F82 -> 20000000
A14: المصروفات
A15: تكلفة التمويل البنكي | B15: =Assumptions!B83 -> 0 | C15: =Assumptions!C83 -> 37240500 | D15: =Assumptions!D83 -> 102822500 | E15: =Assumptions!E83 -> 176827500 | F15: =Assumptions!F83 -> 325335375
A16: مصروف الخسائر الائتمانية | B16: =Assumptions!B84 -> 620169.12 | C16: =Assumptions!C84 -> 12957897 | D16: =Assumptions!D84 -> 12418773 | E16: =Assumptions!E84 -> 24026264 | F16: =Assumptions!F84 -> 43740758
A17: تكلفة العاملين الشاملة | B17: =Assumptions!B85 -> 11156112 | C17: =Assumptions!C85 -> 15618000 | D17: =Assumptions!D85 -> 21893869 | E17: =Assumptions!E85 -> 25061090 | F17: =Assumptions!F85 -> 30073308
A18: المصروفات الإدارية والتشغيلية | B18: =Assumptions!B86 -> 4435200 | C18: =Assumptions!C86 -> 7413120 | D18: =Assumptions!D86 -> 8305440 | E18: =Assumptions!E86 -> 12769614 | F18: =Assumptions!F86 -> 18043568
A19: الإهلاك والاستهلاك | B19: =Assumptions!B87 -> 0 | C19: =Assumptions!C87 -> 0 | D19: =Assumptions!D87 -> 1000000 | E19: =Assumptions!E87 -> 1500000 | F19: =Assumptions!F87 -> 2000000
A20: إجمالي المصروفات | B20: =SUM(B15:B19) -> 16211481 | C20: =SUM(C15:C19) -> 73229517 | D20: =SUM(D15:D19) -> 1.4644058e+08 | E20: =SUM(E15:E19) -> 2.4018447e+08 | F20: =SUM(F15:F19) -> 4.1919301e+08
A21: الربح قبل الضريبة | B21: =B12+B13-B20 -> -8166870.8 | C21: =C12+C13-C20 -> 9569122.8 | D21: =D12+D13-D20 -> 99033950 | E21: =E12+E13-E20 -> 2.0637527e+08 | F21: =F12+F13-F20 -> 3.7388384e+08
A22: ضريبة الدخل | B22: =Assumptions!B88 -> 0 | C22: =Assumptions!C88 -> 315506.7 | D22: =Assumptions!D88 -> 22282639 | E22: =Assumptions!E88 -> 46434436 | F22: =Assumptions!F88 -> 84123865
A23: صافي الربح | B23: =Assumptions!B89 -> -8166870.8 | C23: =Assumptions!C89 -> 9253616.1 | D23: =Assumptions!D89 -> 76751312 | E23: =Assumptions!E89 -> 1.5994083e+08 | F23: =Assumptions!F89 -> 2.8975998e+08
A25: مؤشرات الربحية
A26: EBITDA | B26: =B21+B15+B16+B19 -> -7546701.6 | C26: =C21+C15+C16+C19 -> 59767520 | D26: =D21+D15+D16+D19 -> 2.1527522e+08 | E26: =E21+E15+E16+E19 -> 4.0872903e+08 | F26: =F21+F15+F16+F19 -> 7.4495998e+08
A27: EBIT | B27: =B21+B15 -> -8166870.8 | C27: =C21+C15 -> 46809623 | D27: =D21+D15 -> 2.0185645e+08 | E27: =E21+E15 -> 3.8320277e+08 | F27: =F21+F15 -> 6.9921922e+08
A28: هامش صافي الربح | B28: =IFERROR(B23/B12,0) -> -1.6577941 | C28: =IFERROR(C23/C12,0) -> 0.11176048 | D28: =IFERROR(D23/D12,0) -> 0.3199644 | E28: =IFERROR(E23/E12,0) -> 0.36703904 | F28: =IFERROR(F23/F12,0) -> 0.37481394
A30: أساس الاحتساب: العوائد على متوسط المحفظة، الرسوم على المنح، تكلفة التمويل على متوسط رصيد الدين، المصروفات وفق الهيكل الوظيفي وخطة التشغيل، والضريبة 22.5% متى تحقق وعاء موجب.
A33: التسوية الضريبية Year 1-Year 5 - ترحيل الخسائر الضريبية
A34: البند | B34: Year 1 | C34: Year 2 | D34: Year 3 | E34: Year 4 | F34: Year 5
A35: الربح/(الخسارة) المحاسبي قبل الضريبة | B35: =B21 -> -8166870.8 | C35: =C21 -> 9569122.8 | D35: =D21 -> 99033950 | E35: =E21 -> 2.0637527e+08 | F35: =F21 -> 3.7388384e+08
A36: + إضافات ضريبية غير معترف بها محاسبيا (لا توجد فروق مؤقتة/دائمة محددة حاليا) | B36: 0 | C36: 0 | D36: 0 | E36: 0 | F36: 0
A37: - خصومات ضريبية إضافية (لا توجد حاليا) | B37: 0 | C37: 0 | D37: 0 | E37: 0 | F37: 0
A38: الوعاء الضريبي قبل ترحيل الخسائر (لا يقل عن صفر) | B38: =MAX(0,B35+B36-B37) -> 0 | C38: =MAX(0,C35+C36-C37) -> 9569122.8 | D38: =MAX(0,D35+D36-D37) -> 99033950 | E38: =MAX(0,E35+E36-E37) -> 2.0637527e+08 | F38: =MAX(0,F35+F36-F37) -> 3.7388384e+08
A39: خسائر ضريبية مرحلة - رصيد أول المدة | B39: 0 | C39: =B41 -> 8166870.8 | D39: =C41 -> 0 | E39: =D41 -> 0 | F39: =E41 -> 0
A40: الخسائر المستخدمة خلال السنة | B40: =MIN(B38,B39) -> 0 | C40: =MIN(C38,C39) -> 8166870.8 | D40: =MIN(D38,D39) -> 0 | E40: =MIN(E38,E39) -> 0 | F40: =MIN(F38,F39) -> 0
A41: خسائر ضريبية مرحلة - رصيد آخر المدة | B41: =B39-B40+MAX(0,-(B35+B36-B37)) -> 8166870.8 | C41: =C39-C40+MAX(0,-(C35+C36-C37)) -> 0 | D41: =D39-D40+MAX(0,-(D35+D36-D37)) -> 0 | E41: =E39-E40+MAX(0,-(E35+E36-E37)) -> 0 | F41: =F39-F40+MAX(0,-(F35+F36-F37)) -> 0
A42: الوعاء الضريبي بعد ترحيل الخسائر | B42: =B38-B40 -> 0 | C42: =C38-C40 -> 1402252 | D42: =D38-D40 -> 99033950 | E42: =E38-E40 -> 2.0637527e+08 | F42: =F38-F40 -> 3.7388384e+08
A43: معدل ضريبة الدخل | B43: =Assumptions!$B$33 -> 0.225 | C43: =Assumptions!$B$33 -> 0.225 | D43: =Assumptions!$B$33 -> 0.225 | E43: =Assumptions!$B$33 -> 0.225 | F43: =Assumptions!$B$33 -> 0.225
A44: الضريبة الحالية | B44: =MAX(0,B42*B43) -> 0 | C44: =MAX(0,C42*C43) -> 315506.7 | D44: =MAX(0,D42*D43) -> 22282639 | E44: =MAX(0,E42*E43) -> 46434436 | F44: =MAX(0,F42*F43) -> 84123865
A45: + الضريبة المؤجلة (غير محتسبة حاليا - تحتاج اعتماد مراقب الحسابات) | B45: 0 | C45: 0 | D45: 0 | E45: 0 | F45: 0
A46: صافي مصروف ضريبة الدخل (يربط تلقائيا بقائمة الدخل عبر Assumptions) | B46: =B44+B45 -> 0 | C46: =C44+C45 -> 315506.7 | D46: =D44+D45 -> 22282639 | E46: =E44+E45 -> 46434436 | F46: =F44+F45 -> 84123865
A47: ملاحظة: ترحل خسارة Year 1 وتستخدم مقابل الوعاء الضريبي الموجب في Year 2 وفق افتراض التخطيط الحالي. مبلغ الضريبة الناتج يتغير تلقائيا مع نتائج النموذج؛ ويظل خاضعا لتأكيد المستشار الضريبي/مراقب الحسابات بشأن شروط وحدود ترحيل الخسائر وأي فروق مؤقتة أو دائمة.

Sheet Balance Sheet
A1: قائمة المركز المالي التقديرية - خمس سنوات
A3: البند | B3: Year 1 | C3: Year 2 | D3: Year 3 | E3: Year 4 | F3: Year 5
A4: الأصول
A5: النقدية وما في حكمها | B5: ='Cash Flow'!B25 -> 3220918 | C5: ='Cash Flow'!C25 -> 9502515.4 | D5: ='Cash Flow'!D25 -> 13213489 | E5: ='Cash Flow'!E25 -> 65805120 | F5: ='Cash Flow'!F25 -> 2.4078058e+08
A6: إجمالي الاستثمار في عقود التأجير | B6: =Assumptions!B79 -> 20672304 | C6: =Assumptions!C79 -> 4.5260222e+08 | D6: =Assumptions!D79 -> 8.6656133e+08 | E6: =Assumptions!E79 -> 1.6674368e+09 | F6: =Assumptions!F79 -> 3.1254621e+09
A7: مخصص الخسائر الائتمانية | B7: =B6*Assumptions!$B$31 -> 620169.12 | C7: =C6*Assumptions!$B$31 -> 13578067 | D7: =D6*Assumptions!$B$31 -> 25996840 | E7: =E6*Assumptions!$B$31 -> 50023104 | F7: =F6*Assumptions!$B$31 -> 93763862
A8: صافي الاستثمار في عقود التأجير | B8: =B6-B7 -> 20052135 | C8: =C6-C7 -> 4.3902415e+08 | D8: =D6-D7 -> 8.4056449e+08 | E8: =E6-E7 -> 1.6174137e+09 | F8: =F6-F7 -> 3.0316982e+09
A9: أصول أخرى ومصروفات مدفوعة مقدما | B9: =Assumptions!B99 -> 258076.28 | C9: =Assumptions!C99 -> 258076.28 | D9: =Assumptions!D99 -> 258076.28 | E9: =Assumptions!E99 -> 258076.28 | F9: =Assumptions!F99 -> 258076.28
A10: صافي الأصول الثابتة وغير الملموسة | B10: =Assumptions!B11-'Income Statement'!B19 -> 4302000 | C10: =B10+Assumptions!C11-'Income Statement'!C19 -> 4802000 | D10: =C10+Assumptions!D11-'Income Statement'!D19 -> 4802000 | E10: =D10+Assumptions!E11-'Income Statement'!E19 -> 4802000 | F10: =E10+Assumptions!F11-'Income Statement'!F19 -> 4802000
A11: إجمالي الأصول | B11: =SUM(B5,B8:B10) -> 27833129 | C11: =SUM(C5,C8:C10) -> 4.5358675e+08 | D11: =SUM(D5,D8:D10) -> 8.5883806e+08 | E11: =SUM(E5,E8:E10) -> 1.6882789e+09 | F11: =SUM(F5,F8:F10) -> 3.2775389e+09
A13: الالتزامات
A14: قروض وتسهيلات بنكية | B14: =Assumptions!B90 -> 0 | C14: =Assumptions!C90 -> 370000000 | D14: =Assumptions!D90 -> 685000000 | E14: =Assumptions!E90 -> 1335000000 | F14: =Assumptions!F90 -> 2600000000
A15: رسوم مؤجلة ومقدمات عملاء والتزامات تشغيلية | B15: =Assumptions!B100 -> 6000000 | C15: =Assumptions!C100 -> 7500000 | D15: =Assumptions!D100 -> 21000000 | E15: =Assumptions!E100 -> 40500000 | F15: =Assumptions!F100 -> 75000000
A16: إجمالي الالتزامات | B16: =SUM(B14:B15) -> 6000000 | C16: =SUM(C14:C15) -> 377500000 | D16: =SUM(D14:D15) -> 706000000 | E16: =SUM(E14:E15) -> 1375500000 | F16: =SUM(F14:F15) -> 2675000000
A18: حقوق الملكية
A19: رأس المال المصدر والمدفوع | B19: =Assumptions!B91 -> 30000000 | C19: =Assumptions!C91 -> 75000000 | D19: =Assumptions!D91 -> 75000000 | E19: =Assumptions!E91 -> 75000000 | F19: =Assumptions!F91 -> 75000000
A20: الاحتياطي القانوني | B20: =Assumptions!B93 -> 0 | C20: =Assumptions!C93 -> 462680.8 | D20: =Assumptions!D93 -> 4300246.4 | E20: =Assumptions!E93 -> 12297288 | F20: =Assumptions!F93 -> 26785287
A21: الأرباح/(الخسائر) المرحلة | B21: =Assumptions!B92-B20 -> -8166870.8 | C21: =Assumptions!C92-C20 -> 624064.51 | D21: =Assumptions!D92-D20 -> 73537811 | E21: =Assumptions!E92-E20 -> 2.254816e+08 | F21: =Assumptions!F92-F20 -> 5.0075358e+08
A22: إجمالي حقوق الملكية | B22: =SUM(B19:B21) -> 21833129 | C22: =SUM(C19:C21) -> 76086745 | D22: =SUM(D19:D21) -> 1.5283806e+08 | E22: =SUM(E19:E21) -> 3.1277889e+08 | F22: =SUM(F19:F21) -> 6.0253887e+08
A23: إجمالي الالتزامات وحقوق الملكية | B23: =B16+B22 -> 27833129 | C23: =C16+C22 -> 4.5358675e+08 | D23: =D16+D22 -> 8.5883806e+08 | E23: =E16+E22 -> 1.6882789e+09 | F23: =F16+F22 -> 3.2775389e+09
A24: فحص التوازن | B24: =B23-B11 -> 0 | C24: =C23-C11 -> 0 | D24: =D23-D11 -> 0 | E24: =E23-E11 -> 0 | F24: =F23-F11 -> 0

Sheet Cash Flow
A1: قائمة التدفقات النقدية التقديرية - خمس سنوات
A3: البند | B3: Year 1 | C3: Year 2 | D3: Year 3 | E3: Year 4 | F3: Year 5
A4: التدفقات من أنشطة التشغيل
A5: صافي الربح | B5: ='Income Statement'!B23 -> -8166870.8 | C5: ='Income Statement'!C23 -> 9253616.1 | D5: ='Income Statement'!D23 -> 76751312 | E5: ='Income Statement'!E23 -> 1.5994083e+08 | F5: ='Income Statement'!F23 -> 2.8975998e+08
A6: الإهلاك والاستهلاك | B6: ='Income Statement'!B19 -> 0 | C6: ='Income Statement'!C19 -> 0 | D6: ='Income Statement'!D19 -> 1000000 | E6: ='Income Statement'!E19 -> 1500000 | F6: ='Income Statement'!F19 -> 2000000
A7: الزيادة في مخصص الخسائر الائتمانية | B7: ='Balance Sheet'!B7 -> 620169.12 | C7: ='Balance Sheet'!C7-'Balance Sheet'!B7 -> 12957897 | D7: ='Balance Sheet'!D7-'Balance Sheet'!C7 -> 12418773 | E7: ='Balance Sheet'!E7-'Balance Sheet'!D7 -> 24026264 | F7: ='Balance Sheet'!F7-'Balance Sheet'!E7 -> 43740758
A8: الزيادة في محفظة التأجير الإجمالية | B8: =-'Balance Sheet'!B6 -> -20672304 | C8: =-('Balance Sheet'!C6-'Balance Sheet'!B6) -> -4.3192992e+08 | D8: =-('Balance Sheet'!D6-'Balance Sheet'!C6) -> -4.1395911e+08 | E8: =-('Balance Sheet'!E6-'Balance Sheet'!D6) -> -8.0087547e+08 | F8: =-('Balance Sheet'!F6-'Balance Sheet'!E6) -> -1.4580253e+09
A9: التغير في الرسوم المؤجلة والالتزامات التشغيلية | B9: ='Balance Sheet'!B15 -> 6000000 | C9: ='Balance Sheet'!C15-'Balance Sheet'!B15 -> 1500000 | D9: ='Balance Sheet'!D15-'Balance Sheet'!C15 -> 13500000 | E9: ='Balance Sheet'!E15-'Balance Sheet'!D15 -> 19500000 | F9: ='Balance Sheet'!F15-'Balance Sheet'!E15 -> 34500000
A10: التغير في الأصول الأخرى | B10: =0 -> 0 | C10: =-('Balance Sheet'!C9-'Balance Sheet'!B9) -> 0 | D10: =-('Balance Sheet'!D9-'Balance Sheet'!C9) -> 0 | E10: =-('Balance Sheet'!E9-'Balance Sheet'!D9) -> 0 | F10: =-('Balance Sheet'!F9-'Balance Sheet'!E9) -> 0
A11: صافي التدفق من التشغيل | B11: =SUM(B5:B10) -> -22219006 | C11: =SUM(C5:C10) -> -4.082184e+08 | D11: =SUM(D5:D10) -> -3.1028903e+08 | E11: =SUM(E5:E10) -> -5.9590837e+08 | F11: =SUM(F5:F10) -> -1.0880245e+09
A13: التدفقات من أنشطة الاستثمار
A14: الإنفاق الرأسمالي | B14: =-Assumptions!B11 -> -4302000 | C14: =-Assumptions!C11 -> -500000 | D14: =-Assumptions!D11 -> -1000000 | E14: =-Assumptions!E11 -> -1500000 | F14: =-Assumptions!F11 -> -2000000
A15: صافي التدفق من الاستثمار | B15: =B14 -> -4302000 | C15: =C14 -> -500000 | D15: =D14 -> -1000000 | E15: =E14 -> -1500000 | F15: =F14 -> -2000000
A17: التدفقات من أنشطة التمويل
A18: الزيادة/(السداد) في التمويل البنكي | B18: =Assumptions!B90 -> 0 | C18: =Assumptions!C90-Assumptions!B90 -> 370000000 | D18: =Assumptions!D90-Assumptions!C90 -> 315000000 | E18: =Assumptions!E90-Assumptions!D90 -> 650000000 | F18: =Assumptions!F90-Assumptions!E90 -> 1265000000
A19: الزيادة في رأس المال المدفوع | B19: =15000000 -> 15000000 | C19: ='Balance Sheet'!C19-'Balance Sheet'!B19 -> 45000000 | D19: ='Balance Sheet'!D19-'Balance Sheet'!C19 -> 0 | E19: ='Balance Sheet'!E19-'Balance Sheet'!D19 -> 0 | F19: ='Balance Sheet'!F19-'Balance Sheet'!E19 -> 0
A20: توزيعات الأرباح | B20: =0 -> 0 | C20: =0 -> 0 | D20: =0 -> 0 | E20: =0 -> 0 | F20: =0 -> 0
A21: صافي التدفق من التمويل | B21: =SUM(B18:B20) -> 15000000 | C21: =SUM(C18:C20) -> 415000000 | D21: =SUM(D18:D20) -> 315000000 | E21: =SUM(E18:E20) -> 650000000 | F21: =SUM(F18:F20) -> 1265000000
A23: صافي التغير في النقدية | B23: =B11+B15+B21 -> -11521006 | C23: =C11+C15+C21 -> 6281597.4 | D23: =D11+D15+D21 -> 3710973.1 | E23: =E11+E15+E21 -> 52591631 | F23: =F11+F15+F21 -> 1.7497546e+08
A24: النقدية أول السنة | B24: =14741923.72 -> 14741924 | C24: =B25 -> 3220918 | D24: =C25 -> 9502515.4 | E24: =D25 -> 13213489 | F24: =E25 -> 65805120
A25: النقدية آخر السنة | B25: =B24+B23 -> 3220918 | C25: =C24+C23 -> 9502515.4 | D25: =D24+D23 -> 13213489 | E25: =E24+E23 -> 65805120 | F25: =F24+F23 -> 2.4078058e+08
A26: اختبار الربط بقائمة المركز المالي | B26: =B25-'Balance Sheet'!B5 -> 0 | C26: =C25-'Balance Sheet'!C5 -> 0 | D26: =D25-'Balance Sheet'!D5 -> 0 | E26: =E25-'Balance Sheet'!E5 -> 0 | F26: =F25-'Balance Sheet'!F5 -> 0
A27: حد التسهيلات البنكية المخطط | B27: =Assumptions!B101 -> 0 | C27: =Assumptions!C101 -> 420000000 | D27: =Assumptions!D101 -> 850000000 | E27: =Assumptions!E101 -> 1600000000 | F27: =Assumptions!F101 -> 3000000000
A28: سداد التمويل البنكي | B28: ='Funding & Liquidity'!B12 -> 0 | C28: ='Funding & Liquidity'!C12 -> 71677563 | D28: ='Funding & Liquidity'!D12 -> 292500000 | E28: ='Funding & Liquidity'!E12 -> 615000000 | F28: ='Funding & Liquidity'!F12 -> 1162500000
A29: لا يتضمن التدفق النقدي أي بند موازن غير مسمى. ينتج الرصيد الختامي من الربح، تغيرات المحفظة والمخصصات ورأس المال العامل، الإنفاق الرأسمالي، تغير الدين وزيادات رأس المال.

Sheet Investments
A1: الخطة الاستثمارية لخمس سنوات
A3: البند | B3: Year 1 | C3: Year 2 | D3: Year 3 | E3: Year 4 | F3: Year 5
A4: منصة التأجير والتكاملات | B4: 2300000 | C4: 200000 | D4: 400000 | E4: 550000 | F4: 700000
A5: الأمن السيبراني واستمرارية الأعمال | B5: 600000 | C5: 100000 | D5: 150000 | E5: 200000 | F5: 250000
A6: أجهزة ومعدات المركز الرئيسي | B6: 702000 | C6: 50000 | D6: 100000 | E6: 150000 | F6: 200000
A7: تجهيز مكاتب التوقيع وخدمات الأصول | B7: 500000 | C7: 50000 | D7: 200000 | E7: 400000 | F7: 650000
A8: تراخيص وبرمجيات | B8: 200000 | C8: 100000 | D8: 150000 | E8: 200000 | F8: 200000
A9: مخزن الأصول المستردة | B9: 0 | C9: 0 | D9: 0 | E9: 0 | F9: 0
A10: إجمالي الإنفاق الرأسمالي | B10: =SUM(B4:B9) -> 4302000 | C10: =SUM(C4:C9) -> 500000 | D10: =SUM(D4:D9) -> 1000000 | E10: =SUM(E4:E9) -> 1500000 | F10: =SUM(F4:F9) -> 2000000
A12: مخزن القاهرة في أول ثلاث سنوات، بإيجار تقديري 20 ألف جنيه شهريا، مفصح عنه فقط وغير مدرج في التكاليف أو الإنفاق الرأسمالي لحين التعاقد.

Sheet Feasibility
A1: معايير الجدوى واتخاذ القرار الاستثماري
A3: البند | B3: سنة 0 | C3: Year 1 | D3: Year 2 | E3: Year 3 | F3: Year 4 | G3: Year 5
A4: مساهمات رأس المال | B4: -15258076 | C4: -15000000 | D4: -45000000 | E4: 0 | F4: 0 | G4: 0
A5: توزيعات الأرباح | B5: 0 | C5: 0 | D5: 0 | E5: 0 | F5: 0 | G5: 0
A6: القيمة النهائية (صافي ربح Year 5 × مضاعف الربحية النهائي) | B6: 0 | C6: 0 | D6: 0 | E6: 0 | F6: 0 | G6: ='Income Statement'!F23*Assumptions!$B$40 -> 2.3180798e+09
A7: التدفق النقدي للمساهمين | B7: =B4+B5+B6 -> -15258076 | C7: =C4+C5+C6 -> -15000000 | D7: =D4+D5+D6 -> -45000000 | E7: =E4+E5+E6 -> 0 | F7: =F4+F5+F6 -> 0 | G7: =G4+G5+G6 -> 2.3180798e+09
A8: معامل الخصم | B8: =1 -> 1 | C8: =1/(1+$B$22)^1 -> 0.8 | D8: =1/(1+$B$22)^2 -> 0.64 | E8: =1/(1+$B$22)^3 -> 0.512 | F8: =1/(1+$B$22)^4 -> 0.4096 | G8: =1/(1+$B$22)^5 -> 0.32768
A9: التدفق المخصوم | B9: =B7*B8 -> -15258076 | C9: =C7*C8 -> -12000000 | D9: =D7*D8 -> -28800000 | E9: =E7*E8 -> 0 | F9: =F7*F8 -> 0 | G9: =G7*G8 -> 7.595884e+08
A10: التدفق المخصوم التراكمي | B10: =B9 -> -15258076 | C10: =B10+C9 -> -27258076 | D10: =C10+D9 -> -56058076 | E10: =D10+E9 -> -56058076 | F10: =E10+F9 -> -56058076 | G10: =F10+G9 -> 7.0353032e+08
A12: نتائج التقييم - مبنية على تدفقات المساهمين والقيمة النهائية
A13: صافي القيمة الحالية NPV | B13: =SUM(B9:G9) -> 7.0353032e+08
A14: معدل العائد الداخلي IRR | B14: =IRR(B7:G7) -> 1.3959752
A15: فترة الاسترداد | B15: =IF(B7>=0,0,IF(SUM(B7:C7)>=0,ABS(B7)/C7,IF(SUM(B7:D7)>=0,1+ABS(SUM(B7:C7))/D7,IF(SUM(B7:E7)>=0,2+ABS(SUM(B7:D7))/E7,IF(SUM(B7:F7)>=0,3+ABS(SUM(B7:E7))/F7,IF(SUM(B7:G7)>=0,4+ABS(SUM(B7:F7))/G7,"غير مسترد")))))) -> 4.0324657
A16: فترة الاسترداد المخصومة | B16: =IF(B9>=0,0,IF(SUM(B9:C9)>=0,ABS(B9)/C9,IF(SUM(B9:D9)>=0,1+ABS(SUM(B9:C9))/D9,IF(SUM(B9:E9)>=0,2+ABS(SUM(B9:D9))/E9,IF(SUM(B9:F9)>=0,3+ABS(SUM(B9:E9))/F9,IF(SUM(B9:G9)>=0,4+ABS(SUM(B9:F9))/G9,"غير مسترد")))))) -> 4.0738006
A17: معدل العائد المحاسبي ARR - مؤشر تخطيطي | B17: =IFERROR(AVERAGE('Income Statement'!B23:F23)/AVERAGE('Balance Sheet'!B19:F19),0) -> 1.5986026
A18: دليل الربحية PI | B18: =IFERROR(SUMIF(B9:G9,">0",B9:G9)/ABS(SUMIF(B9:G9,"<0",B9:G9)),0) -> 13.550026
A19: تكلفة الدين بعد الضريبة | B19: =SUMPRODUCT(Assumptions!B9:F9,'Balance Sheet'!B14:F14)/SUM('Balance Sheet'!B14:F14)*(1-Assumptions!$B$33) -> 0.13988828
A20: تكلفة رأس المال WACC | B20: =('Balance Sheet'!F14/('Balance Sheet'!F14+'Balance Sheet'!F22))*Assumptions!F9*(1-Assumptions!$B$33)+('Balance Sheet'!F22/('Balance Sheet'!F14+'Balance Sheet'!F22))*$B$22 -> 0.15399804
A21: الحكم الاستثماري - استرشادي | B21: =IF(B13>0,"مجد استرشاديا وفق افتراض القيمة النهائية","غير مجد وفق الافتراضات الحالية") -> مجد استرشاديا وفق افتراض القيمة النهائية
A22: تكلفة حقوق الملكية | B22: =25% -> 0.25
A24: بدائل التمويل
A25: المصدر | B25: الحجم المقترح | C25: العمر | D25: التسعير | E25: القسط/السداد | F25: المزايا | G25: القيود
A26: تسهيل دوار | B26: 600000000 | C26: 12 شهر متجدد | D26: سعر مرجعي + 3% | E26: سداد من التحصيلات | F26: مرونة السحب | G26: تغير السعر وقصر الأجل
A27: تمويل متوسط الأجل | B27: 1200000000 | C27: 3 سنوات | D27: متغير أو ثابت وفق العرض | E27: أقساط أصل متساوية | F27: مطابقة أفضل للأجل | G27: ضمانات وتعهدات
A28: توريق بعد تكوين سجل أداء | B28: 1000000000 | C28: مرتبط بعمر المحفظة | D28: وفق السوق والتصنيف | E28: من تدفقات المحفظة | F28: تنويع مصادر التمويل | G28: يتطلب محفظة وسجل تحصيل
A29: ملاحظة: NPV/IRR/PI/Payback هي عوائد مساهمين، وليست تدفقات تشغيلية للمشروع. لا توجد توزيعات أرباح مفترضة خلال Year 1-Year 5، والقيمة النهائية = صافي ربح Year 5 × مضاعف الربحية في Assumptions!B40؛ لذلك لا يجوز اعتماد الحكم الاستثماري دون قراءة حساسية مضاعف الخروج والتحقق من إمكانية التوزيع/الخروج فعليا. | B29: 2800000000

Sheet Ratios
A1: المؤشرات والنسب المالية
A3: البند | B3: Year 1 | C3: Year 2 | D3: Year 3 | E3: Year 4 | F3: Year 5
A4: السيولة
A5: نسبة تغطية السيولة LCR | B5: ='Funding & Liquidity'!B21 -> 4.5399059 | C5: ='Funding & Liquidity'!C21 -> 1.1073139 | D5: ='Funding & Liquidity'!D21 -> 1.34692 | E5: ='Funding & Liquidity'!E21 -> 4.6489449 | F5: ='Funding & Liquidity'!F21 -> 9.697416
A6: نسبة صافي التمويل المستقر NSFR | B6: ='Funding & Liquidity'!B35 -> 1.0984709 | C6: ='Funding & Liquidity'!C35 -> 1.0778519 | D6: ='Funding & Liquidity'!D35 -> 1.0914494 | E6: ='Funding & Liquidity'!E35 -> 1.1190646 | F6: ='Funding & Liquidity'!F35 -> 1.1614912
A7: النقدية / إجمالي الأصول | B7: =IFERROR('Balance Sheet'!B5/'Balance Sheet'!B11,0) -> 0.11572245 | C7: =IFERROR('Balance Sheet'!C5/'Balance Sheet'!C11,0) -> 0.02094972 | D7: =IFERROR('Balance Sheet'!D5/'Balance Sheet'!D11,0) -> 0.015385309 | E7: =IFERROR('Balance Sheet'!E5/'Balance Sheet'!E11,0) -> 0.038977636 | F7: =IFERROR('Balance Sheet'!F5/'Balance Sheet'!F11,0) -> 0.073463836
A8: أشهر تغطية المصروفات النقدية | B8: =IFERROR('Balance Sheet'!B5/(('Income Statement'!B15+'Income Statement'!B17+'Income Statement'!B18)/12),0) -> 2.4790098 | C8: =IFERROR('Balance Sheet'!C5/(('Income Statement'!C15+'Income Statement'!C17+'Income Statement'!C18)/12),0) -> 1.8919383 | D8: =IFERROR('Balance Sheet'!D5/(('Income Statement'!D15+'Income Statement'!D17+'Income Statement'!D18)/12),0) -> 1.191999 | E8: =IFERROR('Balance Sheet'!E5/(('Income Statement'!E15+'Income Statement'!E17+'Income Statement'!E18)/12),0) -> 3.6786921 | F8: =IFERROR('Balance Sheet'!F5/(('Income Statement'!F15+'Income Statement'!F17+'Income Statement'!F18)/12),0) -> 7.7369113
A10: الربحية
A11: العائد على الأصول ROA | B11: =IFERROR('Income Statement'!B23/AVERAGE(15000000,'Balance Sheet'!B11),0) -> -0.3813343 | C11: =IFERROR('Income Statement'!C23/AVERAGE('Balance Sheet'!B11,'Balance Sheet'!C11),0) -> 0.038443016 | D11: =IFERROR('Income Statement'!D23/AVERAGE('Balance Sheet'!C11,'Balance Sheet'!D11),0) -> 0.11696108 | E11: =IFERROR('Income Statement'!E23/AVERAGE('Balance Sheet'!D11,'Balance Sheet'!E11),0) -> 0.12558578 | F11: =IFERROR('Income Statement'!F23/AVERAGE('Balance Sheet'!E11,'Balance Sheet'!F11),0) -> 0.11670182
A12: العائد على حقوق الملكية ROE | B12: =IFERROR('Income Statement'!B23/AVERAGE(15000000,'Balance Sheet'!B22),0) -> -0.44345245 | C12: =IFERROR('Income Statement'!C23/AVERAGE('Balance Sheet'!B22,'Balance Sheet'!C22),0) -> 0.18900384 | D12: =IFERROR('Income Statement'!D23/AVERAGE('Balance Sheet'!C22,'Balance Sheet'!D22),0) -> 0.67053732 | E12: =IFERROR('Income Statement'!E23/AVERAGE('Balance Sheet'!D22,'Balance Sheet'!E22),0) -> 0.68700607 | F12: =IFERROR('Income Statement'!F23/AVERAGE('Balance Sheet'!E22,'Balance Sheet'!F22),0) -> 0.63313527
A13: العائد على الاستثمار ROI | B13: =IFERROR('Income Statement'!B27/AVERAGE('Balance Sheet'!B22+'Balance Sheet'!B14-'Balance Sheet'!B5,1),0) -> -0.87758195 | C13: =IFERROR('Income Statement'!C27/AVERAGE('Balance Sheet'!C22+'Balance Sheet'!C14-'Balance Sheet'!C5,1),0) -> 0.2144357 | D13: =IFERROR('Income Statement'!D27/AVERAGE('Balance Sheet'!D22+'Balance Sheet'!D14-'Balance Sheet'!D5,1),0) -> 0.48957176 | E13: =IFERROR('Income Statement'!E27/AVERAGE('Balance Sheet'!E22+'Balance Sheet'!E14-'Balance Sheet'!E5,1),0) -> 0.4844616 | F13: =IFERROR('Income Statement'!F27/AVERAGE('Balance Sheet'!F22+'Balance Sheet'!F14-'Balance Sheet'!F5,1),0) -> 0.47216494
A14: هامش صافي الربح | B14: ='Income Statement'!B28 -> -1.6577941 | C14: ='Income Statement'!C28 -> 0.11176048 | D14: ='Income Statement'!D28 -> 0.3199644 | E14: ='Income Statement'!E28 -> 0.36703904 | F14: ='Income Statement'!F28 -> 0.37481394
A15: تغطية تكلفة التمويل | B15: =IFERROR(('Income Statement'!B21+'Income Statement'!B15)/'Income Statement'!B15,0) -> 0 | C15: =IFERROR(('Income Statement'!C21+'Income Statement'!C15)/'Income Statement'!C15,0) -> 1.2569547 | D15: =IFERROR(('Income Statement'!D21+'Income Statement'!D15)/'Income Statement'!D15,0) -> 1.9631545 | E15: =IFERROR(('Income Statement'!E21+'Income Statement'!E15)/'Income Statement'!E15,0) -> 2.1670994 | F15: =IFERROR(('Income Statement'!F21+'Income Statement'!F15)/'Income Statement'!F15,0) -> 2.1492259
A17: الملكية والرافعة
A18: مضاعف الاقتراض الرقابي للهيئة | B18: ='Regulatory Capital Plan'!B13 -> 0 | C18: ='Regulatory Capital Plan'!C13 -> 4.8628706 | D18: ='Regulatory Capital Plan'!D13 -> 4.5679805 | E18: ='Regulatory Capital Plan'!E13 -> 4.3078733 | F18: ='Regulatory Capital Plan'!F13 -> 4.3358071
A19: سقف مضاعف الاقتراض للهيئة | B19: ='Regulatory Capital Plan'!B14 -> 4 | C19: ='Regulatory Capital Plan'!C14 -> 4 | D19: ='Regulatory Capital Plan'!D14 -> 9 | E19: ='Regulatory Capital Plan'!E14 -> 9 | F19: ='Regulatory Capital Plan'!F14 -> 9
A20: حقوق الملكية / إجمالي الأصول | B20: =IFERROR('Balance Sheet'!B22/'Balance Sheet'!B11,0) -> 0.78442956 | C20: =IFERROR('Balance Sheet'!C22/'Balance Sheet'!C11,0) -> 0.16774464 | D20: =IFERROR('Balance Sheet'!D22/'Balance Sheet'!D11,0) -> 0.17795911 | E20: =IFERROR('Balance Sheet'!E22/'Balance Sheet'!E11,0) -> 0.18526494 | F20: =IFERROR('Balance Sheet'!F22/'Balance Sheet'!F11,0) -> 0.18383882
A21: الدين / حقوق الملكية | B21: =IFERROR('Balance Sheet'!B14/'Balance Sheet'!B22,0) -> 0 | C21: =IFERROR('Balance Sheet'!C14/'Balance Sheet'!C22,0) -> 4.8628706 | D21: =IFERROR('Balance Sheet'!D14/'Balance Sheet'!D22,0) -> 4.481868 | E21: =IFERROR('Balance Sheet'!E14/'Balance Sheet'!E22,0) -> 4.2681908 | F21: =IFERROR('Balance Sheet'!F14/'Balance Sheet'!F22,0) -> 4.3150743
A22: كفاية رأس المال CAR | B22: ='Regulatory Capital Plan'!B31 -> 0.39828096 | C22: ='Regulatory Capital Plan'!C31 -> 0.14432739 | D22: ='Regulatory Capital Plan'!D31 -> 0.15976352 | E22: ='Regulatory Capital Plan'!E31 -> 0.1720075 | F22: ='Regulatory Capital Plan'!F31 -> 0.17792877
A23: هامش CAR فوق الحد الأدنى | B23: =B22-'Regulatory Capital Plan'!B32 -> 0.27828096 | C23: =C22-'Regulatory Capital Plan'!C32 -> 0.024327395 | D23: =D22-'Regulatory Capital Plan'!D32 -> 0.039763521 | E23: =E22-'Regulatory Capital Plan'!E32 -> 0.052007505 | F23: =F22-'Regulatory Capital Plan'!F32 -> 0.057928766
A25: مؤشرات أخرى
A26: مخصص الخسائر / المحفظة | B26: =IFERROR('Balance Sheet'!B7/'Balance Sheet'!B6,0) -> 0.03 | C26: =IFERROR('Balance Sheet'!C7/'Balance Sheet'!C6,0) -> 0.03 | D26: =IFERROR('Balance Sheet'!D7/'Balance Sheet'!D6,0) -> 0.03 | E26: =IFERROR('Balance Sheet'!E7/'Balance Sheet'!E6,0) -> 0.03 | F26: =IFERROR('Balance Sheet'!F7/'Balance Sheet'!F6,0) -> 0.03
A27: حد العميل الواحد | B27: ='Regulatory Capital Plan'!B36 -> 5775578.8 | C27: ='Regulatory Capital Plan'!C36 -> 21961664 | D27: ='Regulatory Capital Plan'!D36 -> 44987057 | E27: ='Regulatory Capital Plan'!E36 -> 92969307 | F27: ='Regulatory Capital Plan'!F36 -> 1.798973e+08
A28: الحد الداخلي المخطط | B28: ='Regulatory Capital Plan'!B37 -> 4812982.3 | C28: ='Regulatory Capital Plan'!C37 -> 18301386 | D28: ='Regulatory Capital Plan'!D37 -> 37489214 | E28: ='Regulatory Capital Plan'!E37 -> 77474423 | F28: ='Regulatory Capital Plan'!F37 -> 1.4991442e+08
A29: حالة التركز | B29: ='Regulatory Capital Plan'!B39 -> بيانات معلقة - سجل تركز العملاء/الأطراف المرتبطة مطلوب | C29: ='Regulatory Capital Plan'!C39 -> بيانات معلقة - سجل تركز العملاء/الأطراف المرتبطة مطلوب | D29: ='Regulatory Capital Plan'!D39 -> بيانات معلقة - سجل تركز العملاء/الأطراف المرتبطة مطلوب | E29: ='Regulatory Capital Plan'!E39 -> بيانات معلقة - سجل تركز العملاء/الأطراف المرتبطة مطلوب | F29: ='Regulatory Capital Plan'!F39 -> بيانات معلقة - سجل تركز العملاء/الأطراف المرتبطة مطلوب

Sheet Scenarios
A1: تحليل حساسية قائمة الدخل - ليس إعادة تشغيل كاملة للتمويل والسيولة
A3: المحرك | B3: أفضل | C3: أساسي | D3: أسوأ
A4: معامل حجم المنح | B4: 1.15 | C4: 1 | D4: 0.8
A5: تغير عائد العميل | B5: 0.02 | C5: 0 | D5: -0.03
A6: تغير تكلفة التمويل | B6: -0.02 | C6: 0 | D6: 0.03
A7: معامل الخسائر الائتمانية | B7: 0.75 | C7: 1 | D7: 1.5
A8: معامل المصروفات التشغيلية | B8: 0.95 | C8: 1 | D8: 1.1
A10: صافي الربح حسب الحساسية - تعديل جبري لمخرجات قائمة الدخل فقط
A11: السيناريو | B11: Year 1 | C11: Year 2 | D11: Year 3 | E11: Year 4 | F11: Year 5
A12: أفضل | B12: =MAX(0,(('Income Statement'!B9*(1+$B$5/Assumptions!B6)+'Income Statement'!B10+'Income Statement'!B13)*$B$4-'Income Statement'!B15-('Income Statement'!B16*$B$7)-('Income Statement'!B17+'Income Statement'!B18+'Income Statement'!B19)*$B$8)*(1-Assumptions!$B$33))+MIN(0,(('Income Statement'!B9*(1+$B$5/Assumptions!B6)+'Income Statement'!B10+'Income Statement'!B13)*$B$4-'Income Statement'!B15-('Income Statement'!B16*$B$7)-('Income Statement'!B17+'Income Statement'!B18+'Income Statement'!B19)*$B$8)) -> -5786178.7 | C12: =MAX(0,(('Income Statement'!C9*(1+$B$5/Assumptions!C6)+'Income Statement'!C10+'Income Statement'!C13)*$B$4-'Income Statement'!C15-('Income Statement'!C16*$B$7)-('Income Statement'!C17+'Income Statement'!C18+'Income Statement'!C19)*$B$8)*(1-Assumptions!$B$33))+MIN(0,(('Income Statement'!C9*(1+$B$5/Assumptions!C6)+'Income Statement'!C10+'Income Statement'!C13)*$B$4-'Income Statement'!C15-('Income Statement'!C16*$B$7)-('Income Statement'!C17+'Income Statement'!C18+'Income Statement'!C19)*$B$8)) -> 22999766 | D12: =MAX(0,(('Income Statement'!D9*(1+$B$5/Assumptions!D6)+'Income Statement'!D10+'Income Statement'!D13)*$B$4-'Income Statement'!D15-('Income Statement'!D16*$B$7)-('Income Statement'!D17+'Income Statement'!D18+'Income Statement'!D19)*$B$8)*(1-Assumptions!$B$33))+MIN(0,(('Income Statement'!D9*(1+$B$5/Assumptions!D6)+'Income Statement'!D10+'Income Statement'!D13)*$B$4-'Income Statement'!D15-('Income Statement'!D16*$B$7)-('Income Statement'!D17+'Income Statement'!D18+'Income Statement'!D19)*$B$8)) -> 1.2065988e+08 | E12: =MAX(0,(('Income Statement'!E9*(1+$B$5/Assumptions!E6)+'Income Statement'!E10+'Income Statement'!E13)*$B$4-'Income Statement'!E15-('Income Statement'!E16*$B$7)-('Income Statement'!E17+'Income Statement'!E18+'Income Statement'!E19)*$B$8)*(1-Assumptions!$B$33))+MIN(0,(('Income Statement'!E9*(1+$B$5/Assumptions!E6)+'Income Statement'!E10+'Income Statement'!E13)*$B$4-'Income Statement'!E15-('Income Statement'!E16*$B$7)-('Income Statement'!E17+'Income Statement'!E18+'Income Statement'!E19)*$B$8)) -> 2.4061682e+08 | F12: =MAX(0,(('Income Statement'!F9*(1+$B$5/Assumptions!F6)+'Income Statement'!F10+'Income Statement'!F13)*$B$4-'Income Statement'!F15-('Income Statement'!F16*$B$7)-('Income Statement'!F17+'Income Statement'!F18+'Income Statement'!F19)*$B$8)*(1-Assumptions!$B$33))+MIN(0,(('Income Statement'!F9*(1+$B$5/Assumptions!F6)+'Income Statement'!F10+'Income Statement'!F13)*$B$4-'Income Statement'!F15-('Income Statement'!F16*$B$7)-('Income Statement'!F17+'Income Statement'!F18+'Income Statement'!F19)*$B$8)) -> 4.3508868e+08
A13: أساسي | B13: ='Income Statement'!B23 -> -8166870.8 | C13: ='Income Statement'!C23 -> 9253616.1 | D13: ='Income Statement'!D23 -> 76751312 | E13: ='Income Statement'!E23 -> 1.5994083e+08 | F13: ='Income Statement'!F23 -> 2.8975998e+08
A14: أسوأ | B14: =MAX(0,(('Income Statement'!B9*(1+$D$5/Assumptions!B6)+'Income Statement'!B10+'Income Statement'!B13)*$D$4-'Income Statement'!B15-('Income Statement'!B16*$D$7)-('Income Statement'!B17+'Income Statement'!B18+'Income Statement'!B19)*$D$8)*(1-Assumptions!$B$33))+MIN(0,(('Income Statement'!B9*(1+$D$5/Assumptions!B6)+'Income Statement'!B10+'Income Statement'!B13)*$D$4-'Income Statement'!B15-('Income Statement'!B16*$D$7)-('Income Statement'!B17+'Income Statement'!B18+'Income Statement'!B19)*$D$8)) -> -11894810 | C14: =MAX(0,(('Income Statement'!C9*(1+$D$5/Assumptions!C6)+'Income Statement'!C10+'Income Statement'!C13)*$D$4-'Income Statement'!C15-('Income Statement'!C16*$D$7)-('Income Statement'!C17+'Income Statement'!C18+'Income Statement'!C19)*$D$8)*(1-Assumptions!$B$33))+MIN(0,(('Income Statement'!C9*(1+$D$5/Assumptions!C6)+'Income Statement'!C10+'Income Statement'!C13)*$D$4-'Income Statement'!C15-('Income Statement'!C16*$D$7)-('Income Statement'!C17+'Income Statement'!C18+'Income Statement'!C19)*$D$8)) -> -19213189 | D14: =MAX(0,(('Income Statement'!D9*(1+$D$5/Assumptions!D6)+'Income Statement'!D10+'Income Statement'!D13)*$D$4-'Income Statement'!D15-('Income Statement'!D16*$D$7)-('Income Statement'!D17+'Income Statement'!D18+'Income Statement'!D19)*$D$8)*(1-Assumptions!$B$33))+MIN(0,(('Income Statement'!D9*(1+$D$5/Assumptions!D6)+'Income Statement'!D10+'Income Statement'!D13)*$D$4-'Income Statement'!D15-('Income Statement'!D16*$D$7)-('Income Statement'!D17+'Income Statement'!D18+'Income Statement'!D19)*$D$8)) -> 19204317 | E14: =MAX(0,(('Income Statement'!E9*(1+$D$5/Assumptions!E6)+'Income Statement'!E10+'Income Statement'!E13)*$D$4-'Income Statement'!E15-('Income Statement'!E16*$D$7)-('Income Statement'!E17+'Income Statement'!E18+'Income Statement'!E19)*$D$8)*(1-Assumptions!$B$33))+MIN(0,(('Income Statement'!E9*(1+$D$5/Assumptions!E6)+'Income Statement'!E10+'Income Statement'!E13)*$D$4-'Income Statement'!E15-('Income Statement'!E16*$D$7)-('Income Statement'!E17+'Income Statement'!E18+'Income Statement'!E19)*$D$8)) -> 54799586 | F14: =MAX(0,(('Income Statement'!F9*(1+$D$5/Assumptions!F6)+'Income Statement'!F10+'Income Statement'!F13)*$D$4-'Income Statement'!F15-('Income Statement'!F16*$D$7)-('Income Statement'!F17+'Income Statement'!F18+'Income Statement'!F19)*$D$8)*(1-Assumptions!$B$33))+MIN(0,(('Income Statement'!F9*(1+$D$5/Assumptions!F6)+'Income Statement'!F10+'Income Statement'!F13)*$D$4-'Income Statement'!F15-('Income Statement'!F16*$D$7)-('Income Statement'!F17+'Income Statement'!F18+'Income Statement'!F19)*$D$8)) -> 1.0142551e+08
A16: ملخص النتائج
A17: المؤشر | B17: أفضل | C17: أساسي | D17: أسوأ
A18: إجمالي صافي الربح | B18: =SUM(B12:F12) -> 8.1357896e+08 | C18: =SUM(B13:F13) -> 5.2753887e+08 | D18: =SUM(B14:F14) -> 1.4432141e+08
A19: صافي ربح Year 5 | B19: =F12 -> 4.3508868e+08 | C19: =F13 -> 2.8975998e+08 | D19: =F14 -> 1.0142551e+08
A20: النتيجة - حساسية ربحية فقط | B20: =IF(B18>0,"موجب - يلزم إعادة اختبار التمويل والسيولة وCAR","سالب - يلزم إعادة اختبار التمويل والسيولة وCAR") -> موجب - يلزم إعادة اختبار التمويل والسيولة وCAR | C20: =IF(C18>0,"موجب - يلزم إعادة اختبار التمويل والسيولة وCAR","سالب - يلزم إعادة اختبار التمويل والسيولة وCAR") -> موجب - يلزم إعادة اختبار التمويل والسيولة وCAR | D20: =IF(D18>0,"موجب - يلزم إعادة اختبار التمويل والسيولة وCAR","سالب - يلزم إعادة اختبار التمويل والسيولة وCAR") -> موجب - يلزم إعادة اختبار التمويل والسيولة وCAR

Sheet Sensitivity
A1: تحليل الحساسية - صافي ربح Year 5
A3: تغير عائد العميل / معامل المنح | B3: 80% | C3: 90% | D3: 100% | E3: 110% | F3: 120%
A4: -0.04 | B4: =MAX(0,(('Income Statement'!F9*(1+$A4/Assumptions!F6)+'Income Statement'!F10+'Income Statement'!F13)*0.8-'Income Statement'!F15-'Income Statement'!F16-'Income Statement'!F17-'Income Statement'!F18-'Income Statement'!F19)*(1-Assumptions!$B$33))+MIN(0,(('Income Statement'!F9*(1+$A4/Assumptions!F6)+'Income Statement'!F10+'Income Statement'!F13)*0.8-'Income Statement'!F15-'Income Statement'!F16-'Income Statement'!F17-'Income Statement'!F18-'Income Statement'!F19)) -> 1.0740112e+08 | C4: =MAX(0,(('Income Statement'!F9*(1+$A4/Assumptions!F6)+'Income Statement'!F10+'Income Statement'!F13)*0.9-'Income Statement'!F15-'Income Statement'!F16-'Income Statement'!F17-'Income Statement'!F18-'Income Statement'!F19)*(1-Assumptions!$B$33))+MIN(0,(('Income Statement'!F9*(1+$A4/Assumptions!F6)+'Income Statement'!F10+'Income Statement'!F13)*0.9-'Income Statement'!F15-'Income Statement'!F16-'Income Statement'!F17-'Income Statement'!F18-'Income Statement'!F19)) -> 1.6143558e+08 | D4: =MAX(0,(('Income Statement'!F9*(1+$A4/Assumptions!F6)+'Income Statement'!F10+'Income Statement'!F13)*1-'Income Statement'!F15-'Income Statement'!F16-'Income Statement'!F17-'Income Statement'!F18-'Income Statement'!F19)*(1-Assumptions!$B$33))+MIN(0,(('Income Statement'!F9*(1+$A4/Assumptions!F6)+'Income Statement'!F10+'Income Statement'!F13)*1-'Income Statement'!F15-'Income Statement'!F16-'Income Statement'!F17-'Income Statement'!F18-'Income Statement'!F19)) -> 2.1547005e+08 | E4: =MAX(0,(('Income Statement'!F9*(1+$A4/Assumptions!F6)+'Income Statement'!F10+'Income Statement'!F13)*1.1-'Income Statement'!F15-'Income Statement'!F16-'Income Statement'!F17-'Income Statement'!F18-'Income Statement'!F19)*(1-Assumptions!$B$33))+MIN(0,(('Income Statement'!F9*(1+$A4/Assumptions!F6)+'Income Statement'!F10+'Income Statement'!F13)*1.1-'Income Statement'!F15-'Income Statement'!F16-'Income Statement'!F17-'Income Statement'!F18-'Income Statement'!F19)) -> 2.6950451e+08 | F4: =MAX(0,(('Income Statement'!F9*(1+$A4/Assumptions!F6)+'Income Statement'!F10+'Income Statement'!F13)*1.2-'Income Statement'!F15-'Income Statement'!F16-'Income Statement'!F17-'Income Statement'!F18-'Income Statement'!F19)*(1-Assumptions!$B$33))+MIN(0,(('Income Statement'!F9*(1+$A4/Assumptions!F6)+'Income Statement'!F10+'Income Statement'!F13)*1.2-'Income Statement'!F15-'Income Statement'!F16-'Income Statement'!F17-'Income Statement'!F18-'Income Statement'!F19)) -> 3.2353897e+08
A5: -0.02 | B5: =MAX(0,(('Income Statement'!F9*(1+$A5/Assumptions!F6)+'Income Statement'!F10+'Income Statement'!F13)*0.8-'Income Statement'!F15-'Income Statement'!F16-'Income Statement'!F17-'Income Statement'!F18-'Income Statement'!F19)*(1-Assumptions!$B$33))+MIN(0,(('Income Statement'!F9*(1+$A5/Assumptions!F6)+'Income Statement'!F10+'Income Statement'!F13)*0.8-'Income Statement'!F15-'Income Statement'!F16-'Income Statement'!F17-'Income Statement'!F18-'Income Statement'!F19)) -> 1.3711709e+08 | C5: =MAX(0,(('Income Statement'!F9*(1+$A5/Assumptions!F6)+'Income Statement'!F10+'Income Statement'!F13)*0.9-'Income Statement'!F15-'Income Statement'!F16-'Income Statement'!F17-'Income Statement'!F18-'Income Statement'!F19)*(1-Assumptions!$B$33))+MIN(0,(('Income Statement'!F9*(1+$A5/Assumptions!F6)+'Income Statement'!F10+'Income Statement'!F13)*0.9-'Income Statement'!F15-'Income Statement'!F16-'Income Statement'!F17-'Income Statement'!F18-'Income Statement'!F19)) -> 1.9486605e+08 | D5: =MAX(0,(('Income Statement'!F9*(1+$A5/Assumptions!F6)+'Income Statement'!F10+'Income Statement'!F13)*1-'Income Statement'!F15-'Income Statement'!F16-'Income Statement'!F17-'Income Statement'!F18-'Income Statement'!F19)*(1-Assumptions!$B$33))+MIN(0,(('Income Statement'!F9*(1+$A5/Assumptions!F6)+'Income Statement'!F10+'Income Statement'!F13)*1-'Income Statement'!F15-'Income Statement'!F16-'Income Statement'!F17-'Income Statement'!F18-'Income Statement'!F19)) -> 2.5261501e+08 | E5: =MAX(0,(('Income Statement'!F9*(1+$A5/Assumptions!F6)+'Income Statement'!F10+'Income Statement'!F13)*1.1-'Income Statement'!F15-'Income Statement'!F16-'Income Statement'!F17-'Income Statement'!F18-'Income Statement'!F19)*(1-Assumptions!$B$33))+MIN(0,(('Income Statement'!F9*(1+$A5/Assumptions!F6)+'Income Statement'!F10+'Income Statement'!F13)*1.1-'Income Statement'!F15-'Income Statement'!F16-'Income Statement'!F17-'Income Statement'!F18-'Income Statement'!F19)) -> 3.1036397e+08 | F5: =MAX(0,(('Income Statement'!F9*(1+$A5/Assumptions!F6)+'Income Statement'!F10+'Income Statement'!F13)*1.2-'Income Statement'!F15-'Income Statement'!F16-'Income Statement'!F17-'Income Statement'!F18-'Income Statement'!F19)*(1-Assumptions!$B$33))+MIN(0,(('Income Statement'!F9*(1+$A5/Assumptions!F6)+'Income Statement'!F10+'Income Statement'!F13)*1.2-'Income Statement'!F15-'Income Statement'!F16-'Income Statement'!F17-'Income Statement'!F18-'Income Statement'!F19)) -> 3.6811293e+08
A6: 0 | B6: =MAX(0,(('Income Statement'!F9*(1+$A6/Assumptions!F6)+'Income Statement'!F10+'Income Statement'!F13)*0.8-'Income Statement'!F15-'Income Statement'!F16-'Income Statement'!F17-'Income Statement'!F18-'Income Statement'!F19)*(1-Assumptions!$B$33))+MIN(0,(('Income Statement'!F9*(1+$A6/Assumptions!F6)+'Income Statement'!F10+'Income Statement'!F13)*0.8-'Income Statement'!F15-'Income Statement'!F16-'Income Statement'!F17-'Income Statement'!F18-'Income Statement'!F19)) -> 1.6683307e+08 | C6: =MAX(0,(('Income Statement'!F9*(1+$A6/Assumptions!F6)+'Income Statement'!F10+'Income Statement'!F13)*0.9-'Income Statement'!F15-'Income Statement'!F16-'Income Statement'!F17-'Income Statement'!F18-'Income Statement'!F19)*(1-Assumptions!$B$33))+MIN(0,(('Income Statement'!F9*(1+$A6/Assumptions!F6)+'Income Statement'!F10+'Income Statement'!F13)*0.9-'Income Statement'!F15-'Income Statement'!F16-'Income Statement'!F17-'Income Statement'!F18-'Income Statement'!F19)) -> 2.2829652e+08 | D6: =MAX(0,(('Income Statement'!F9*(1+$A6/Assumptions!F6)+'Income Statement'!F10+'Income Statement'!F13)*1-'Income Statement'!F15-'Income Statement'!F16-'Income Statement'!F17-'Income Statement'!F18-'Income Statement'!F19)*(1-Assumptions!$B$33))+MIN(0,(('Income Statement'!F9*(1+$A6/Assumptions!F6)+'Income Statement'!F10+'Income Statement'!F13)*1-'Income Statement'!F15-'Income Statement'!F16-'Income Statement'!F17-'Income Statement'!F18-'Income Statement'!F19)) -> 2.8975998e+08 | E6: =MAX(0,(('Income Statement'!F9*(1+$A6/Assumptions!F6)+'Income Statement'!F10+'Income Statement'!F13)*1.1-'Income Statement'!F15-'Income Statement'!F16-'Income Statement'!F17-'Income Statement'!F18-'Income Statement'!F19)*(1-Assumptions!$B$33))+MIN(0,(('Income Statement'!F9*(1+$A6/Assumptions!F6)+'Income Statement'!F10+'Income Statement'!F13)*1.1-'Income Statement'!F15-'Income Statement'!F16-'Income Statement'!F17-'Income Statement'!F18-'Income Statement'!F19)) -> 3.5122344e+08 | F6: =MAX(0,(('Income Statement'!F9*(1+$A6/Assumptions!F6)+'Income Statement'!F10+'Income Statement'!F13)*1.2-'Income Statement'!F15-'Income Statement'!F16-'Income Statement'!F17-'Income Statement'!F18-'Income Statement'!F19)*(1-Assumptions!$B$33))+MIN(0,(('Income Statement'!F9*(1+$A6/Assumptions!F6)+'Income Statement'!F10+'Income Statement'!F13)*1.2-'Income Statement'!F15-'Income Statement'!F16-'Income Statement'!F17-'Income Statement'!F18-'Income Statement'!F19)) -> 4.1268689e+08
A7: 0.02 | B7: =MAX(0,(('Income Statement'!F9*(1+$A7/Assumptions!F6)+'Income Statement'!F10+'Income Statement'!F13)*0.8-'Income Statement'!F15-'Income Statement'!F16-'Income Statement'!F17-'Income Statement'!F18-'Income Statement'!F19)*(1-Assumptions!$B$33))+MIN(0,(('Income Statement'!F9*(1+$A7/Assumptions!F6)+'Income Statement'!F10+'Income Statement'!F13)*0.8-'Income Statement'!F15-'Income Statement'!F16-'Income Statement'!F17-'Income Statement'!F18-'Income Statement'!F19)) -> 1.9654904e+08 | C7: =MAX(0,(('Income Statement'!F9*(1+$A7/Assumptions!F6)+'Income Statement'!F10+'Income Statement'!F13)*0.9-'Income Statement'!F15-'Income Statement'!F16-'Income Statement'!F17-'Income Statement'!F18-'Income Statement'!F19)*(1-Assumptions!$B$33))+MIN(0,(('Income Statement'!F9*(1+$A7/Assumptions!F6)+'Income Statement'!F10+'Income Statement'!F13)*0.9-'Income Statement'!F15-'Income Statement'!F16-'Income Statement'!F17-'Income Statement'!F18-'Income Statement'!F19)) -> 2.6172699e+08 | D7: =MAX(0,(('Income Statement'!F9*(1+$A7/Assumptions!F6)+'Income Statement'!F10+'Income Statement'!F13)*1-'Income Statement'!F15-'Income Statement'!F16-'Income Statement'!F17-'Income Statement'!F18-'Income Statement'!F19)*(1-Assumptions!$B$33))+MIN(0,(('Income Statement'!F9*(1+$A7/Assumptions!F6)+'Income Statement'!F10+'Income Statement'!F13)*1-'Income Statement'!F15-'Income Statement'!F16-'Income Statement'!F17-'Income Statement'!F18-'Income Statement'!F19)) -> 3.2690495e+08 | E7: =MAX(0,(('Income Statement'!F9*(1+$A7/Assumptions!F6)+'Income Statement'!F10+'Income Statement'!F13)*1.1-'Income Statement'!F15-'Income Statement'!F16-'Income Statement'!F17-'Income Statement'!F18-'Income Statement'!F19)*(1-Assumptions!$B$33))+MIN(0,(('Income Statement'!F9*(1+$A7/Assumptions!F6)+'Income Statement'!F10+'Income Statement'!F13)*1.1-'Income Statement'!F15-'Income Statement'!F16-'Income Statement'!F17-'Income Statement'!F18-'Income Statement'!F19)) -> 3.920829e+08 | F7: =MAX(0,(('Income Statement'!F9*(1+$A7/Assumptions!F6)+'Income Statement'!F10+'Income Statement'!F13)*1.2-'Income Statement'!F15-'Income Statement'!F16-'Income Statement'!F17-'Income Statement'!F18-'Income Statement'!F19)*(1-Assumptions!$B$33))+MIN(0,(('Income Statement'!F9*(1+$A7/Assumptions!F6)+'Income Statement'!F10+'Income Statement'!F13)*1.2-'Income Statement'!F15-'Income Statement'!F16-'Income Statement'!F17-'Income Statement'!F18-'Income Statement'!F19)) -> 4.5726085e+08
A8: 0.04 | B8: =MAX(0,(('Income Statement'!F9*(1+$A8/Assumptions!F6)+'Income Statement'!F10+'Income Statement'!F13)*0.8-'Income Statement'!F15-'Income Statement'!F16-'Income Statement'!F17-'Income Statement'!F18-'Income Statement'!F19)*(1-Assumptions!$B$33))+MIN(0,(('Income Statement'!F9*(1+$A8/Assumptions!F6)+'Income Statement'!F10+'Income Statement'!F13)*0.8-'Income Statement'!F15-'Income Statement'!F16-'Income Statement'!F17-'Income Statement'!F18-'Income Statement'!F19)) -> 2.2626501e+08 | C8: =MAX(0,(('Income Statement'!F9*(1+$A8/Assumptions!F6)+'Income Statement'!F10+'Income Statement'!F13)*0.9-'Income Statement'!F15-'Income Statement'!F16-'Income Statement'!F17-'Income Statement'!F18-'Income Statement'!F19)*(1-Assumptions!$B$33))+MIN(0,(('Income Statement'!F9*(1+$A8/Assumptions!F6)+'Income Statement'!F10+'Income Statement'!F13)*0.9-'Income Statement'!F15-'Income Statement'!F16-'Income Statement'!F17-'Income Statement'!F18-'Income Statement'!F19)) -> 2.9515746e+08 | D8: =MAX(0,(('Income Statement'!F9*(1+$A8/Assumptions!F6)+'Income Statement'!F10+'Income Statement'!F13)*1-'Income Statement'!F15-'Income Statement'!F16-'Income Statement'!F17-'Income Statement'!F18-'Income Statement'!F19)*(1-Assumptions!$B$33))+MIN(0,(('Income Statement'!F9*(1+$A8/Assumptions!F6)+'Income Statement'!F10+'Income Statement'!F13)*1-'Income Statement'!F15-'Income Statement'!F16-'Income Statement'!F17-'Income Statement'!F18-'Income Statement'!F19)) -> 3.6404991e+08 | E8: =MAX(0,(('Income Statement'!F9*(1+$A8/Assumptions!F6)+'Income Statement'!F10+'Income Statement'!F13)*1.1-'Income Statement'!F15-'Income Statement'!F16-'Income Statement'!F17-'Income Statement'!F18-'Income Statement'!F19)*(1-Assumptions!$B$33))+MIN(0,(('Income Statement'!F9*(1+$A8/Assumptions!F6)+'Income Statement'!F10+'Income Statement'!F13)*1.1-'Income Statement'!F15-'Income Statement'!F16-'Income Statement'!F17-'Income Statement'!F18-'Income Statement'!F19)) -> 4.3294236e+08 | F8: =MAX(0,(('Income Statement'!F9*(1+$A8/Assumptions!F6)+'Income Statement'!F10+'Income Statement'!F13)*1.2-'Income Statement'!F15-'Income Statement'!F16-'Income Statement'!F17-'Income Statement'!F18-'Income Statement'!F19)*(1-Assumptions!$B$33))+MIN(0,(('Income Statement'!F9*(1+$A8/Assumptions!F6)+'Income Statement'!F10+'Income Statement'!F13)*1.2-'Income Statement'!F15-'Income Statement'!F16-'Income Statement'!F17-'Income Statement'!F18-'Income Statement'!F19)) -> 5.0183481e+08
A10: يعرض الجدول أثر تغير عائد العميل ±4 نقاط مئوية وحجم المنح ±20% على صافي ربح السنة الخامسة مع ثبات هيكل التكلفة. يجب إعادة اختبار الرافعة وCAR والسيولة قبل اعتماد أي زيادة في المنح.

Sheet Break Even
A1: تحليل نقطة التعادل
A3: البند | B3: Year 1 | C3: Year 2 | D3: Year 3 | E3: Year 4 | F3: Year 5
A4: هامش المساهمة
A5: عائد العميل على متوسط المحفظة | B5: =Assumptions!B6 -> 0.34 | C5: =Assumptions!C6 -> 0.32 | D5: =Assumptions!D6 -> 0.3 | E5: =Assumptions!E6 -> 0.28 | F5: =Assumptions!F6 -> 0.26
A6: تكلفة التمويل المعدلة بنسبة الدين | B6: =Assumptions!B9*IFERROR(AVERAGE(0,'Balance Sheet'!B14)/AVERAGE(0,'Balance Sheet'!B6),0) -> 0 | C6: =Assumptions!C9*IFERROR(AVERAGE('Balance Sheet'!B14,'Balance Sheet'!C14)/AVERAGE('Balance Sheet'!B6,'Balance Sheet'!C6),0) -> 0.1719932 | D6: =Assumptions!D9*IFERROR(AVERAGE('Balance Sheet'!C14,'Balance Sheet'!D14)/AVERAGE('Balance Sheet'!C6,'Balance Sheet'!D6),0) -> 0.15994984 | E6: =Assumptions!E9*IFERROR(AVERAGE('Balance Sheet'!D14,'Balance Sheet'!E14)/AVERAGE('Balance Sheet'!D6,'Balance Sheet'!E6),0) -> 0.14348866 | F6: =Assumptions!F9*IFERROR(AVERAGE('Balance Sheet'!E14,'Balance Sheet'!F14)/AVERAGE('Balance Sheet'!E6,'Balance Sheet'!F6),0) -> 0.13957106
A7: الخسائر الائتمانية على متوسط المحفظة | B7: =IFERROR('Income Statement'!B16/AVERAGE(0,'Balance Sheet'!B6),0) -> 0.06 | C7: =IFERROR('Income Statement'!C16/AVERAGE('Balance Sheet'!B6,'Balance Sheet'!C6),0) -> 0.054758483 | D7: =IFERROR('Income Statement'!D16/AVERAGE('Balance Sheet'!C6,'Balance Sheet'!D6),0) -> 0.018828254 | E7: =IFERROR('Income Statement'!E16/AVERAGE('Balance Sheet'!D6,'Balance Sheet'!E6),0) -> 0.018963127 | F7: =IFERROR('Income Statement'!F16/AVERAGE('Balance Sheet'!E6,'Balance Sheet'!F6),0) -> 0.018252318
A8: تكلفة خدمة متغيرة | B8: =0.2% -> 0.002 | C8: =0.2% -> 0.002 | D8: =0.2% -> 0.002 | E8: =0.2% -> 0.002 | F8: =0.2% -> 0.002
A9: هامش المساهمة على متوسط المحفظة | B9: =B5-B6-B7-B8 -> 0.278 | C9: =C5-C6-C7-C8 -> 0.091248317 | D9: =D5-D6-D7-D8 -> 0.11922191 | E9: =E5-E6-E7-E8 -> 0.11554821 | F9: =F5-F6-F7-F8 -> 0.10017662
A11: التكاليف الثابتة
A12: تكلفة العاملين | B12: ='Income Statement'!B17 -> 11156112 | C12: ='Income Statement'!C17 -> 15618000 | D12: ='Income Statement'!D17 -> 21893869 | E12: ='Income Statement'!E17 -> 25061090 | F12: ='Income Statement'!F17 -> 30073308
A13: المصروفات الإدارية والتشغيلية (G&A) | B13: ='Income Statement'!B18 -> 4435200 | C13: ='Income Statement'!C18 -> 7413120 | D13: ='Income Statement'!D18 -> 8305440 | E13: ='Income Statement'!E18 -> 12769614 | F13: ='Income Statement'!F18 -> 18043568
A14: الإهلاك والاستهلاك (D&A) | B14: ='Income Statement'!B19 -> 0 | C14: ='Income Statement'!C19 -> 0 | D14: ='Income Statement'!D19 -> 1000000 | E14: ='Income Statement'!E19 -> 1500000 | F14: ='Income Statement'!F19 -> 2000000
A15: إجمالي التكاليف الثابتة | B15: =SUM(B12:B14) -> 15591312 | C15: =SUM(C12:C14) -> 23031120 | D15: =SUM(D12:D14) -> 31199309 | E15: =SUM(E12:E14) -> 39330704 | F15: =SUM(F12:F14) -> 50116876
A17: نقطة التعادل
A18: متوسط المحفظة المطلوب للتعادل | B18: =IFERROR(B15/B9,0) -> 56083856 | C18: =IFERROR(C15/C9,0) -> 2.5240049e+08 | D18: =IFERROR(D15/D9,0) -> 2.6169108e+08 | E18: =IFERROR(E15/E9,0) -> 3.4038349e+08 | F18: =IFERROR(F15/F9,0) -> 5.0028518e+08
A19: المنح السنوي المطلوب للتعادل | B19: =B18/(1-Assumptions!$B$25)*(12/Assumptions!$B$29) -> 26392403 | C19: =C18/(1-Assumptions!$B$25)*(12/Assumptions!$B$29) -> 1.187767e+08 | D19: =D18/(1-Assumptions!$B$25)*(12/Assumptions!$B$29) -> 1.2314874e+08 | E19: =E18/(1-Assumptions!$B$25)*(12/Assumptions!$B$29) -> 1.6018047e+08 | F19: =F18/(1-Assumptions!$B$25)*(12/Assumptions!$B$29) -> 2.3542832e+08
A20: متوسط المحفظة الفعلي | B20: =AVERAGE(0,'Balance Sheet'!B6) -> 10336152 | C20: =AVERAGE('Balance Sheet'!B6,'Balance Sheet'!C6) -> 2.3663726e+08 | D20: =AVERAGE('Balance Sheet'!C6,'Balance Sheet'!D6) -> 6.5958178e+08 | E20: =AVERAGE('Balance Sheet'!D6,'Balance Sheet'!E6) -> 1.2669991e+09 | F20: =AVERAGE('Balance Sheet'!E6,'Balance Sheet'!F6) -> 2.3964494e+09
A21: هامش الأمان | B21: =IFERROR(1-B18/B20,0) -> -4.4259899 | C21: =IFERROR(1-C18/C20,0) -> -0.06661347 | D21: =IFERROR(1-D18/D20,0) -> 0.60324695 | E21: =IFERROR(1-E18/E20,0) -> 0.73134669 | F21: =IFERROR(1-F18/F20,0) -> 0.791239
A22: الحالة | B22: =IF(B20>=B18,"فوق التعادل","دون التعادل") -> دون التعادل | C22: =IF(C20>=C18,"فوق التعادل","دون التعادل") -> دون التعادل | D22: =IF(D20>=D18,"فوق التعادل","دون التعادل") -> فوق التعادل | E22: =IF(E20>=E18,"فوق التعادل","دون التعادل") -> فوق التعادل | F22: =IF(F20>=F18,"فوق التعادل","دون التعادل") -> فوق التعادل

Sheet Compliance
A1: مصفوفة الالتزام والمتطلبات
A3: المتطلب | B3: المعيار | C3: Year 1 | D3: Year 2 | E3: Year 3 | F3: Year 4 | G3: Year 5 | H3: المكان/المنهجية
A4: قائمة الدخل لخمس سنوات | B4: سنوي | C4: مستوفى | D4: مستوفى | E4: مستوفى | F4: مستوفى | G4: مستوفى | H4: Income Statement
A5: قائمة المركز المالي لخمس سنوات | B5: سنوي ومتوازن | C5: مستوفى | D5: مستوفى | E5: مستوفى | F5: مستوفى | G5: مستوفى | H5: Balance Sheet + Checks
A6: قائمة التدفقات النقدية لخمس سنوات | B6: سنوي دون بند موازن | C6: مستوفى | D6: مستوفى | E6: مستوفى | F6: مستوفى | G6: مستوفى | H6: Cash Flow + Checks
A7: حد الاقتراض الرقابي للهيئة - اختبار تخطيطي وفق تاريخ الترخيص المفترض | B7: 4× قبل الترخيص النهائي؛ 9× بعده | C7: ='Regulatory Capital Plan'!B16 -> متوافق | D7: ='Regulatory Capital Plan'!C16 -> فجوة | E7: ='Regulatory Capital Plan'!D16 -> متوافق | F7: ='Regulatory Capital Plan'!E16 -> متوافق | G7: ='Regulatory Capital Plan'!F16 -> متوافق | H7: Regulatory Capital Plan + monthly Year 2 test
A8: كفاية رأس المال CAR | B8: >=12% | C8: =IF('Regulatory Capital Plan'!B31<12%,"فجوة تخطيطية","استرشادي - يتطلب اعتماد المدخلات الرقابية") -> استرشادي - يتطلب اعتماد المدخلات الرقابية | D8: =IF('Regulatory Capital Plan'!C31<12%,"فجوة تخطيطية","استرشادي - يتطلب اعتماد المدخلات الرقابية") -> استرشادي - يتطلب اعتماد المدخلات الرقابية | E8: =IF('Regulatory Capital Plan'!D31<12%,"فجوة تخطيطية","استرشادي - يتطلب اعتماد المدخلات الرقابية") -> استرشادي - يتطلب اعتماد المدخلات الرقابية | F8: =IF('Regulatory Capital Plan'!E31<12%,"فجوة تخطيطية","استرشادي - يتطلب اعتماد المدخلات الرقابية") -> استرشادي - يتطلب اعتماد المدخلات الرقابية | G8: =IF('Regulatory Capital Plan'!F31<12%,"فجوة تخطيطية","استرشادي - يتطلب اعتماد المدخلات الرقابية") -> استرشادي - يتطلب اعتماد المدخلات الرقابية | H8: Regulatory Capital Plan
A9: LCR | B9: >=100% | C9: ='Funding & Liquidity'!B22 -> استرشادي - بيانات آجال تعاقدية مطلوبة | D9: ='Funding & Liquidity'!C22 -> استرشادي - بيانات آجال تعاقدية مطلوبة | E9: ='Funding & Liquidity'!D22 -> استرشادي - بيانات آجال تعاقدية مطلوبة | F9: ='Funding & Liquidity'!E22 -> استرشادي - بيانات آجال تعاقدية مطلوبة | G9: ='Funding & Liquidity'!F22 -> استرشادي - بيانات آجال تعاقدية مطلوبة | H9: Funding & Liquidity
A10: NSFR | B10: >=100% | C10: ='Funding & Liquidity'!B36 -> استرشادي - جداول ASF/RSF الفعلية مطلوبة | D10: ='Funding & Liquidity'!C36 -> استرشادي - جداول ASF/RSF الفعلية مطلوبة | E10: ='Funding & Liquidity'!D36 -> استرشادي - جداول ASF/RSF الفعلية مطلوبة | F10: ='Funding & Liquidity'!E36 -> استرشادي - جداول ASF/RSF الفعلية مطلوبة | G10: ='Funding & Liquidity'!F36 -> استرشادي - جداول ASF/RSF الفعلية مطلوبة | H10: Funding & Liquidity
A11: حد العميل الواحد | B11: <=30% من القاعدة الرأسمالية | C11: ='Regulatory Capital Plan'!B39 -> بيانات معلقة - سجل تركز العملاء/الأطراف المرتبطة مطلوب | D11: ='Regulatory Capital Plan'!C39 -> بيانات معلقة - سجل تركز العملاء/الأطراف المرتبطة مطلوب | E11: ='Regulatory Capital Plan'!D39 -> بيانات معلقة - سجل تركز العملاء/الأطراف المرتبطة مطلوب | F11: ='Regulatory Capital Plan'!E39 -> بيانات معلقة - سجل تركز العملاء/الأطراف المرتبطة مطلوب | G11: ='Regulatory Capital Plan'!F39 -> بيانات معلقة - سجل تركز العملاء/الأطراف المرتبطة مطلوب | H11: Regulatory Capital Plan
A12: حجم المنح الربع سنوي | B12: كل ربع سنة | C12: مستوفى | D12: مستوفى | E12: مستوفى | F12: مستوفى | G12: مستوفى | H12: Originations
A13: مؤشرات الجدوى | B13: NPV, IRR, ARR, Payback, WACC, PI, BEP | C13: مستوفى | D13: مستوفى | E13: مستوفى | F13: مستوفى | G13: مستوفى | H13: Feasibility, Scenarios, Sensitivity, Break Even
A14: مسؤول AML/CFT | B14: وظيفة مستقلة واختصاصات موثقة | C14: مستوفى | D14: مستوفى | E14: مستوفى | F14: مستوفى | G14: مستوفى | H14: Staff rows 23-24
A16: الامتثال المعروض هو امتثال تخطيطي وفق الافتراضات المبينة؛ لا يحل محل الإقرارات والنماذج الرقابية أو تحقق مراقب الحسابات من البيانات الفعلية.

Sheet Checks
A1: اختبارات سلامة النموذج
A3: الاختبار | B3: Year 1 | C3: Year 2 | D3: Year 3 | E3: Year 4 | F3: Year 5
A4: توازن المركز المالي | B4: =IF(ABS('Balance Sheet'!B24)<1,"OK","ERROR") -> OK | C4: =IF(ABS('Balance Sheet'!C24)<1,"OK","ERROR") -> OK | D4: =IF(ABS('Balance Sheet'!D24)<1,"OK","ERROR") -> OK | E4: =IF(ABS('Balance Sheet'!E24)<1,"OK","ERROR") -> OK | F4: =IF(ABS('Balance Sheet'!F24)<1,"OK","ERROR") -> OK
A5: ربط النقدية | B5: =IF(ABS('Cash Flow'!B26)<1,"OK","ERROR") -> OK | C5: =IF(ABS('Cash Flow'!C26)<1,"OK","ERROR") -> OK | D5: =IF(ABS('Cash Flow'!D26)<1,"OK","ERROR") -> OK | E5: =IF(ABS('Cash Flow'!E26)<1,"OK","ERROR") -> OK | F5: =IF(ABS('Cash Flow'!F26)<1,"OK","ERROR") -> OK
A6: المنح السنوي يساوي خطة التشغيل | B6: =IF(ABS('Income Statement'!B5-Assumptions!B4)<1,"OK","ERROR") -> OK | C6: =IF(ABS('Income Statement'!C5-Assumptions!C4)<1,"OK","ERROR") -> OK | D6: =IF(ABS('Income Statement'!D5-Assumptions!D4)<1,"OK","ERROR") -> OK | E6: =IF(ABS('Income Statement'!E5-Assumptions!E4)<1,"OK","ERROR") -> OK | F6: =IF(ABS('Income Statement'!F5-Assumptions!F4)<1,"OK","ERROR") -> OK
A7: المنح الربع سنوي يساوي السنوي | B7: =IF(ABS(SUMIFS(Originations!$B$7:$BI$7,Originations!$B$4:$BI$4,2027)-Assumptions!B4)<1,"OK","ERROR") -> OK | C7: =IF(ABS(SUMIFS(Originations!$B$7:$BI$7,Originations!$B$4:$BI$4,2028)-Assumptions!C4)<1,"OK","ERROR") -> OK | D7: =IF(ABS(SUMIFS(Originations!$B$7:$BI$7,Originations!$B$4:$BI$4,2029)-Assumptions!D4)<1,"OK","ERROR") -> OK | E7: =IF(ABS(SUMIFS(Originations!$B$7:$BI$7,Originations!$B$4:$BI$4,2030)-Assumptions!E4)<1,"OK","ERROR") -> OK | F7: =IF(ABS(SUMIFS(Originations!$B$7:$BI$7,Originations!$B$4:$BI$4,2031)-Assumptions!F4)<1,"OK","ERROR") -> OK
A8: حد الاقتراض الرقابي - اختبار شهري وفق سيناريو الترخيص المتوقع (4× صافي حقوق الملكية / 9× قاعدة رأسمالية تخطيطية) | B8: =IF(COUNTIF('Monthly Model'!B36:M36,"فجوة")=0,"متوافق تخطيطيا","فجوة") -> متوافق تخطيطيا | C8: =IF(COUNTIF('Monthly Model'!N36:Y36,"فجوة")=0,"متوافق تخطيطيا","فجوة") -> فجوة | D8: =IF(COUNTIF('Monthly Model'!Z36:AK36,"فجوة")=0,"متوافق تخطيطيا","فجوة") -> متوافق تخطيطيا | E8: =IF(COUNTIF('Monthly Model'!AL36:AW36,"فجوة")=0,"متوافق تخطيطيا","فجوة") -> متوافق تخطيطيا | F8: =IF(COUNTIF('Monthly Model'!AX36:BI36,"فجوة")=0,"متوافق تخطيطيا","فجوة") -> متوافق تخطيطيا
A9: CAR - تحقق تخطيطي؛ الاعتماد النهائي يتطلب مدخلات رقابية فعلية | B9: =IF('Regulatory Capital Plan'!B31<12%,"فجوة تخطيطية","استرشادي - اعتماد خارجي مطلوب") -> استرشادي - اعتماد خارجي مطلوب | C9: =IF('Regulatory Capital Plan'!C31<12%,"فجوة تخطيطية","استرشادي - اعتماد خارجي مطلوب") -> استرشادي - اعتماد خارجي مطلوب | D9: =IF('Regulatory Capital Plan'!D31<12%,"فجوة تخطيطية","استرشادي - اعتماد خارجي مطلوب") -> استرشادي - اعتماد خارجي مطلوب | E9: =IF('Regulatory Capital Plan'!E31<12%,"فجوة تخطيطية","استرشادي - اعتماد خارجي مطلوب") -> استرشادي - اعتماد خارجي مطلوب | F9: =IF('Regulatory Capital Plan'!F31<12%,"فجوة تخطيطية","استرشادي - اعتماد خارجي مطلوب") -> استرشادي - اعتماد خارجي مطلوب
A10: LCR - Proxy 30 يوما؛ لا PASS نهائي دون آجال تعاقدية | B10: =IF('Funding & Liquidity'!B21<100%,"فجوة تخطيطية","استرشادي - بيانات آجال مطلوبة") -> استرشادي - بيانات آجال مطلوبة | C10: =IF('Funding & Liquidity'!C21<100%,"فجوة تخطيطية","استرشادي - بيانات آجال مطلوبة") -> استرشادي - بيانات آجال مطلوبة | D10: =IF('Funding & Liquidity'!D21<100%,"فجوة تخطيطية","استرشادي - بيانات آجال مطلوبة") -> استرشادي - بيانات آجال مطلوبة | E10: =IF('Funding & Liquidity'!E21<100%,"فجوة تخطيطية","استرشادي - بيانات آجال مطلوبة") -> استرشادي - بيانات آجال مطلوبة | F10: =IF('Funding & Liquidity'!F21<100%,"فجوة تخطيطية","استرشادي - بيانات آجال مطلوبة") -> استرشادي - بيانات آجال مطلوبة
A11: NSFR - Proxy ASF/RSF؛ لا PASS نهائي دون جداول استحقاق فعلية | B11: =IF('Funding & Liquidity'!B35<100%,"فجوة تخطيطية","استرشادي - بيانات آجال مطلوبة") -> استرشادي - بيانات آجال مطلوبة | C11: =IF('Funding & Liquidity'!C35<100%,"فجوة تخطيطية","استرشادي - بيانات آجال مطلوبة") -> استرشادي - بيانات آجال مطلوبة | D11: =IF('Funding & Liquidity'!D35<100%,"فجوة تخطيطية","استرشادي - بيانات آجال مطلوبة") -> استرشادي - بيانات آجال مطلوبة | E11: =IF('Funding & Liquidity'!E35<100%,"فجوة تخطيطية","استرشادي - بيانات آجال مطلوبة") -> استرشادي - بيانات آجال مطلوبة | F11: =IF('Funding & Liquidity'!F35<100%,"فجوة تخطيطية","استرشادي - بيانات آجال مطلوبة") -> استرشادي - بيانات آجال مطلوبة
A12: حد العميل الواحد | B12: ='Regulatory Capital Plan'!B39 -> بيانات معلقة - سجل تركز العملاء/الأطراف المرتبطة مطلوب | C12: ='Regulatory Capital Plan'!C39 -> بيانات معلقة - سجل تركز العملاء/الأطراف المرتبطة مطلوب | D12: ='Regulatory Capital Plan'!D39 -> بيانات معلقة - سجل تركز العملاء/الأطراف المرتبطة مطلوب | E12: ='Regulatory Capital Plan'!E39 -> بيانات معلقة - سجل تركز العملاء/الأطراف المرتبطة مطلوب | F12: ='Regulatory Capital Plan'!F39 -> بيانات معلقة - سجل تركز العملاء/الأطراف المرتبطة مطلوب
A13: رأس المال المدفوع لا يتجاوز المرخص | B13: =IF('Balance Sheet'!B19<=Assumptions!$B$20,"OK","ERROR") -> OK | C13: =IF('Balance Sheet'!C19<=Assumptions!$B$20,"OK","ERROR") -> OK | D13: =IF('Balance Sheet'!D19<=Assumptions!$B$20,"OK","ERROR") -> OK | E13: =IF('Balance Sheet'!E19<=Assumptions!$B$20,"OK","ERROR") -> OK | F13: =IF('Balance Sheet'!F19<=Assumptions!$B$20,"OK","ERROR") -> OK
A14: عدد العاملين يطابق جدول الهيكل | B14: =IF(Staff!C21=36,"OK","ERROR") -> OK | C14: =IF(Staff!D21=36,"OK","ERROR") -> OK | D14: =IF(Staff!E21=36,"OK","ERROR") -> OK | E14: =IF(Staff!F21=36,"OK","ERROR") -> OK | F14: =IF(Staff!G21=36,"OK","ERROR") -> OK
A15: تكلفة العاملين مرتبطة بالقوائم | B15: =IF(AND(ABS(Staff!H21-Staff!H22)<1,ABS('Income Statement'!B17-Staff!H21)<1),"OK","ERROR") -> OK | C15: =IF(AND(ABS(Staff!I21-Staff!I22)<1,ABS('Income Statement'!C17-Staff!I21)<1),"OK","ERROR") -> OK | D15: =IF(AND(ABS(Staff!J21-Staff!J22)<1,ABS('Income Statement'!D17-Staff!J21)<1),"OK","ERROR") -> OK | E15: =IF(AND(ABS(Staff!K21-Staff!K22)<1,ABS('Income Statement'!E17-Staff!K21)<1),"OK","ERROR") -> OK | F15: =IF(AND(ABS(Staff!L21-Staff!L22)<1,ABS('Income Statement'!F17-Staff!L21)<1),"OK","ERROR") -> OK
A16: تسوية حركة الدين البنكي | B16: =IF(ABS(0+'Funding & Liquidity'!B7-'Funding & Liquidity'!B12-'Balance Sheet'!B14)<1,"OK","ERROR") -> OK | C16: =IF(ABS('Balance Sheet'!B14+'Funding & Liquidity'!C7-'Funding & Liquidity'!C12-'Balance Sheet'!C14)<1,"OK","ERROR") -> OK | D16: =IF(ABS('Balance Sheet'!C14+'Funding & Liquidity'!D7-'Funding & Liquidity'!D12-'Balance Sheet'!D14)<1,"OK","ERROR") -> OK | E16: =IF(ABS('Balance Sheet'!D14+'Funding & Liquidity'!E7-'Funding & Liquidity'!E12-'Balance Sheet'!E14)<1,"OK","ERROR") -> OK | F16: =IF(ABS('Balance Sheet'!E14+'Funding & Liquidity'!F7-'Funding & Liquidity'!F12-'Balance Sheet'!F14)<1,"OK","ERROR") -> OK
A17: حد التسهيلات وعدم وجود نقدية سالبة - شهري | B17: =IF(AND(MAX('Monthly Model'!B33:M33)<=Assumptions!B101+1,MIN('Monthly Model'!B27:M27)>=0),"OK","ERROR") -> OK | C17: =IF(AND(MAX('Monthly Model'!N33:Y33)<=Assumptions!C101+1,MIN('Monthly Model'!N27:Y27)>=0),"OK","ERROR") -> OK | D17: =IF(AND(MAX('Monthly Model'!Z33:AK33)<=Assumptions!D101+1,MIN('Monthly Model'!Z27:AK27)>=0),"OK","ERROR") -> OK | E17: =IF(AND(MAX('Monthly Model'!AL33:AW33)<=Assumptions!E101+1,MIN('Monthly Model'!AL27:AW27)>=0),"OK","ERROR") -> OK | F17: =IF(AND(MAX('Monthly Model'!AX33:BI33)<=Assumptions!F101+1,MIN('Monthly Model'!AX27:BI27)>=0),"OK","ERROR") -> OK
A18: نسبة رافعة بازل الاسترشادية (Tier 1 ÷ الانكشافات) | B18: =IF('Basel III'!B54>=3%,"OK - استرشادي","ERROR") -> OK - استرشادي | C18: =IF('Basel III'!C54>=3%,"OK - استرشادي","ERROR") -> OK - استرشادي | D18: =IF('Basel III'!D54>=3%,"OK - استرشادي","ERROR") -> OK - استرشادي | E18: =IF('Basel III'!E54>=3%,"OK - استرشادي","ERROR") -> OK - استرشادي | F18: =IF('Basel III'!F54>=3%,"OK - استرشادي","ERROR") -> OK - استرشادي
A19: حركة مخصص الخسائر الائتمانية تطابق مصروف قائمة الدخل | B19: =IF(ABS('Income Statement'!B16-'Balance Sheet'!B7)<1,"OK","ERROR") -> OK | C19: =IF(ABS('Income Statement'!C16-('Balance Sheet'!C7-'Balance Sheet'!B7))<1,"OK","ERROR") -> OK | D19: =IF(ABS('Income Statement'!D16-('Balance Sheet'!D7-'Balance Sheet'!C7))<1,"OK","ERROR") -> OK | E19: =IF(ABS('Income Statement'!E16-('Balance Sheet'!E7-'Balance Sheet'!D7))<1,"OK","ERROR") -> OK | F19: =IF(ABS('Income Statement'!F16-('Balance Sheet'!F7-'Balance Sheet'!E7))<1,"OK","ERROR") -> OK
A20: ملاحظة: الاختبارات الحسابية يجب أن تكون OK/متوافق؛ المؤشرات الرقابية المعتمدة على بيانات خارجية تبقى استرشادية/معلقة حتى اكتمال المدخلات.
A21: السيناريو الأساسي يطابق صافي ربح قائمة الدخل | B21: =IF(ABS(Scenarios!B13-'Income Statement'!B23)<1,"OK","ERROR") -> OK | C21: =IF(ABS(Scenarios!C13-'Income Statement'!C23)<1,"OK","ERROR") -> OK | D21: =IF(ABS(Scenarios!D13-'Income Statement'!D23)<1,"OK","ERROR") -> OK | E21: =IF(ABS(Scenarios!E13-'Income Statement'!E23)<1,"OK","ERROR") -> OK | F21: =IF(ABS(Scenarios!F13-'Income Statement'!F23)<1,"OK","ERROR") -> OK
A22: نقطة الحساسية الأساسية (0% عائد / 100% منح) تطابق صافي ربح Year 5 | B22: =IF(ABS(Sensitivity!D6-'Income Statement'!F23)<1,"OK","ERROR") -> OK | C22: - | D22: - | E22: - | F22: -
A23: الجدوى: القيمة النهائية مرتبطة بمضاعف الخروج المعتمد | B23: =IF(ABS(Feasibility!G6-('Income Statement'!F23*Assumptions!$B$40))<1,"OK","ERROR") -> OK | C23: - | D23: - | E23: - | F23: -
A24: عوائد التأجير - مصدر ومنهجية | B24: خطة معتمدة/مدخل | C24: خطة معتمدة/مدخل | D24: OK - Formula | E24: OK - Formula | F24: OK - Formula
A25: سداد البنك الشهري يساوي السداد السنوي | B25: =IF(ABS(SUMIFS('Monthly Model'!$B$24:$BI$24,'Monthly Model'!$B$4:$BI$4,2027)-'Funding & Liquidity'!B12)<1,"OK","ERROR") -> OK | C25: =IF(ABS(SUMIFS('Monthly Model'!$B$24:$BI$24,'Monthly Model'!$B$4:$BI$4,2028)-'Funding & Liquidity'!C12)<1,"OK","ERROR") -> OK | D25: =IF(ABS(SUMIFS('Monthly Model'!$B$24:$BI$24,'Monthly Model'!$B$4:$BI$4,2029)-'Funding & Liquidity'!D12)<1,"OK","ERROR") -> OK | E25: =IF(ABS(SUMIFS('Monthly Model'!$B$24:$BI$24,'Monthly Model'!$B$4:$BI$4,2030)-'Funding & Liquidity'!E12)<1,"OK","ERROR") -> OK | F25: =IF(ABS(SUMIFS('Monthly Model'!$B$24:$BI$24,'Monthly Model'!$B$4:$BI$4,2031)-'Funding & Liquidity'!F12)<1,"OK","ERROR") -> OK
A26: تكلفة التمويل الشهرية على متوسط الدين تساوي قائمة الدخل | B26: =IF(ABS(SUMIFS('Monthly Model'!$B$41:$BI$41,'Monthly Model'!$B$4:$BI$4,2027)-'Income Statement'!B15)<1,"OK","ERROR") -> OK | C26: =IF(ABS(SUMIFS('Monthly Model'!$B$41:$BI$41,'Monthly Model'!$B$4:$BI$4,2028)-'Income Statement'!C15)<1,"OK","ERROR") -> OK | D26: =IF(ABS(SUMIFS('Monthly Model'!$B$41:$BI$41,'Monthly Model'!$B$4:$BI$4,2029)-'Income Statement'!D15)<1,"OK","ERROR") -> OK | E26: =IF(ABS(SUMIFS('Monthly Model'!$B$41:$BI$41,'Monthly Model'!$B$4:$BI$4,2030)-'Income Statement'!E15)<1,"OK","ERROR") -> OK | F26: =IF(ABS(SUMIFS('Monthly Model'!$B$41:$BI$41,'Monthly Model'!$B$4:$BI$4,2031)-'Income Statement'!F15)<1,"OK","ERROR") -> OK
A27: خطة السحب البنكي تغطي الحد الأدنى للاحتياج الشهري دون تجاوز التسهيل | B27: =IF(COUNTIF('Monthly Model'!B45:M45,"GAP")=0,"OK","GAP") -> OK | C27: =IF(COUNTIF('Monthly Model'!N45:Y45,"GAP")=0,"OK","GAP") -> OK | D27: =IF(COUNTIF('Monthly Model'!Z45:AK45,"GAP")=0,"OK","GAP") -> OK | E27: =IF(COUNTIF('Monthly Model'!AL45:AW45,"GAP")=0,"OK","GAP") -> OK | F27: =IF(COUNTIF('Monthly Model'!AX45:BI45,"GAP")=0,"OK","GAP") -> OK
A28: عدد العقود الشهري يساوي العدد السنوي المعتمد | B28: =IF(ABS(SUM(Originations!B11:M11)-Assumptions!B77)<0.5,"OK","فجوة") -> OK | C28: =IF(ABS(SUM(Originations!N11:Y11)-Assumptions!C77)<0.5,"OK","فجوة") -> OK | D28: =IF(ABS(SUM(Originations!Z11:AK11)-Assumptions!D77)<0.5,"OK","فجوة") -> OK | E28: =IF(ABS(SUM(Originations!AL11:AW11)-Assumptions!E77)<0.5,"OK","فجوة") -> OK | F28: =IF(ABS(SUM(Originations!AX11:BI11)-Assumptions!F77)<0.5,"OK","فجوة") -> OK
A29: رسوم الخدمات الإدارية = المنح × نسبة الرسوم | B29: =IF(ABS('Cohort Fees'!B6-'Income Statement'!B10)<1,"OK","ERROR") -> OK | C29: =IF(ABS('Cohort Fees'!C6-'Income Statement'!C10)<1,"OK","ERROR") -> OK | D29: =IF(ABS('Cohort Fees'!D6-'Income Statement'!D10)<1,"OK","ERROR") -> OK | E29: =IF(ABS('Cohort Fees'!E6-'Income Statement'!E10)<1,"OK","ERROR") -> OK | F29: =IF(ABS('Cohort Fees'!F6-'Income Statement'!F10)<1,"OK","ERROR") -> OK
A30: إجمالي Opex التفصيلي = المصروف في قائمة الدخل | B30: =IF(ABS(Opex!H19-'Income Statement'!B18)<1,"OK","ERROR") -> OK | C30: =IF(ABS(Opex!I19-'Income Statement'!C18)<1,"OK","ERROR") -> OK | D30: =IF(ABS(Opex!J19-'Income Statement'!D18)<1,"OK","ERROR") -> OK | E30: =IF(ABS(Opex!K19-'Income Statement'!E18)<1,"OK","ERROR") -> OK | F30: =IF(ABS(Opex!L19-'Income Statement'!F18)<1,"OK","ERROR") -> OK

Sheet Sources
A1: المصادر وسجل الافتراضات
A3: ID | B3: الموضوع | C3: المصدر | D3: المرجع | E3: الاستخدام
A4: S01 | B4: قواعد الشركات الناشئة في التكنولوجيا المالية | C4: https://fra.gov.eg/wp-content/uploads/2024/01/alamiria_2023_268.pdf | D4: قرار 268 لسنة 2023 | E4: رأس المال، الرافعة 4×، وشروط الترخيص المبدئي
A5: S02 | B5: كفاية رأس المال والسيولة والتركز | C5: https://fra.gov.eg/wp-content/uploads/2025/08/alamiria_2025_137.pdf | D5: قرار 137 لسنة 2025 | E5: CAR وRWA وLCR وNSFR وحد العميل
A6: S03 | B6: قانون التأجير التمويلي والتخصيم | C6: ملف الهيئة الرسمي | D6: قانون 176 لسنة 2018 | E6: الإطار القانوني للنشاط
A7: F01 | B7: خطة العمل | C7: Flexy business plan v2.5.pdf | D7: ملف الإدارة | E7: القطاعات والتشغيل
A8: F02 | B8: دراسة الجدوى وخطة العمل | C8: دراسة الجدوى وخطة العمل.pdf | D8: ملف الإدارة | E8: الافتراضات التشغيلية والمالية
A9: F03 | B9: الجداول المالية | C9: جداول الدراسة المالية.pdf | D9: أغسطس 2026 | E9: أرقام Year 1 وYear 2 وجدول العاملين وتكاليفه Year 1-Year 5
A10: F04 | B10: السياسة الائتمانية | C10: السياسة الائتمانية.pdf | D10: ملف الإدارة | E10: الضوابط الائتمانية والقطاعات
A11: F05 | B11: مصفوفات الموافقة المبدئية | C11: Flexy_Preliminary_Approval_Matrices.xlsx | D11: ملف الإدارة | E11: الأنظمة والأدوار
A12: F06 | B12: مصروفات التأسيس | C12: FLEXY - Expenses.xlsx | D12: حتى 7 يونيو 2026 | E12: 258,076.28 جنيه
A13: A01 | B13: تكلفة التمويل | C13: افتراض إداري | D13: Year 1-Year 5 | E13: يستبدل بعروض البنوك
A14: A02 | B14: القيمة الاسمية للسهم | C14: افتراض قانوني: 1 جنيه | D14: قبل اعتماد عقد التأسيس | E14: يتطلب تأكيد المستشار
... A25: A13 | B25: الدعم التشغيلي / إيرادات الخدمات المساندة | C25: الجداول المالية القديمة + افتراض الإدارة | D25: Year 1 دعم شركاء 3,118,262.40؛ Year 2 صفر؛ Year 3-Year 5 = 0.8% من المنح | E25: Year 1 يخضع تصنيفه المحاسبي لاعتماد المراجع؛ Year 2 أزيلت قيمة غير مؤيدة؛ السنوات اللاحقة افتراض تخطيطي مشروط بتقديم الخدمة.

Sheet Formula Map
A1: خريطة المعادلات ومنهجية الحساب
A3: البند | B3: المكان | C3: المعادلة | D3: الغرض
A4: المنح السنوي | B4: Assumptions row 4 | C4: مدخل سنوي موزع شهريا وربع سنويا | D4: خطة النمو
A5: الرصيد الختامي للمحفظة | B5: Assumptions row 79 | C5: رصيد سابق × (1-12/المدة) + المنح × (1-المقدم) | D5: تطور المحفظة
A6: عوائد التأجير | B6: Assumptions row 80 | C6: Year 1-Year 2: مدخلات خطة معتمدة؛ Year 3-Year 5: متوسط المحفظة × العائد السنوي | D6: الإيرادات
A7: الرسوم الإدارية | B7: Assumptions row 81 | C7: المنح × نسبة الرسوم السنوية (Year 1=5%، Year 2=7%، ومن Year 3=6%) | D7: إيرادات الخدمات
A8: تكلفة التمويل | B8: Assumptions row 83 | C8: مجموع تكلفة التمويل الشهرية على متوسط رصيد الدين الشهري × معدل الاقتراض السنوي ÷ 12 | D8: تكلفة الدين
A9: التدفق التشغيلي | B9: Cash Flow row 11 | C9: الربح + البنود غير النقدية + تغير المحفظة ورأس المال العامل | D9: السيولة
A10: الرافعة | B10: Regulatory Capital Plan row 13 | C10: قبل الترخيص النهائي: الدين ÷ صافي حقوق الملكية؛ بعده: الدين ÷ القاعدة الرأسمالية التخطيطية بعد الخصومات | D10: 4×/9×
A11: ILDC | B11: Regulatory Capital Plan row 21 | C11: الأقل من |عائد التأجير-تكلفة التمويل| أو 2.25% من متوسط الأصول المدرة | D11: مخاطر التشغيل
A12: SC | B12: Regulatory Capital Plan row 22 | C12: الأكبر من إيرادات الخدمات أو مصروفات العاملين والتشغيل | D12: مخاطر التشغيل
A13: RWA التشغيلي | B13: Regulatory Capital Plan row 28 | C13: BI × معامل الشريحة التخطيطي (الحالة الأساسية حاليا 12%) × ILM × 12.5 | D13: CAR
A14: CAR | B14: Regulatory Capital Plan row 31 | C14: القاعدة الرأسمالية بعد الخصومات ÷ إجمالي RWA | D14: حد أدنى 12%
... A22: تكلفة العاملين | B22: Staff rows 4-21 / Assumptions rows 34, 36, 64-65, 85 | C22: الراتب الأساسي × العدد × 12 × الزيادة السنوية + بند حوافز متغير يكمل موازنة العاملين المعتمدة؛ الصرف الفعلي يخضع لمؤشرات الأداء | D22: مطابقة عدد وتكلفة العاملين

Sheet Regulatory Capital Plan
A1: خطة القاعدة الرأسمالية وكفاية رأس المال
A3: البند | B3: Year 1 | C3: Year 2 | D3: Year 3 | E3: Year 4 | F3: Year 5
A4: رأس المال المدفوع | B4: ='Balance Sheet'!B19 -> 30000000 | C4: ='Balance Sheet'!C19 -> 75000000 | D4: ='Balance Sheet'!D19 -> 75000000 | E4: ='Balance Sheet'!E19 -> 75000000 | F4: ='Balance Sheet'!F19 -> 75000000
A5: الاحتياطي القانوني | B5: ='Balance Sheet'!B20 -> 0 | C5: ='Balance Sheet'!C20 -> 462680.8 | D5: ='Balance Sheet'!D20 -> 4300246.4 | E5: ='Balance Sheet'!E20 -> 12297288 | F5: ='Balance Sheet'!F20 -> 26785287
A6: الأرباح/(الخسائر) المرحلة | B6: ='Balance Sheet'!B21 -> -8166870.8 | C6: ='Balance Sheet'!C21 -> 624064.51 | D6: ='Balance Sheet'!D21 -> 73537811 | E6: ='Balance Sheet'!E21 -> 2.254816e+08 | F6: ='Balance Sheet'!F21 -> 5.0075358e+08
A7: القاعدة الرأسمالية قبل الخصومات | B7: =SUM(B4:B6) -> 21833129 | C7: =SUM(C4:C6) -> 76086745 | D7: =SUM(D4:D6) -> 1.5283806e+08 | E7: =SUM(E4:E6) -> 3.1277889e+08 | F7: =SUM(F4:F6) -> 6.0253887e+08
A8: الأصول غير الملموسة المقدرة | B8: ='Balance Sheet'!B10*60% -> 2581200 | C8: ='Balance Sheet'!C10*60% -> 2881200 | D8: ='Balance Sheet'!D10*60% -> 2881200 | E8: ='Balance Sheet'!E10*60% -> 2881200 | F8: ='Balance Sheet'!F10*60% -> 2881200
A9: الخصومات الرقابية - افتراض متحفظ 100% | B9: =B8 -> 2581200 | C9: =C8 -> 2881200 | D9: =D8 -> 2881200 | E9: =E8 -> 2881200 | F9: =F8 -> 2881200
A10: القاعدة الرأسمالية بعد الخصومات | B10: =B7-B9 -> 19251929 | C10: =C7-C9 -> 73205545 | D10: =D7-D9 -> 1.4995686e+08 | E10: =E7-E9 -> 3.0989769e+08 | F10: =F7-F9 -> 5.9965767e+08
A12: الدين البنكي | B12: ='Balance Sheet'!B14 -> 0 | C12: ='Balance Sheet'!C14 -> 370000000 | D12: ='Balance Sheet'!D14 -> 685000000 | E12: ='Balance Sheet'!E14 -> 1335000000 | F12: ='Balance Sheet'!F14 -> 2600000000
A13: الرافعة المالية (المقام: صافي حقوق الملكية قبل خصومات CAR في مرحلة 4x؛ القاعدة الرأسمالية بعد الخصومات في مرحلة 9x) | B13: =IFERROR(B12/IF(B14=9,B10,B7),0) -> 0 | C13: =IFERROR(C12/IF(C14=9,C10,C7),0) -> 4.8628706 | D13: =IFERROR(D12/IF(D14=9,D10,D7),0) -> 4.5679805 | E13: =IFERROR(E12/IF(E14=9,E10,E7),0) -> 4.3078733 | F13: =IFERROR(F12/IF(F14=9,F10,F7),0) -> 4.3358071
A14: السقف التنظيمي المتوقع في نهاية السنة حسب خطة الترخيص | B14: =Assumptions!B51 -> 4 | C14: =Assumptions!C51 -> 4 | D14: =Assumptions!D51 -> 9 | E14: =Assumptions!E51 -> 9 | F14: =Assumptions!F51 -> 9
A15: هامش الرافعة | B15: =B14-B13 -> 4 | C15: =C14-C13 -> -0.86287064 | D15: =D14-D13 -> 4.4320195 | E15: =E14-E13 -> 4.6921267 | F15: =F14-F13 -> 4.6641929
A16: حالة الرافعة في السيناريو المتوقع | B16: =IF(B13<=B14,"متوافق","فجوة") -> متوافق | C16: =IF(C13<=C14,"متوافق","فجوة") -> فجوة | D16: =IF(D13<=D14,"متوافق","فجوة") -> متوافق | E16: =IF(E13<=E14,"متوافق","فجوة") -> متوافق | F16: =IF(F13<=F14,"متوافق","فجوة") -> متوافق
A18: الأصول المرجحة بالمخاطر
A19: RWA الائتماني - صافي محفظة التأجير 100% | B19: ='Balance Sheet'!B8 -> 20052135 | C19: ='Balance Sheet'!C8 -> 4.3902415e+08 | D19: ='Balance Sheet'!D8 -> 8.4056449e+08 | E19: ='Balance Sheet'!E8 -> 1.6174137e+09 | F19: ='Balance Sheet'!F8 -> 3.0316982e+09
A20: RWA أصول تشغيلية أخرى 100% | B20: ='Balance Sheet'!B9+'Balance Sheet'!B10 -> 4560076.3 | C20: ='Balance Sheet'!C9+'Balance Sheet'!C10 -> 5060076.3 | D20: ='Balance Sheet'!D9+'Balance Sheet'!D10 -> 5060076.3 | E20: ='Balance Sheet'!E9+'Balance Sheet'!E10 -> 5060076.3 | F20: ='Balance Sheet'!F9+'Balance Sheet'!F10 -> 5060076.3
A21: ILDC: الأقل من مجمل الربح أو 2.25% من متوسط الأصول المدرة | B21: =MIN(ABS('Income Statement'!B9-'Income Statement'!B15),2.25%*AVERAGE(0,'Balance Sheet'!B8)) -> 225586.52 | C21: =MIN(ABS('Income Statement'!C9-'Income Statement'!C15),2.25%*AVERAGE('Balance Sheet'!B8,'Balance Sheet'!C8)) -> 5164608.2 | D21: =MIN(ABS('Income Statement'!D9-'Income Statement'!D15),2.25%*AVERAGE('Balance Sheet'!C8,'Balance Sheet'!D8)) -> 14395372 | E21: =MIN(ABS('Income Statement'!E9-'Income Statement'!E15),2.25%*AVERAGE('Balance Sheet'!D8,'Balance Sheet'!E8)) -> 27652255 | F21: =MIN(ABS('Income Statement'!F9-'Income Statement'!F15),2.25%*AVERAGE('Balance Sheet'!E8,'Balance Sheet'!F8)) -> 52302509
A22: SC: الأكبر من إيرادات الخدمات أو المصروفات التشغيلية | B22: =MAX('Income Statement'!B10+'Income Statement'!B13,'Income Statement'!B17+'Income Statement'!B18) -> 15591312 | C22: =MAX('Income Statement'!C10+'Income Statement'!C13,'Income Statement'!C17+'Income Statement'!C18) -> 36925000 | D22: =MAX('Income Statement'!D10+'Income Statement'!D13,'Income Statement'!D17+'Income Statement'!D18) -> 47600000 | E22: =MAX('Income Statement'!E10+'Income Statement'!E13,'Income Statement'!E17+'Income Statement'!E18) -> 91800000 | F22: =MAX('Income Statement'!F10+'Income Statement'!F13,'Income Statement'!F17+'Income Statement'!F18) -> 170000000
A23: FC: المكون المالي | B23: =0 -> 0 | C23: =0 -> 0 | D23: =0 -> 0 | E23: =0 -> 0 | F23: =0 -> 0
A24: مؤشر الأعمال BI | B24: =SUM(B21:B23) -> 15816899 | C24: =SUM(C21:C23) -> 42089608 | D24: =SUM(D21:D23) -> 61995372 | E24: =SUM(E21:E23) -> 1.1945225e+08 | F24: =SUM(F21:F23) -> 2.2230251e+08
A25: معامل BI المستخدم في الحالة الأساسية - مشتق من شريحة BI التخطيطية (راجع Basel III صف 96) | B25: ='Basel III'!B96 -> 0.12 | C25: ='Basel III'!C96 -> 0.12 | D25: ='Basel III'!D96 -> 0.12 | E25: ='Basel III'!E96 -> 0.12 | F25: ='Basel III'!F96 -> 0.12
A26: مضاعف الخسارة الداخلية - افتراض | B26: =1 -> 1 | C26: =1 -> 1 | D26: =1 -> 1 | E26: =1 -> 1 | F26: =1 -> 1
A27: مضاعف التحويل إلى RWA | B27: =Assumptions!B97 -> 12.5 | C27: =Assumptions!C97 -> 12.5 | D27: =Assumptions!D97 -> 12.5 | E27: =Assumptions!E97 -> 12.5 | F27: =Assumptions!F97 -> 12.5
A28: RWA مخاطر التشغيل | B28: =B24*B25*B26*B27 -> 23725348 | C28: =C24*C25*C26*C27 -> 63134412 | D28: =D24*D25*D26*D27 -> 92993058 | E28: =E24*E25*E26*E27 -> 1.7917838e+08 | F28: =F24*F25*F26*F27 -> 3.3345376e+08
A29: RWA مخاطر السوق | B29: =0 -> 0 | C29: =0 -> 0 | D29: =0 -> 0 | E29: =0 -> 0 | F29: =0 -> 0
A30: إجمالي RWA | B30: =SUM(B19:B20,B28:B29) -> 48337559 | C30: =SUM(C19:C20,C28:C29) -> 5.0721864e+08 | D30: =SUM(D19:D20,D28:D29) -> 9.3861763e+08 | E30: =SUM(E19:E20,E28:E29) -> 1.8016522e+09 | F30: =SUM(F19:F20,F28:F29) -> 3.3702121e+09
A31: كفاية رأس المال CAR - تقدير تخطيطي | B31: =IFERROR(B10/B30,0) -> 0.39828096 | C31: =IFERROR(C10/C30,0) -> 0.14432739 | D31: =IFERROR(D10/D30,0) -> 0.15976352 | E31: =IFERROR(E10/E30,0) -> 0.1720075 | F31: =IFERROR(F10/F30,0) -> 0.17792877
A32: الحد الأدنى | B32: =Assumptions!B95 -> 0.12 | C32: =Assumptions!C95 -> 0.12 | D32: =Assumptions!D95 -> 0.12 | E32: =Assumptions!E95 -> 0.12 | F32: =Assumptions!F95 -> 0.12
A33: فائض/(فجوة) رأس المال | B33: =B10-B30*B32 -> 13451422 | C33: =C10-C30*C32 -> 12339308 | D33: =D10-D30*D32 -> 37322742 | E33: =E10-E30*E32 -> 93699433 | F33: =F10-F30*F32 -> 1.9523222e+08
A34: حالة CAR الرقابية النهائية | B34: استرشادي - يتطلب اعتماد سجل الأصول/الخصومات ومعامل BI/ILM وبيانات السوق | C34: استرشادي - يتطلب اعتماد سجل الأصول/الخصومات ومعامل BI/ILM وبيانات السوق | D34: استرشادي - يتطلب اعتماد سجل الأصول/الخصومات ومعامل BI/ILM وبيانات السوق | E34: استرشادي - يتطلب اعتماد سجل الأصول/الخصومات ومعامل BI/ILM وبيانات السوق | F34: استرشادي - يتطلب اعتماد سجل الأصول/الخصومات ومعامل BI/ILM وبيانات السوق
A35: التركز الائتماني
A36: حد العميل الواحد والأطراف المرتبطة 30% | B36: =B10*30% -> 5775578.8 | C36: =C10*30% -> 21961664 | D36: =D10*30% -> 44987057 | E36: =E10*30% -> 92969307 | F36: =F10*30% -> 1.798973e+08
A37: حد داخلي استرشادي 25% من القاعدة الرأسمالية | B37: =B10*25% -> 4812982.3 | C37: =C10*25% -> 18301386 | D37: =D10*25% -> 37489214 | E37: =E10*25% -> 77474423 | F37: =F10*25% -> 1.4991442e+08
A38: أكبر تعرض فعلي لعميل/أطراف مرتبطة | B38: بيانات تشغيلية مطلوبة | C38: بيانات تشغيلية مطلوبة | D38: بيانات تشغيلية مطلوبة | E38: بيانات تشغيلية مطلوبة | F38: بيانات تشغيلية مطلوبة
A39: حالة التركز - اختبار 30% | B39: =IF(ISNUMBER(B38),IF(B38<=B36,"متوافق","فجوة"),"بيانات معلقة - سجل تركز العملاء/الأطراف المرتبطة مطلوب") -> بيانات معلقة - سجل تركز العملاء/الأطراف المرتبطة مطلوب | C39: =IF(ISNUMBER(C38),IF(C38<=C36,"متوافق","فجوة"),"بيانات معلقة - سجل تركز العملاء/الأطراف المرتبطة مطلوب") -> بيانات معلقة - سجل تركز العملاء/الأطراف المرتبطة مطلوب | D39: =IF(ISNUMBER(D38),IF(D38<=D36,"متوافق","فجوة"),"بيانات معلقة - سجل تركز العملاء/الأطراف المرتبطة مطلوب") -> بيانات معلقة - سجل تركز العملاء/الأطراف المرتبطة مطلوب | E39: =IF(ISNUMBER(E38),IF(E38<=E36,"متوافق","فجوة"),"بيانات معلقة - سجل تركز العملاء/الأطراف المرتبطة مطلوب") -> بيانات معلقة - سجل تركز العملاء/الأطراف المرتبطة مطلوب | F39: =IF(ISNUMBER(F38),IF(F38<=F36,"متوافق","فجوة"),"بيانات معلقة - سجل تركز العملاء/الأطراف المرتبطة مطلوب") -> بيانات معلقة - سجل تركز العملاء/الأطراف المرتبطة مطلوب
A41: افتراضات رقابية تخطيطية: وزن 100% لصافي محفظة التأجير والأصول التشغيلية؛ الخصم الحالي للأصول غير الملموسة Proxy مؤقت لحين سجل الأصول؛ معامل BI مشتق من شريحة BI التخطيطية في Basel III مع حساسية 15%/18%؛ ILM=1 مؤقتا لعدم وجود سجل خسائر؛ وRWA السوقية = صفر فقط مع افتراض عدم وجود محفظة تداول. لذلك CAR استرشادي وليس إقرار امتثال نهائيا.
A43: شرائح رأس المال التنظيمي واحتياطيات رأس المال (وفق قرار 137/2025)
A44: البند | B44: Year 1 | C44: Year 2 | D44: Year 3 | E44: Year 4 | F44: Year 5
A45: الشريحة الأولى الأساسية CET1 (= القاعدة بعد الخصومات؛ لا توجد أدوات AT1 مؤهلة) | B45: =B10 -> 19251929 | C45: =C10 -> 73205545 | D45: =D10 -> 1.4995686e+08 | E45: =E10 -> 3.0989769e+08 | F45: =F10 -> 5.9965767e+08
A46: + الشريحة الأولى الإضافية AT1 (لا توجد أدوات مؤهلة حاليا) | B46: 0 | C46: 0 | D46: 0 | E46: 0 | F46: 0
A47: إجمالي الشريحة الأولى | B47: =B45+B46 -> 19251929 | C47: =C45+C46 -> 73205545 | D47: =D45+D46 -> 1.4995686e+08 | E47: =E45+E46 -> 3.0989769e+08 | F47: =F45+F46 -> 5.9965767e+08
A48: + الشريحة الثانية Tier 2 (دين تابع مؤهل - غير موجود حاليا) | B48: =Assumptions!B55 -> 0 | C48: =Assumptions!C55 -> 0 | D48: =Assumptions!D55 -> 0 | E48: =Assumptions!E55 -> 0 | F48: =Assumptions!F55 -> 0
A49: إجمالي القاعدة الرأسمالية التنظيمية | B49: =B47+B48 -> 19251929 | C49: =C47+C48 -> 73205545 | D49: =D47+D48 -> 1.4995686e+08 | E49: =E47+E48 -> 3.0989769e+08 | F49: =F47+F48 -> 5.9965767e+08
A50: نسبة الشريحة الأولى الأساسية CET1 | B50: =IFERROR(B45/B30,0) -> 0.39828096 | C50: =IFERROR(C45/C30,0) -> 0.14432739 | D50: =IFERROR(D45/D30,0) -> 0.15976352 | E50: =IFERROR(E45/E30,0) -> 0.1720075 | F50: =IFERROR(F45/F30,0) -> 0.17792877
A51: نسبة الشريحة الأولى Tier 1 | B51: =IFERROR(B47/B30,0) -> 0.39828096 | C51: =IFERROR(C47/C30,0) -> 0.14432739 | D51: =IFERROR(D47/D30,0) -> 0.15976352 | E51: =IFERROR(E47/E30,0) -> 0.1720075 | F51: =IFERROR(F47/F30,0) -> 0.17792877
A52: كفاية رأس المال الإجمالية CAR (تكرار من الصف 31 للمقارنة) | B52: =B31 -> 0.39828096 | C52: =C31 -> 0.14432739 | D52: =D31 -> 0.15976352 | E52: =E31 -> 0.1720075 | F52: =F31 -> 0.17792877
A53: الحد الأدنى الأساسي (Pillar 1) | B53: =B32 -> 0.12 | C53: =C32 -> 0.12 | D53: =D32 -> 0.12 | E53: =E32 -> 0.12 | F53: =F32 -> 0.12
A54: + احتياطي حماية رأس المال 2.5% | B54: 0.025 | C54: 0.025 | D54: 0.025 | E54: 0.025 | F54: 0.025
A55: + الاحتياطي المعاكس للدورة الاقتصادية (0%-2.5%، يحدده مجلس إدارة الهيئة - لم يصدر تحديد بعد) | B55: 0 | C55: 0 | D55: 0 | E55: 0 | F55: 0
A56: الحد الأدنى الشامل للاحتياطيات | B56: =B53+B54+B55 -> 0.145 | C56: =C53+C54+C55 -> 0.145 | D56: =D53+D54+D55 -> 0.145 | E56: =E53+E54+E55 -> 0.145 | F56: =F53+F54+F55 -> 0.145
A57: هامش/(فجوة) فوق الحد الشامل للاحتياطيات | B57: =B52-B56 -> 0.25328096 | C57: =C52-C56 -> -0.00067260504 | D57: =D52-D56 -> 0.014763521 | E57: =E52-E56 -> 0.027007505 | F57: =F52-F56 -> 0.032928766
A58: الحالة الشاملة للاحتياطيات - استرشادية | B58: =IF(B57>=0,"متوافق استرشاديا","فجوة استرشادية") -> متوافق استرشاديا | C58: =IF(C57>=0,"متوافق استرشاديا","فجوة استرشادية") -> فجوة استرشادية | D58: =IF(D57>=0,"متوافق استرشاديا","فجوة استرشادية") -> متوافق استرشاديا | E58: =IF(E57>=0,"متوافق استرشاديا","فجوة استرشادية") -> متوافق استرشاديا | F58: =IF(F57>=0,"متوافق استرشاديا","فجوة استرشادية") -> متوافق استرشاديا
A60: ملاحظة: قرار 137/2025 يميز بين الشريحة الأولى (الأساسية) والشريحة الثانية (المساندة) واحتياطي حماية رأس المال 2.5% واحتياطي معاكس للدورة الاقتصادية 0%-2.5%؛ لا توجد لدى Flexy أدوات شريحة أولى إضافية (AT1) أو شريحة ثانية مؤهلة حاليا، فالشريحة الأولى الأساسية تساوي إجمالي رأس المال بعد الخصومات. قيمة الاحتياطي المعاكس للدورة الاقتصادية الفعلية تحددها الهيئة دوريا ولم تصدر بعد؛ استخدمت صفر مؤقتا.
A62: جدول خصم الأصول غير الملموسة التفصيلي (بانتظار سجل الأصول الثابتة المعتمد)
A63: الفئة | B63: Year 1 | C63: Year 2 | D63: Year 3 | E63: Year 4 | F63: Year 5
A64: أجهزة وأثاث — ملموس، غير مقتطع | B64: 0 | C64: 0 | D64: 0 | E64: 0 | F64: 0
A65: برمجيات جاهزة (تراخيص استخدام) — غير ملموس، يقتطع | B65: 0 | C65: 0 | D65: 0 | E65: 0 | F65: 0
A66: تطوير المنصة (برمجة داخلية/خارجية) — غير ملموس، يقتطع | B66: 0 | C66: 0 | D66: 0 | E66: 0 | F66: 0
A67: التراخيص والتصاريح — غير ملموس، يقتطع | B67: 0 | C67: 0 | D67: 0 | E67: 0 | F67: 0
A68: مصروفات التأسيس — غير ملموس، يقتطع ما لم يعتمد خلاف ذلك | B68: 0 | C68: 0 | D68: 0 | E68: 0 | F68: 0
A69: ملاحظة: بانتظار سجل الأصول الثابتة وغير الملموسة المعتمد وتأكيد مراقب الحسابات، يفترض النموذج مؤقتا أن 60% من صافي الأصول الثابتة/غير الملموسة تمثل أصولا غير ملموسة، ثم يخصم هذا الرصيد المقدر بالكامل بصورة متحفظة لأغراض CAR. هذا أكثر تحفظا من جدول الخصم الانتقالي الوارد بالقرار 137/2025، وسيستبدل بالتفصيل الفعلي ونسبة الخصم القانونية لكل فئة عند اعتماد سجل الأصول. Pending fixed-asset register and auditor validation.
A70: أصول ملموسة أخرى — ملموس، غير مقتطع | B70: 0 | C70: 0 | D70: 0 | E70: 0 | F70: 0
A71: إجمالي الخصم التفصيلي (يستكمل عند توافر السجل) | B71: =SUM(B64:B70) -> 0 | C71: =SUM(C64:C70) -> 0 | D71: =SUM(D64:D70) -> 0 | E71: =SUM(E64:E70) -> 0 | F71: =SUM(F64:F70) -> 0
A72: ملاحظة: بانتظار سجل الأصول الثابتة والاستثمارات المعتمد وتأكيد مراقب الحسابات، يستمر النموذج باستخدام الافتراض المتحفظ الحالي (خصم 60% من صافي الأصول الثابتة وغير الملموسة إجمالا - الصفوف 8-9 أعلاه) بدلا من هذا التفصيل الصفري مؤقتا؛ يجب استبدال هذا الافتراض بالتفصيل الفعلي عند اعتماد السجل وإعادة احتساب القاعدة الرأسمالية. Pending fixed-asset register and auditor validation.
A74: قياس معالجة فجوة سقف الاقتراض (خفض الدين أو زيادة القاعدة الرأسمالية)
A75: البند | B75: Year 1 | C75: Year 2 | D75: Year 3 | E75: Year 4 | F75: Year 5
A76: خفض الدين المطلوب للالتزام بالسقف الساري = MAX(0، الدين القائم - السقف الساري × المقام الصحيح لكل مرحلة) | B76: =MAX(0,B12-B14*IF(B14=9,B10,B7)) -> 0 | C76: =MAX(0,C12-C14*IF(C14=9,C10,C7)) -> 65653019 | D76: =MAX(0,D12-D14*IF(D14=9,D10,D7)) -> 0 | E76: =MAX(0,E12-E14*IF(E14=9,E10,E7)) -> 0 | F76: =MAX(0,F12-F14*IF(F14=9,F10,F7)) -> 0
A77: الزيادة المطلوبة في القاعدة الرأسمالية بديلا عن خفض الدين = MAX(0، الدين القائم ÷ السقف الساري - المقام الصحيح لكل مرحلة) | B77: =MAX(0,B12/B14-IF(B14=9,B10,B7)) -> 0 | C77: =MAX(0,C12/C14-IF(C14=9,C10,C7)) -> 16413255 | D77: =MAX(0,D12/D14-IF(D14=9,D10,D7)) -> 0 | E77: =MAX(0,E12/E14-IF(E14=9,E10,E7)) -> 0 | F77: =MAX(0,F12/F14-IF(F14=9,F10,F7)) -> 0
A78: ملاحظة: القيمتان أعلاه بديلتان لبعضهما (تنفيذ أي منهما كاف لإغلاق فجوة الرافعة في السنة المعنية)، وتحسبان بالسقف الساري الفعلي لكل سنة (4× افتراضيا حتى تأكيد صدور الترخيص النهائي فعليا، أو 9× بعده) وليس برقم ثابت. راجع أيضا ورقتي Scenario - Slower Year 2 وScenario - Standby Capital كأداتين عمليتين لتنفيذ أي من الخيارين.

Sheet Funding & Liquidity
A1: خطة التمويل والسيولة
A3: البند | B3: Year 1 | C3: Year 2 | D3: Year 3 | E3: Year 4 | F3: Year 5
A4: مصادر التمويل وتكلفته
A5: حد التسهيلات البنكية | B5: =Assumptions!B101 -> 0 | C5: =Assumptions!C101 -> 420000000 | D5: =Assumptions!D101 -> 850000000 | E5: =Assumptions!E101 -> 1600000000 | F5: =Assumptions!F101 -> 3000000000
A6: رصيد الدين الختامي | B6: ='Balance Sheet'!B14 -> 0 | C6: ='Balance Sheet'!C14 -> 370000000 | D6: ='Balance Sheet'!D14 -> 685000000 | E6: ='Balance Sheet'!E14 -> 1335000000 | F6: ='Balance Sheet'!F14 -> 2600000000
A7: السحوبات البنكية الإجمالية | B7: =B14+B12 -> 0 | C7: =C14+C12 -> 4.4167756e+08 | D7: =D14+D12 -> 607500000 | E7: =E14+E12 -> 1265000000 | F7: =F14+F12 -> 2427500000
A8: تكلفة الاقتراض | B8: =Assumptions!B9 -> 0.24 | C8: =Assumptions!C9 -> 0.22 | D8: =Assumptions!D9 -> 0.2 | E8: =Assumptions!E9 -> 0.18 | F8: =Assumptions!F9 -> 0.17
A9: العمر المرجح - سنة | B9: =3 -> 3 | C9: =3 -> 3 | D9: =3 -> 3 | E9: =3 -> 3 | F9: =3 -> 3
A10: نسبة تسهيل دوار | B10: =1-Assumptions!B102 -> 0.2 | C10: =1-Assumptions!C102 -> 0.15 | D10: =1-Assumptions!D102 -> 0.1 | E10: =1-Assumptions!E102 -> 0.1 | F10: =1-Assumptions!F102 -> 0.1
A11: نسبة تمويل متوسط الأجل | B11: =Assumptions!B102 -> 0.8 | C11: =Assumptions!C102 -> 0.85 | D11: =Assumptions!D102 -> 0.9 | E11: =Assumptions!E102 -> 0.9 | F11: =Assumptions!F102 -> 0.9
A12: سداد التمويل البنكي | B12: =IF(B6<=0,0,Assumptions!B78*Assumptions!$B$32) -> 0 | C12: =IF(C6<=0,0,Assumptions!C78*Assumptions!$B$32) -> 71677563 | D12: =IF(D6<=0,0,Assumptions!D78*Assumptions!$B$32) -> 292500000 | E12: =IF(E6<=0,0,Assumptions!E78*Assumptions!$B$32) -> 615000000 | F12: =IF(F6<=0,0,Assumptions!F78*Assumptions!$B$32) -> 1162500000
A13: خدمة الدين السنوية | B13: =B12+'Income Statement'!B15 -> 0 | C13: =C12+'Income Statement'!C15 -> 1.0891806e+08 | D13: =D12+'Income Statement'!D15 -> 395322500 | E13: =E12+'Income Statement'!E15 -> 791827500 | F13: =F12+'Income Statement'!F15 -> 1487835375
A14: صافي السحب/(السداد) البنكي | B14: =B6 -> 0 | C14: =C6-B6 -> 370000000 | D14: =D6-C6 -> 315000000 | E14: =E6-D6 -> 650000000 | F14: =F6-E6 -> 1265000000
A15: اختبار تغطية السيولة لمدة 30 يوما
A16: الأصول السائلة عالية الجودة | B16: ='Balance Sheet'!B5 -> 3220918 | C16: ='Balance Sheet'!C5 -> 9502515.4 | D16: ='Balance Sheet'!D5 -> 13213489 | E16: ='Balance Sheet'!E5 -> 65805120 | F16: ='Balance Sheet'!F5 -> 2.4078058e+08
A17: تدفقات نقدية خارجة خلال 30 يوما | B17: =('Income Statement'!B17+'Income Statement'!B18+'Income Statement'!B15)/12+B12/12+'Balance Sheet'!B14*(1-Assumptions!B102)*10% -> 1299276 | C17: =('Income Statement'!C17+'Income Statement'!C18+'Income Statement'!C15)/12+C12/12+'Balance Sheet'!C14*(1-Assumptions!C102)*10% -> 16545765 | D17: =('Income Statement'!D17+'Income Statement'!D18+'Income Statement'!D15)/12+D12/12+'Balance Sheet'!D14*(1-Assumptions!D102)*10% -> 42310151 | E17: =('Income Statement'!E17+'Income Statement'!E18+'Income Statement'!E15)/12+E12/12+'Balance Sheet'!E14*(1-Assumptions!E102)*10% -> 82488184 | F17: =('Income Statement'!F17+'Income Statement'!F18+'Income Statement'!F15)/12+F12/12+'Balance Sheet'!F14*(1-Assumptions!F102)*10% -> 1.5399602e+08
A18: تدفقات نقدية داخلة خلال 30 يوما | B18: =Assumptions!B78/12 -> 589807.99 | C18: =Assumptions!C78/12 -> 7964173.7 | D18: =Assumptions!D78/12 -> 32500000 | E18: =Assumptions!E78/12 -> 68333333 | F18: =Assumptions!F78/12 -> 1.2916667e+08
A19: الحد الأقصى للاعتداد بالتدفقات الداخلة 90% (وفق النص النهائي لقرار 137/2025) | B19: =B17*90% -> 1169348.4 | C19: =C17*90% -> 14891189 | D19: =D17*90% -> 38079136 | E19: =E17*90% -> 74239365 | F19: =F17*90% -> 1.3859642e+08
A20: صافي التدفقات الخارجة | B20: =MAX(1,B17-MIN(B18,B19)) -> 709468.01 | C20: =MAX(1,C17-MIN(C18,C19)) -> 8581591.6 | D20: =MAX(1,D17-MIN(D18,D19)) -> 9810150.8 | E20: =MAX(1,E17-MIN(E18,E19)) -> 14154850 | F20: =MAX(1,F17-MIN(F18,F19)) -> 24829354
A21: نسبة تغطية السيولة LCR - تقدير 30 يوما تخطيطي | B21: =B16/B20 -> 4.5399059 | C21: =C16/C20 -> 1.1073139 | D21: =D16/D20 -> 1.34692 | E21: =E16/E20 -> 4.6489449 | F21: =F16/F20 -> 9.697416
